Workbook
Name Siema2024: #REF!
Name Siema2025: 'Siema 2025'!$1:$1048576

Sheet Siema 2025
A1: 1 - Número de Registro | B1: 2 - Data do Incidente | C1: 3 - Município | D1: 4 - UF | E1: 5 - Origem | F1: 6 - Tipo de Evento | G1: 7 - Produtos ONU | H1: 8 - Qtd. Produtos ONU | I1: 9 - Unidade Produtos ONU | J1: 10 - Outros Produtos | K1: 11 - Qtd. Outros Produtos | L1: 12 - Unidade Outros Produtos | M1: 13 - Ocorrências/Ambientes Atingidos | N1: 14 - Inst. Atuando no Local | O1: 15 - Fontes de Informação | P1: 16 - Dia da Semana | Q1: 17 - Período | R1: 18 - Feriado | S1: 19 - Bacia Sedimentar | T1: 20 - Endereço da Ocorrência | U1: 21 - Origem do Acidente - Informações Complementares | V1: 22 - Tipo de evento - Informações Complementares | W1: 23 - Produto perigoso | X1: 24 - Produto não se aplica | Y1: 25 - Produto não especificado | Z1: 26 - Causa provável do acidente | AA1: 27 - Ambientes atingidos - Informações Complementares | AB1: 28 - Identificação da Empresa - Nome | AC1: 29 - Identificação da Empresa - CPF/CNPJ | AD1: 30 - Identificação da Empresa -Licença Ambiental | AE1: 31 - Instituição Atuando - Informações complementares | AF1: 32 - Instituição Atuando - Nome responsável | AG1: 33 - Instituição Atuando - Telefone responsável | AH1: 34 - Ações Tomadas - Possui Plano de Emergência | AI1: 35 - Ações Tomadas - Plano de Emergência acionado | AJ1: 36 - Ações Tomadas - Tomado outras providências | AK1: 37 - Ações Tomadas - Descrição de providências tomadas | AL1: 38 - Informações Gerais - Informações julgadas úteis | AM1: 39 - Identificação Comunicante - Nome | AN1: 40 - Identificação Comunicante - Instituição/Empresa | AO1: 41 - Identificação Comunicante - Cargo/Função Navio/Instalação | AP1: 42 - Identificação Comunicante - Telefone | AQ1: 43 - Identificação Comunicante - E-mail | AR1: 44 - Fonte Informação - Descrição fonte | AS1: 45 - Origem Acidente - Nome do navio | AT1: 46 - Origem Acidente - Nome da instalação | AU1: 47 - Tipo de Produto - Tipo de substância | AV1: 48 - Tipo de Produto - Volume estimado | AW1: 49 - Detalhes acidente - Situação atual da descarga | AX1: 50 Óbitos/ feridos | AY1: 51 Óbitos/ feridos (X) | AZ1: 52 População afetada/evacuada | BA1: 53 População afetada/evacuada (x) | BB1: 54 Suspensão de abastecimento de água | BC1: 55 Suspensão de abastecimento de água (X) | BD1: 56 Rio/ córrego | BE1: 57 Rio/ córrego (X) | BF1: 58 Lago | BG1: 59 Lago (X) | BH1: 60 Mar | BI1: 61 Mar (X) | BJ1: 62 Praia | BK1: 63 Praia (X) | BL1: 64 Solo | BM1: 65 Solo (x) | BN1: 66 Águas subterrâneas | BO1: 67 Águas subterrâneas (X) | BP1: 68 Atmosfera | BQ1: 69 Atmosfera (X) | BR1: 70 Flora | BS1: 71 Flora (X) | BT1: 72 Fauna | BU1: 73 Fauna(X) | BV1: 74 UC Federal | BW1: 75 UC Federal (x) | BX1: 76 UC estadual/ municipal | BY1: 77 UC estadual/ municipal (x) | BZ1: 78 Outro(s) | CA1: 79 Outro(s) (x) | CB1: 80 Sem dano | CC1: 81 Sem dano (x) | CD1: 82 Sem Informação | CE1: 83 IBAMA | CF1: 84 IBAMA (X) | CG1: 85 OEMA | CH1: 86 OEMA (X) | CI1: 87 DEFESA CIVIL | CJ1: 88 DEFESA CIVIL (X) | CK1: 89 CORPO DE BOMBEIROS | CL1: 90 CORPO DE BOMBEIROS (X) | CM1: 91 POLÍCIA RODOVIÁRIA | CN1: 92 POLÍCIA RODOVIÁRIA (X) | CO1: 93 POLÍCIA MILITAR | CP1: 94 POLÍCIA MILITAR (X) | CQ1: 95 POLÍCIA CIVIL | CR1: 96 POLÍCIA CIVIL (X) | CS1: 97 MARINHA DO BRASIL | CT1: 98 MARINHA DO BRASIL (X) | CU1: 99 EMPRESA ESPECIALIZADA EM ATENDIMENTO | CV1: 100 EMPRESA ESPECIALIZADA EM ATENDIMENTO (X) | CW1: 101 EQUIPE DA PRÓPRIA EMPRESA | CX1: 102 EQUIPE DA PRÓPRIA EMPRESA (X) | CY1: 103 SEM INFORMAÇÃO (X) | CZ1: 104 OUTRA (S) | DA1: 105 OUTRA(S) (X) | DB1: 106 Ações Tomadas - Possui Plano de Emergência2 | DC1: 107 Ações Tomadas - Plano de Emergência acionado 2 | DD1: 108 Ações Tomadas - Tomado outras providências2 | DE1: 109 Identificação da Empresa -Licença Ambiental2
A2: 20251246819 | B2: 45658 | C2: null | D2: null | E2: Plataforma | F2: Derramamento de líquidos | J2: Fluido Hidraulico | K2: 0.0022 | L2: M3 | M2: Mar | N2: Outra(s) | O2: Outra(s) fonte(s) | P2: Quarta | Q2: Vespertino | R2: Não | S2: Santos | T2: Campo de Mero - Bacia de Santos | U2: Durante operação de recolhimento do cabo mensageiro do hauser, foi observado uma perda de contenção de aproximadamente 0,0022 m3 de fluido hidráulico (MOBIL DTE 10 EXCEL 32) na conexão flangeada da tubulação hidráulica do sistema de offloading da unidade, resultando na descarga do fluido para o mar. | V2: FLUIDO HIDRÁULICO - 0,0022m³ | Z2: Falha da junta de vedação de conexão hidráulica. Em investigação. | AB2: PETROBRAS | AC2: 33000167000292 | AD2: 1 | AE2: PETROBRAS | AH2: S | AI2: N | AJ2: S | AK2: Paralisação e despressurização do sistema hidráulico, cessando o vazamento imediatamente. Mobilizado embarcação oil rec para varredura (feição não encontrada). | AL2: Processo sei nº #{23565508|02001.000070/2025-40} (Emergência Ambiental: Acidente Ambiental)# [1] Volume descarregado: 0,0022 m³ de fluido hidráulico base óleo; [2] Nome comercial do produto: MOBIL DTE 10 EXCEL 32; [3] Composição química: Destilados (petróleo), parafínicos pesados, tratados com hidrogénio; destilados (petróleo), parafínicos pesados, desparafinados com solventes; [4] Classificação ONU ou IMDG: Não regulado; [5] Ambiente atingido: Mar. | AM2: PETRLEO BRASILEIRO S/A - PETROBRAS | AQ2: giselletinoco@petrobras.com.br | AX2: =IFERROR(FIND("Óbitos/feridos",consulta_completa__11[[#This Row],[13 - Ocorrências/Ambientes Atingidos]]),0) -> 0 | AY2: =IF(AX2=0,"","X") | AZ2: =IFERROR(FIND("População afetada/evacuada",consulta_completa__11[[#This Row],[13 - Ocorrências/Ambientes Atingidos]]),0) -> 0 | BA2: =IF(AZ2=0,"","X") | BB2: =IFERROR(FIND("Suspensão de abastecimento de água",consulta_completa__11[[#This Row],[13 - Ocorrências/Ambientes Atingidos]]),0) -> 0 | BC2: =IF(BB2=0,"","X") | BD2: =IFERROR(FIND("Rio/córrego",consulta_completa__11[[#This Row],[13 - Ocorrências/Ambientes Atingidos]]),0) -> 0 | BE2: =IF(BD2=0,"","X") | BF2: =IFERROR(FIND("Lago",consulta_completa__11[[#This Row],[13 - Ocorrências/Ambientes Atingidos]]),0) -> 0 | BG2: =IF(BF2=0,"","X") | BH2: =IFERROR(FIND("Mar",consulta_completa__11[[#This Row],[13 - Ocorrências/Ambientes Atingidos]]),0) -> 1 | BI2: =IF(BH2=0,"","X") -> X | BJ2: =IFERROR(FIND("Praia",consulta_completa__11[[#This Row],[13 - Ocorrências/Ambientes Atingidos]]),0) -> 0 | BK2: =IF(BJ2=0,"","X") | BL2: =IFERROR(FIND("Solo",consulta_completa__11[[#This Row],[13 - Ocorrências/Ambientes Atingidos]]),0) -> 0 | BM2: =IF(BL2=0,"","X") | BN2: =IFERROR(FIND("Águas subterrâneas",consulta_completa__11[[#This Row],[13 - Ocorrências/Ambientes Atingidos]]),0) -> 0 | BO2: =IF(BN2=0,"","X") | BP2: =IFERROR(FIND("Atmosfera",consulta_completa__11[[#This Row],[13 - Ocorrências/Ambientes Atingidos]]),0) -> 0 | BQ2: =IF(BP2=0,"","X") | BR2: =IFERROR(FIND("Flora",consulta_completa__11[[#This Row],[13 - Ocorrências/Ambientes Atingidos]]),0) -> 0 | BS2: =IF(BR2=0,"","X") | BT2: =IFERROR(FIND("Fauna",consulta_completa__11[[#This Row],[13 - Ocorrências/Ambientes Atingidos]]),0) -> 0 | BU2: =IF(BT2=0,"","X") | BV2: =IFERROR(FIND("UC federal",consulta_completa__11[[#This Row],[13 - Ocorrências/Ambientes Atingidos]]),0) -> 0 | BW2: =IF(BV2=0,"","X") | BX2: =IFERROR(FIND("UC estadual/municipal",consulta_completa__11[[#This Row],[13 - Ocorrências/Ambientes Atingidos]]),0) -> 0 | BY2: =IF(BX2=0,"","X") | BZ2: =IFERROR(FIND("Outro(s)",consulta_completa__11[[#This Row],[13 - Ocorrências/Ambientes Atingidos]]),0) -> 0 | CA2: =IF(BZ2=0,"","X") | CB2: =IFERROR(FIND("Sem dano",consulta_completa__11[[#This Row],[13 - Ocorrências/Ambientes Atingidos]]),0) -> 0 | CC2: =IF(CB2=0,"","X") | CD2: =IF(consulta_completa__11[[#This Row],[13 - Ocorrências/Ambientes Atingidos]]="","X","") | CE2: =IFERROR(FIND("IBAMA",consulta_completa__11[[#This Row],[14 - Inst. Atuando no Local]]),0) -> 0 | CF2: =IF(CE2=0,"","X") | CG2: =IFERROR(FIND("OEMA",consulta_completa__11[[#This Row],[14 - Inst. Atuando no Local]]),0) -> 0 | CH2: =IF(CG2=0,"","X") | CI2: =IFERROR(FIND("DEFESA CIVIL",consulta_completa__11[[#This Row],[14 - Inst. Atuando no Local]]),0) -> 0 | CJ2: =IF(CI2=0,"","X") | CK2: =IFERROR(FIND("CORPO DE BOMBEIROS",consulta_completa__11[[#This Row],[14 - Inst. Atuando no Local]]),0) -> 0 | CL2: =IF(CK2=0,"","X") | CM2: =IFERROR(FIND("POLÍCIA RODOVIÁRIA",consulta_completa__11[[#This Row],[14 - Inst. Atuando no Local]]),0) -> 0 | CN2: =IF(CM2=0,"","X") | CO2: =IFERROR(FIND("POLÍCIA MILITAR",consulta_completa__11[[#This Row],[14 - Inst. Atuando no Local]]),0) -> 0 | CP2: =IF(CO2=0,"","X") | CQ2: =IFERROR(FIND("POLÍCIA CIVIL",consulta_completa__11[[#This Row],[14 - Inst. Atuando no Local]]),0) -> 0 | CR2: =IF(CQ2=0,"","X") | CS2: =IFERROR(FIND("MARINHA DO BRASIL",consulta_completa__11[[#This Row],[14 - Inst. Atuando no Local]]),0) -> 0 | CT2: =IF(CS2=0,"","X") | CU2: =IFERROR(FIND("EMPRESA ESPECIALIZADA EM ATENDIMENTO",consulta_completa__11[[#This Row],[14 - Inst. Atuando no Local]]),0) -> 0 | CV2: =IF(CU2=0,"","X") | CW2: =IFERROR(FIND("IBAMA",consulta_completa__11[[#This Row],[14 - Inst. Atuando no Local]]),0) -> 0 | CX2: =IF(CW2=0,"","X") | CY2: =IF(consulta_completa__11[[#This Row],[14 - Inst. Atuando no Local]]="","X","") | CZ2: =IFERROR(FIND("OUTRA (S)",consulta_completa__11[[#This Row],[14 - Inst. Atuando no Local]]),0) -> 0 | DA2: =IF(CZ2=0,"","X") | DB2: =IF(AH$2="","",IF(AH$2="S","Sim",IF(AH$2="N","Não", IF(AH$2="I","Sem Informação")))) -> Sim | DC2: =IF(AI$2="","",IF(AI$2="S","Sim",IF(AI$2="N","Não", IF(AI$2="I","Sem Informação")))) -> Não | DD2: =IF(AJ$2="","",IF(AJ$2="S","Sim",IF(AJ$2="N","Não", IF(AJ$2="I","Sem Informação")))) -> Sim | DE2: =IF(AD2=1,"Federal",IF(AD2=2,"Estadual",IF(AD2=0,"Sem informação",""))) -> Federal
A3: 20251336008 | B3: 45659 | C3: Governador Dix Sept Rosado | D3: RN | E3: Outro(s) | F3: Outro(s) | M3: Solo | N3: Empresa especializada em atendimento | P3: Quinta | Q3: Matutino | R3: Não | T3: : Locação do poço 7-LOR-38-RN (72100019088), Campo Lorena, Bacia Potiguar | U3: Poço terrestre | V3: No dia 02/01/2025, por volta das 10h10, durante o último estágio do bombeio do Fraturamento, no 7-LOR-38-RN, identificou-se um vazamento no ponto de amostragem de gel. Tentou-se realizar a contenção do fluído, porém como não houve êxito, seguiu-se com o deslocamento e paralisação da operação. | Y3: TRUE | Z3: Furo em válvula de amostragem. | AB3: Potiguar E&P | AD3: 2 | AF3: : Jéssica Luisa Santos da Silva | AG3: 71991321907 | AH3: S | AI3: S | AJ3: S | AK3: Operação paralisada, realizada as devidas comunicações internas, e acionado a equipe de limpeza. | AL3: Processo sei nº 02001.000180/2025-10 (Emergência Ambiental: Acidente Ambiental) 1) 0,72m³. 2) Solo. 3) a 4) N/A. 7) e 8) [aguardando equipe operacional, será retificado]. 4) a 11)N/A. | Volume da perda de contenção: 0,72m³. Metodologia de cálculo = área x lâmina: (36m² x 0,02m) = 0,72m³. | AM3: Jeanei Rodrigues Dos Santos | AN3: Ibama | AO3: Técnico Administrativo | AP3: 61999572720 | AQ3: jeanei.santos@ibama.gov.br | AT3: 7-LOR-38-RN | AU3: Fluidos de perfuração completação a base d'agua | AV3: 7200000000 | AW3: Paralisada | AX3: =IFERROR(FIND("Óbitos/feridos",consulta_completa__11[[#This Row],[13 - Ocorrências/Ambientes Atingidos]]),0) -> 0 | AY3: =IF(AX3=0,"","X") | AZ3: =IFERROR(FIND("População afetada/evacuada",consulta_completa__11[[#This Row],[13 - Ocorrências/Ambientes Atingidos]]),0) -> 0 | BA3: =IF(AZ3=0,"","X") | BB3: =IFERROR(FIND("Suspensão de abastecimento de água",consulta_completa__11[[#This Row],[13 - Ocorrências/Ambientes Atingidos]]),0) -> 0 | BC3: =IF(BB3=0,"","X") | BD3: =IFERROR(FIND("Rio/córrego",consulta_completa__11[[#This Row],[13 - Ocorrências/Ambientes Atingidos]]),0) -> 0 | BE3: =IF(BD3=0,"","X") | BF3: =IFERROR(FIND("Lago",consulta_completa__11[[#This Row],[13 - Ocorrências/Ambientes Atingidos]]),0) -> 0 | BG3: =IF(BF3=0,"","X") | BH3: =IFERROR(FIND("Mar",consulta_completa__11[[#This Row],[13 - Ocorrências/Ambientes Atingidos]]),0) -> 0 | BI3: =IF(BH3=0,"","X") | BJ3: =IFERROR(FIND("Praia",consulta_completa__11[[#This Row],[13 - Ocorrências/Ambientes Atingidos]]),0) -> 0 | BK3: =IF(BJ3=0,"","X") | BL3: =IFERROR(FIND("Solo",consulta_completa__11[[#This Row],[13 - Ocorrências/Ambientes Atingidos]]),0) -> 1 | BM3: =IF(BL3=0,"","X") -> X | BN3: =IFERROR(FIND("Águas subterrâneas",consulta_completa__11[[#This Row],[13 - Ocorrências/Ambientes Atingidos]]),0) -> 0 | BO3: =IF(BN3=0,"","X") | BP3: =IFERROR(FIND("Atmosfera",consulta_completa__11[[#This Row],[13 - Ocorrências/Ambientes Atingidos]]),0) -> 0 | BQ3: =IF(BP3=0,"","X") | BR3: =IFERROR(FIND("Flora",consulta_completa__11[[#This Row],[13 - Ocorrências/Ambientes Atingidos]]),0) -> 0 | BS3: =IF(BR3=0,"","X") | BT3: =IFERROR(FIND("Fauna",consulta_completa__11[[#This Row],[13 - Ocorrências/Ambientes Atingidos]]),0) -> 0 | BU3: =IF(BT3=0,"","X") | BV3: =IFERROR(FIND("UC federal",consulta_completa__11[[#This Row],[13 - Ocorrências/Ambientes Atingidos]]),0) -> 0 | BW3: =IF(BV3=0,"","X") | BX3: =IFERROR(FIND("UC estadual/municipal",consulta_completa__11[[#This Row],[13 - Ocorrências/Ambientes Atingidos]]),0) -> 0 | BY3: =IF(BX3=0,"","X") | BZ3: =IFERROR(FIND("Outro(s)",consulta_completa__11[[#This Row],[13 - Ocorrências/Ambientes Atingidos]]),0) -> 0 | CA3: =IF(BZ3=0,"","X") | CB3: =IFERROR(FIND("Sem dano",consulta_completa__11[[#This Row],[13 - Ocorrências/Ambientes Atingidos]]),0) -> 0 | CC3: =IF(CB3=0,"","X") | CD3: =IF(consulta_completa__11[[#This Row],[13 - Ocorrências/Ambientes Atingidos]]="","X","") | CE3: =IFERROR(FIND("IBAMA",consulta_completa__11[[#This Row],[14 - Inst. Atuando no Local]]),0) -> 0 | CF3: =IF(CE3=0,"","X") | CG3: =IFERROR(FIND("OEMA",consulta_completa__11[[#This Row],[14 - Inst. Atuando no Local]]),0) -> 0 | CH3: =IF(CG3=0,"","X") | CI3: =IFERROR(FIND("DEFESA CIVIL",consulta_completa__11[[#This Row],[14 - Inst. Atuando no Local]]),0) -> 0 | CJ3: =IF(CI3=0,"","X") | CK3: =IFERROR(FIND("CORPO DE BOMBEIROS",consulta_completa__11[[#This Row],[14 - Inst. Atuando no Local]]),0) -> 0 | CL3: =IF(CK3=0,"","X") | CM3: =IFERROR(FIND("POLÍCIA RODOVIÁRIA",consulta_completa__11[[#This Row],[14 - Inst. Atuando no Local]]),0) -> 0 | CN3: =IF(CM3=0,"","X") | CO3: =IFERROR(FIND("POLÍCIA MILITAR",consulta_completa__11[[#This Row],[14 - Inst. Atuando no Local]]),0) -> 0 | CP3: =IF(CO3=0,"","X") | CQ3: =IFERROR(FIND("POLÍCIA CIVIL",consulta_completa__11[[#This Row],[14 - Inst. Atuando no Local]]),0) -> 0 | CR3: =IF(CQ3=0,"","X") | CS3: =IFERROR(FIND("MARINHA DO BRASIL",consulta_completa__11[[#This Row],[14 - Inst. Atuando no Local]]),0) -> 0 | CT3: =IF(CS3=0,"","X") | CU3: =IFERROR(FIND("EMPRESA ESPECIALIZADA EM ATENDIMENTO",consulta_completa__11[[#This Row],[14 - Inst. Atuando no Local]]),0) -> 0 | CV3: =IF(CU3=0,"","X") | CW3: =IFERROR(FIND("IBAMA",consulta_completa__11[[#This Row],[14 - Inst. Atuando no Local]]),0) -> 0 | CX3: =IF(CW3=0,"","X") | CY3: =IF(consulta_completa__11[[#This Row],[14 - Inst. Atuando no Local]]="","X","") | CZ3: =IFERROR(FIND("OUTRA (S)",consulta_completa__11[[#This Row],[14 - Inst. Atuando no Local]]),0) -> 0 | DA3: =IF(CZ3=0,"","X") | DB3: =IF(AH$2="","",IF(AH$2="S","Sim",IF(AH$2="N","Não", IF(AH$2="I","Sem Informação")))) -> Sim | DC3: =IF(AI$2="","",IF(AI$2="S","Sim",IF(AI$2="N","Não", IF(AI$2="I","Sem Informação")))) -> Não | DD3: =IF(AJ$2="","",IF(AJ$2="S","Sim",IF(AJ$2="N","Não", IF(AJ$2="I","Sem Informação")))) -> Sim | DE3: =IF(AD3=1,"Federal",IF(AD3=2,"Estadual",IF(AD3=0,"Sem informação",""))) -> Estadual
A4: 20251336012 | B4: 45659 | C4: Cubatão | D4: SP | E4: Ferrovia | F4: Lançamento de sólidos | J4: Cloreto de Potássio | K4: 4 | L4: T | M4: Solo | N4: Outra(s) | O4: Outra(s) fonte(s) | P4: Quinta | Q4: Noturno | R4: Não | U4: Vandalismo na ferrovia com abertura de bicas em vagão graneleiro carregado fertilizante. | V4: Vandalismo com abertura de vagão graneleiro carregado com Fertilizante (Cloreto de Potassio). Lançamento de 4 toneladas de fertilizante granular sobre a linha férrea | Z4: Ato criminoso caracterizado pela abertura de bicas em vagão graneleiro ferroviário carregado com fertilizante granular. | AA4: Solo dentro dos limites da área de domínio da via férrea. | AB4: Rumo Logistica S. A. | AC4: 02502844000166 | AD4: 1 | AE4: Equipes de atendimento de limpeza, contratadas pela Rumo, atuando no trecho afetado. | AH4: S | AI4: N | AJ4: S | AK4: Equipes de atendimento emergêncial de limpeza, contratadas pela rumo, e de segurança patrimonial, atuando no trecho afetado para remoção do material, liberação da via e garantia da segurança dos trabalhadores. | AM4: Eloisa Caxias Coelho | AN4: Rumo Logistica S. A. | AO4: Auditor Ambiental | AP4: 41988207121 | AQ4: eloisa.coelho@rumolog.com | AX4: =IFERROR(FIND("Óbitos/feridos",consulta_completa__11[[#This Row],[13 - Ocorrências/Ambientes Atingidos]]),0) -> 0 | AY4: =IF(AX4=0,"","X") | AZ4: =IFERROR(FIND("População afetada/evacuada",consulta_completa__11[[#This Row],[13 - Ocorrências/Ambientes Atingidos]]),0) -> 0 | BA4: =IF(AZ4=0,"","X") | BB4: =IFERROR(FIND("Suspensão de abastecimento de água",consulta_completa__11[[#This Row],[13 - Ocorrências/Ambientes Atingidos]]),0) -> 0 | BC4: =IF(BB4=0,"","X") | BD4: =IFERROR(FIND("Rio/córrego",consulta_completa__11[[#This Row],[13 - Ocorrências/Ambientes Atingidos]]),0) -> 0 | BE4: =IF(BD4=0,"","X") | BF4: =IFERROR(FIND("Lago",consulta_completa__11[[#This Row],[13 - Ocorrências/Ambientes Atingidos]]),0) -> 0 | BG4: =IF(BF4=0,"","X") | BH4: =IFERROR(FIND("Mar",consulta_completa__11[[#This Row],[13 - Ocorrências/Ambientes Atingidos]]),0) -> 0 | BI4: =IF(BH4=0,"","X") | BJ4: =IFERROR(FIND("Praia",consulta_completa__11[[#This Row],[13 - Ocorrências/Ambientes Atingidos]]),0) -> 0 | BK4: =IF(BJ4=0,"","X") | BL4: =IFERROR(FIND("Solo",consulta_completa__11[[#This Row],[13 - Ocorrências/Ambientes Atingidos]]),0) -> 1 | BM4: =IF(BL4=0,"","X") -> X | BN4: =IFERROR(FIND("Águas subterrâneas",consulta_completa__11[[#This Row],[13 - Ocorrências/Ambientes Atingidos]]),0) -> 0 | BO4: =IF(BN4=0,"","X") | BP4: =IFERROR(FIND("Atmosfera",consulta_completa__11[[#This Row],[13 - Ocorrências/Ambientes Atingidos]]),0) -> 0 | BQ4: =IF(BP4=0,"","X") | BR4: =IFERROR(FIND("Flora",consulta_completa__11[[#This Row],[13 - Ocorrências/Ambientes Atingidos]]),0) -> 0 | BS4: =IF(BR4=0,"","X") | BT4: =IFERROR(FIND("Fauna",consulta_completa__11[[#This Row],[13 - Ocorrências/Ambientes Atingidos]]),0) -> 0 | BU4: =IF(BT4=0,"","X") | BV4: =IFERROR(FIND("UC federal",consulta_completa__11[[#This Row],[13 - Ocorrências/Ambientes Atingidos]]),0) -> 0 | BW4: =IF(BV4=0,"","X") | BX4: =IFERROR(FIND("UC estadual/municipal",consulta_completa__11[[#This Row],[13 - Ocorrências/Ambientes Atingidos]]),0) -> 0 | BY4: =IF(BX4=0,"","X") | BZ4: =IFERROR(FIND("Outro(s)",consulta_completa__11[[#This Row],[13 - Ocorrências/Ambientes Atingidos]]),0) -> 0 | CA4: =IF(BZ4=0,"","X") | CB4: =IFERROR(FIND("Sem dano",consulta_completa__11[[#This Row],[13 - Ocorrências/Ambientes Atingidos]]),0) -> 0 | CC4: =IF(CB4=0,"","X") | CD4: =IF(consulta_completa__11[[#This Row],[13 - Ocorrências/Ambientes Atingidos]]="","X","") | CE4: =IFERROR(FIND("IBAMA",consulta_completa__11[[#This Row],[14 - Inst. Atuando no Local]]),0) -> 0 | CF4: =IF(CE4=0,"","X") | CG4: =IFERROR(FIND("OEMA",consulta_completa__11[[#This Row],[14 - Inst. Atuando no Local]]),0) -> 0 | CH4: =IF(CG4=0,"","X") | CI4: =IFERROR(FIND("DEFESA CIVIL",consulta_completa__11[[#This Row],[14 - Inst. Atuando no Local]]),0) -> 0 | CJ4: =IF(CI4=0,"","X") | CK4: =IFERROR(FIND("CORPO DE BOMBEIROS",consulta_completa__11[[#This Row],[14 - Inst. Atuando no Local]]),0) -> 0 | CL4: =IF(CK4=0,"","X") | CM4: =IFERROR(FIND("POLÍCIA RODOVIÁRIA",consulta_completa__11[[#This Row],[14 - Inst. Atuando no Local]]),0) -> 0 | CN4: =IF(CM4=0,"","X") | CO4: =IFERROR(FIND("POLÍCIA MILITAR",consulta_completa__11[[#This Row],[14 - Inst. Atuando no Local]]),0) -> 0 | CP4: =IF(CO4=0,"","X") | CQ4: =IFERROR(FIND("POLÍCIA CIVIL",consulta_completa__11[[#This Row],[14 - Inst. Atuando no Local]]),0) -> 0 | CR4: =IF(CQ4=0,"","X") | CS4: =IFERROR(FIND("MARINHA DO BRASIL",consulta_completa__11[[#This Row],[14 - Inst. Atuando no Local]]),0) -> 0 | CT4: =IF(CS4=0,"","X") | CU4: =IFERROR(FIND("EMPRESA ESPECIALIZADA EM ATENDIMENTO",consulta_completa__11[[#This Row],[14 - Inst. Atuando no Local]]),0) -> 0 | CV4: =IF(CU4=0,"","X") | CW4: =IFERROR(FIND("IBAMA",consulta_completa__11[[#This Row],[14 - Inst. Atuando no Local]]),0) -> 0 | CX4: =IF(CW4=0,"","X") | CY4: =IF(consulta_completa__11[[#This Row],[14 - Inst. Atuando no Local]]="","X","") | CZ4: =IFERROR(FIND("OUTRA (S)",consulta_completa__11[[#This Row],[14 - Inst. Atuando no Local]]),0) -> 0 | DA4: =IF(CZ4=0,"","X") | DB4: =IF(AH$2="","",IF(AH$2="S","Sim",IF(AH$2="N","Não", IF(AH$2="I","Sem Informação")))) -> Sim | DC4: =IF(AI$2="","",IF(AI$2="S","Sim",IF(AI$2="N","Não", IF(AI$2="I","Sem Informação")))) -> Não | DD4: =IF(AJ$2="","",IF(AJ$2="S","Sim",IF(AJ$2="N","Não", IF(AJ$2="I","Sem Informação")))) -> Sim | DE4: =IF(AD4=1,"Federal",IF(AD4=2,"Estadual",IF(AD4=0,"Sem informação",""))) -> Federal
A5: 20252525226 | B5: 45659 | C5: Betim | D5: MG | E5: Indústria | F5: Vazamento de gases | G5: AMÔNIA, ANIDRA | M5: Outro(s) | N5: Outra(s); Corpo de Bombeiros | O5: Órgão Estadual ou Municipal de Meio Ambiente | P5: Quinta | Q5: Noturno | R5: Não | T5: Av. Nova York, 94 - Capelinha | U5: Conforme relatado ao NEA, houve o vazamento de gás amônia, na Sala de Máquinas, decorrente do rompimento de selo mecânico de uma bomba responsável pelo bombeamento de amônia. O frigorífico foi completamente evacuado e segundo informações, não houve vítimas. Houve o fechamento das válvulas das tubulações de alimentação das bombas bem como substituição da bomba afetada. As ações contaram com atuação da brigada interna e do Corpo de Bombeiros. | V5: Vazamento de gás amônia | Z5: Rompimento de selo mecânico de uma bomba | AA5: Ambiente do empreendimento. | AB5: GRANJA BRASILIA AGROINDUSTRIAL AVICOLA LTDA | AC5: 07150233001000 | AD5: 2 | AE5: Brigada interna | AH5: I | AI5: N | AJ5: S | AK5: O frigorífico foi completamente evacuado e segundo informações, não houve vítimas. Houve o fechamento das válvulas das tubulações de alimentação das bombas bem como substituição da bomba afetada. A | AM5: Cleiton Lopes Ribeiro | AQ5: cleiton.ribeiro@ibama.gov.br | AX5: =IFERROR(FIND("Óbitos/feridos",consulta_completa__11[[#This Row],[13 - Ocorrências/Ambientes Atingidos]]),0) -> 0 | AY5: =IF(AX5=0,"","X") | AZ5: =IFERROR(FIND("População afetada/evacuada",consulta_completa__11[[#This Row],[13 - Ocorrências/Ambientes Atingidos]]),0) -> 0 | BA5: =IF(AZ5=0,"","X") | BB5: =IFERROR(FIND("Suspensão de abastecimento de água",consulta_completa__11[[#This Row],[13 - Ocorrências/Ambientes Atingidos]]),0) -> 0 | BC5: =IF(BB5=0,"","X") | BD5: =IFERROR(FIND("Rio/córrego",consulta_completa__11[[#This Row],[13 - Ocorrências/Ambientes Atingidos]]),0) -> 0 | BE5: =IF(BD5=0,"","X") | BF5: =IFERROR(FIND("Lago",consulta_completa__11[[#This Row],[13 - Ocorrências/Ambientes Atingidos]]),0) -> 0 | BG5: =IF(BF5=0,"","X") | BH5: =IFERROR(FIND("Mar",consulta_completa__11[[#This Row],[13 - Ocorrências/Ambientes Atingidos]]),0) -> 0 | BI5: =IF(BH5=0,"","X") | BJ5: =IFERROR(FIND("Praia",consulta_completa__11[[#This Row],[13 - Ocorrências/Ambientes Atingidos]]),0) -> 0 | BK5: =IF(BJ5=0,"","X") | BL5: =IFERROR(FIND("Solo",consulta_completa__11[[#This Row],[13 - Ocorrências/Ambientes Atingidos]]),0) -> 0 | BM5: =IF(BL5=0,"","X") | BN5: =IFERROR(FIND("Águas subterrâneas",consulta_completa__11[[#This Row],[13 - Ocorrências/Ambientes Atingidos]]),0) -> 0 | BO5: =IF(BN5=0,"","X") | BP5: =IFERROR(FIND("Atmosfera",consulta_completa__11[[#This Row],[13 - Ocorrências/Ambientes Atingidos]]),0) -> 0 | BQ5: =IF(BP5=0,"","X") | BR5: =IFERROR(FIND("Flora",consulta_completa__11[[#This Row],[13 - Ocorrências/Ambientes Atingidos]]),0) -> 0 | BS5: =IF(BR5=0,"","X") | BT5: =IFERROR(FIND("Fauna",consulta_completa__11[[#This Row],[13 - Ocorrências/Ambientes Atingidos]]),0) -> 0 | BU5: =IF(BT5=0,"","X") | BV5: =IFERROR(FIND("UC federal",consulta_completa__11[[#This Row],[13 - Ocorrências/Ambientes Atingidos]]),0) -> 0 | BW5: =IF(BV5=0,"","X") | BX5: =IFERROR(FIND("UC estadual/municipal",consulta_completa__11[[#This Row],[13 - Ocorrências/Ambientes Atingidos]]),0) -> 0 | BY5: =IF(BX5=0,"","X") | BZ5: =IFERROR(FIND("Outro(s)",consulta_completa__11[[#This Row],[13 - Ocorrências/Ambientes Atingidos]]),0) -> 1 | CA5: =IF(BZ5=0,"","X") -> X | CB5: =IFERROR(FIND("Sem dano",consulta_completa__11[[#This Row],[13 - Ocorrências/Ambientes Atingidos]]),0) -> 0 | CC5: =IF(CB5=0,"","X") | CD5: =IF(consulta_completa__11[[#This Row],[13 - Ocorrências/Ambientes Atingidos]]="","X","") | CE5: =IFERROR(FIND("IBAMA",consulta_completa__11[[#This Row],[14 - Inst. Atuando no Local]]),0) -> 0 | CF5: =IF(CE5=0,"","X") | CG5: =IFERROR(FIND("OEMA",consulta_completa__11[[#This Row],[14 - Inst. Atuando no Local]]),0) -> 0 | CH5: =IF(CG5=0,"","X") | CI5: =IFERROR(FIND("DEFESA CIVIL",consulta_completa__11[[#This Row],[14 - Inst. Atuando no Local]]),0) -> 0 | CJ5: =IF(CI5=0,"","X") | CK5: =IFERROR(FIND("CORPO DE BOMBEIROS",consulta_completa__11[[#This Row],[14 - Inst. Atuando no Local]]),0) -> 0 | CL5: =IF(CK5=0,"","X") | CM5: =IFERROR(FIND("POLÍCIA RODOVIÁRIA",consulta_completa__11[[#This Row],[14 - Inst. Atuando no Local]]),0) -> 0 | CN5: =IF(CM5=0,"","X") | CO5: =IFERROR(FIND("POLÍCIA MILITAR",consulta_completa__11[[#This Row],[14 - Inst. Atuando no Local]]),0) -> 0 | CP5: =IF(CO5=0,"","X") | CQ5: =IFERROR(FIND("POLÍCIA CIVIL",consulta_completa__11[[#This Row],[14 - Inst. Atuando no Local]]),0) -> 0 | CR5: =IF(CQ5=0,"","X") | CS5: =IFERROR(FIND("MARINHA DO BRASIL",consulta_completa__11[[#This Row],[14 - Inst. Atuando no Local]]),0) -> 0 | CT5: =IF(CS5=0,"","X") | CU5: =IFERROR(FIND("EMPRESA ESPECIALIZADA EM ATENDIMENTO",consulta_completa__11[[#This Row],[14 - Inst. Atuando no Local]]),0) -> 0 | CV5: =IF(CU5=0,"","X") | CW5: =IFERROR(FIND("IBAMA",consulta_completa__11[[#This Row],[14 - Inst. Atuando no Local]]),0) -> 0 | CX5: =IF(CW5=0,"","X") | CY5: =IF(consulta_completa__11[[#This Row],[14 - Inst. Atuando no Local]]="","X","") | CZ5: =IFERROR(FIND("OUTRA (S)",consulta_completa__11[[#This Row],[14 - Inst. Atuando no Local]]),0) -> 0 | DA5: =IF(CZ5=0,"","X") | DB5: =IF(AH$2="","",IF(AH$2="S","Sim",IF(AH$2="N","Não", IF(AH$2="I","Sem Informação")))) -> Sim | DC5: =IF(AI$2="","",IF(AI$2="S","Sim",IF(AI$2="N","Não", IF(AI$2="I","Sem Informação")))) -> Não | DD5: =IF(AJ$2="","",IF(AJ$2="S","Sim",IF(AJ$2="N","Não", IF(AJ$2="I","Sem Informação")))) -> Sim | DE5: =IF(AD5=1,"Federal",IF(AD5=2,"Estadual",IF(AD5=0,"Sem informação",""))) -> Estadual
A6: 2025143653 | B6: 45660 | C6: null | D6: null | E6: Outro(s) | F6: Derramamento de líquidos | J6: Etilenoglicol | K6: 0.000132 | L6: M3 | M6: Mar | N6: Outra(s) | O6: Outra(s) fonte(s) | P6: Sexta | Q6: Matutino | R6: Não | S6: Campos | T6: Campo de Jubarte - Bacia de Campos | U6: [EMBARCAÇÃO AKER WAYFARER]: Durante operação visando dissociação de hidratos com suporte de embarcação, foi observada uma queda abrupta de pressão na linha de alimentação de MEG (Etilenoglicol). Após inspeção detalhada no conjunto da ANM (árvore de natal molhada), foi identificado ponto de escape na mangueira que conecta a ferramenta ao equipamento submarino de teste. O vazamento foi estimado em 0,000132 m³. | V6: GLICOL - 0,000132 m3. | Z6: Perda de contenção da mangueira do sistema de alimentação de MEG. | AB6: Petrobras | AC6: 33000167100750 | AD6: 1 | AE6: PETROBRAS | AH6: S | AI6: N | AJ6: S | AK6: 1 - Drenada pressão da linha HCR (mangueira de alta resistência ao colapso) para interrupção do escape. 2 - Desconexão da linha HCR para subida do skid de remediação e troca da mangueira HCR. | AL6: - Cálculo da estimativa do volume: A mangueira HCR tem 28 metros, que correspondem a 3,7 litros. O furo na mangueira está posicionado a 1 metro do ponto de ligação na ANM. Considerando que todo o volume desse 1 metro escapou, chegamos ao volume de 0,132 litros. - Volume descarregado no mar: 0,000132 m3; - Nome comercial: ETILENO GLICOL (MEG); - Composição química: Etileno glicol. - ONU/IMDG: Não classificado como perigoso. | AM6: PETROBRAS - PETROLEO BRASILEIRO S.A. | AQ6: crisguerreiro@petrobras.com.br | AX6: =IFERROR(FIND("Óbitos/feridos",consulta_completa__11[[#This Row],[13 - Ocorrências/Ambientes Atingidos]]),0) -> 0 | AY6: =IF(AX6=0,"","X") | AZ6: =IFERROR(FIND("População afetada/evacuada",consulta_completa__11[[#This Row],[13 - Ocorrências/Ambientes Atingidos]]),0) -> 0 | BA6: =IF(AZ6=0,"","X") | BB6: =IFERROR(FIND("Suspensão de abastecimento de água",consulta_completa__11[[#This Row],[13 - Ocorrências/Ambientes Atingidos]]),0) -> 0 | BC6: =IF(BB6=0,"","X") | BD6: =IFERROR(FIND("Rio/córrego",consulta_completa__11[[#This Row],[13 - Ocorrências/Ambientes Atingidos]]),0) -> 0 | BE6: =IF(BD6=0,"","X") | BF6: =IFERROR(FIND("Lago",consulta_completa__11[[#This Row],[13 - Ocorrências/Ambientes Atingidos]]),0) -> 0 | BG6: =IF(BF6=0,"","X") | BH6: =IFERROR(FIND("Mar",consulta_completa__11[[#This Row],[13 - Ocorrências/Ambientes Atingidos]]),0) -> 1 | BI6: =IF(BH6=0,"","X") -> X | BJ6: =IFERROR(FIND("Praia",consulta_completa__11[[#This Row],[13 - Ocorrências/Ambientes Atingidos]]),0) -> 0 | BK6: =IF(BJ6=0,"","X") | BL6: =IFERROR(FIND("Solo",consulta_completa__11[[#This Row],[13 - Ocorrências/Ambientes Atingidos]]),0) -> 0 | BM6: =IF(BL6=0,"","X") | BN6: =IFERROR(FIND("Águas subterrâneas",consulta_completa__11[[#This Row],[13 - Ocorrências/Ambientes Atingidos]]),0) -> 0 | BO6: =IF(BN6=0,"","X") | BP6: =IFERROR(FIND("Atmosfera",consulta_completa__11[[#This Row],[13 - Ocorrências/Ambientes Atingidos]]),0) -> 0 | BQ6: =IF(BP6=0,"","X") | BR6: =IFERROR(FIND("Flora",consulta_completa__11[[#This Row],[13 - Ocorrências/Ambientes Atingidos]]),0) -> 0 | BS6: =IF(BR6=0,"","X") | BT6: =IFERROR(FIND("Fauna",consulta_completa__11[[#This Row],[13 - Ocorrências/Ambientes Atingidos]]),0) -> 0 | BU6: =IF(BT6=0,"","X") | BV6: =IFERROR(FIND("UC federal",consulta_completa__11[[#This Row],[13 - Ocorrências/Ambientes Atingidos]]),0) -> 0 | BW6: =IF(BV6=0,"","X") | BX6: =IFERROR(FIND("UC estadual/municipal",consulta_completa__11[[#This Row],[13 - Ocorrências/Ambientes Atingidos]]),0) -> 0 | BY6: =IF(BX6=0,"","X") | BZ6: =IFERROR(FIND("Outro(s)",consulta_completa__11[[#This Row],[13 - Ocorrências/Ambientes Atingidos]]),0) -> 0 | CA6: =IF(BZ6=0,"","X") | CB6: =IFERROR(FIND("Sem dano",consulta_completa__11[[#This Row],[13 - Ocorrências/Ambientes Atingidos]]),0) -> 0 | CC6: =IF(CB6=0,"","X") | CD6: =IF(consulta_completa__11[[#This Row],[13 - Ocorrências/Ambientes Atingidos]]="","X","") | CE6: =IFERROR(FIND("IBAMA",consulta_completa__11[[#This Row],[14 - Inst. Atuando no Local]]),0) -> 0 | CF6: =IF(CE6=0,"","X") | CG6: =IFERROR(FIND("OEMA",consulta_completa__11[[#This Row],[14 - Inst. Atuando no Local]]),0) -> 0 | CH6: =IF(CG6=0,"","X") | CI6: =IFERROR(FIND("DEFESA CIVIL",consulta_completa__11[[#This Row],[14 - Inst. Atuando no Local]]),0) -> 0 | CJ6: =IF(CI6=0,"","X") | CK6: =IFERROR(FIND("CORPO DE BOMBEIROS",consulta_completa__11[[#This Row],[14 - Inst. Atuando no Local]]),0) -> 0 | CL6: =IF(CK6=0,"","X") | CM6: =IFERROR(FIND("POLÍCIA RODOVIÁRIA",consulta_completa__11[[#This Row],[14 - Inst. Atuando no Local]]),0) -> 0 | CN6: =IF(CM6=0,"","X") | CO6: =IFERROR(FIND("POLÍCIA MILITAR",consulta_completa__11[[#This Row],[14 - Inst. Atuando no Local]]),0) -> 0 | CP6: =IF(CO6=0,"","X") | CQ6: =IFERROR(FIND("POLÍCIA CIVIL",consulta_completa__11[[#This Row],[14 - Inst. Atuando no Local]]),0) -> 0 | CR6: =IF(CQ6=0,"","X") | CS6: =IFERROR(FIND("MARINHA DO BRASIL",consulta_completa__11[[#This Row],[14 - Inst. Atuando no Local]]),0) -> 0 | CT6: =IF(CS6=0,"","X") | CU6: =IFERROR(FIND("EMPRESA ESPECIALIZADA EM ATENDIMENTO",consulta_completa__11[[#This Row],[14 - Inst. Atuando no Local]]),0) -> 0 | CV6: =IF(CU6=0,"","X") | CW6: =IFERROR(FIND("IBAMA",consulta_completa__11[[#This Row],[14 - Inst. Atuando no Local]]),0) -> 0 | CX6: =IF(CW6=0,"","X") | CY6: =IF(consulta_completa__11[[#This Row],[14 - Inst. Atuando no Local]]="","X","") | CZ6: =IFERROR(FIND("OUTRA (S)",consulta_completa__11[[#This Row],[14 - Inst. Atuando no Local]]),0) -> 0 | DA6: =IF(CZ6=0,"","X") | DB6: =IF(AH$2="","",IF(AH$2="S","Sim",IF(AH$2="N","Não", IF(AH$2="I","Sem Informação")))) -> Sim | DC6: =IF(AI$2="","",IF(AI$2="S","Sim",IF(AI$2="N","Não", IF(AI$2="I","Sem Informação")))) -> Não | DD6: =IF(AJ$2="","",IF(AJ$2="S","Sim",IF(AJ$2="N","Não", IF(AJ$2="I","Sem Informação")))) -> Sim | DE6: =IF(AD6=1,"Federal",IF(AD6=2,"Estadual",IF(AD6=0,"Sem informação",""))) -> Federal
A7: 2025143658 | B7: 45660 | C7: null | D7: RJ | E7: Outro(s) | F7: Derramamento de líquidos | J7: Fluido Hidraulico | K7: 0.001 | L7: M3 | M7: Mar | N7: Outra(s) | O7: Outra(s) fonte(s) | P7: Sexta | Q7: Matutino | R7: Não | S7: Campos | T7: Campo de Congro, Bacia de Campos | U7: [SS-45 (ATLANTIC STAR) em operação no poço 7-CG-5HPA-RJS ]: Na tentativa de abertura da válvula XO (cross over) da ANM (árvore de natal molhada) hidraulicamente, foi observada com auxílio do ROV (veículo de operação remota), descarga estimada de 0,001 m3 de fluido hidráulico base aquosa, Oceanic HW-525 P, pelo atuador da válvula para o fundo do mar. Interrompida atuação hidráulica e cessada descarga. | V7: FLUIDO HIDRÁULICO - 0,001m³ | Z7: Falha de estanqueidade das vedações do atuador hidráulico da XO da ANM. | AB7: Petrobras | AC7: 33000167100750 | AD7: 1 | AE7: Petrobras | AH7: S | AI7: N | AJ7: S | AK7: Após observação da descarga de fluido, interrompida a tentativa de abertura da válvula hidraulicamente. | AL7: - Volume descarregado: 0,001 m3 (1 litro), estimado pelo volume da linha hidráulica da função do carretel do umbilical (ID 1/4") da superfície até o nível de equalização com lâmina d'água (peso do fluido 8,67 lb/gal, peso da água do mar 8,55 lb/gal). - Descarga de Fluido hidráulico base aquosa Oceanic HW 525 P para o mar. - Composição: água, etileno glicol (CAS 107-21- 1): 20 a 30%; 2-butóxietanol (CAS 111-76-2): 4 a 6%. - ONU/IMDG: Não classificado como perigoso. | AM7: PETROBRAS - PETROLEO BRASILEIRO S.A. | AQ7: crisguerreiro@petrobras.com.br | AX7: =IFERROR(FIND("Óbitos/feridos",consulta_completa__11[[#This Row],[13 - Ocorrências/Ambientes Atingidos]]),0) -> 0 | AY7: =IF(AX7=0,"","X") | AZ7: =IFERROR(FIND("População afetada/evacuada",consulta_completa__11[[#This Row],[13 - Ocorrências/Ambientes Atingidos]]),0) -> 0 | BA7: =IF(AZ7=0,"","X") | BB7: =IFERROR(FIND("Suspensão de abastecimento de água",consulta_completa__11[[#This Row],[13 - Ocorrências/Ambientes Atingidos]]),0) -> 0 | BC7: =IF(BB7=0,"","X") | BD7: =IFERROR(FIND("Rio/córrego",consulta_completa__11[[#This Row],[13 - Ocorrências/Ambientes Atingidos]]),0) -> 0 | BE7: =IF(BD7=0,"","X") | BF7: =IFERROR(FIND("Lago",consulta_completa__11[[#This Row],[13 - Ocorrências/Ambientes Atingidos]]),0) -> 0 | BG7: =IF(BF7=0,"","X") | BH7: =IFERROR(FIND("Mar",consulta_completa__11[[#This Row],[13 - Ocorrências/Ambientes Atingidos]]),0) -> 1 | BI7: =IF(BH7=0,"","X") -> X | BJ7: =IFERROR(FIND("Praia",consulta_completa__11[[#This Row],[13 - Ocorrências/Ambientes Atingidos]]),0) -> 0 | BK7: =IF(BJ7=0,"","X") | BL7: =IFERROR(FIND("Solo",consulta_completa__11[[#This Row],[13 - Ocorrências/Ambientes Atingidos]]),0) -> 0 | BM7: =IF(BL7=0,"","X") | BN7: =IFERROR(FIND("Águas subterrâneas",consulta_completa__11[[#This Row],[13 - Ocorrências/Ambientes Atingidos]]),0) -> 0 | BO7: =IF(BN7=0,"","X") | BP7: =IFERROR(FIND("Atmosfera",consulta_completa__11[[#This Row],[13 - Ocorrências/Ambientes Atingidos]]),0) -> 0 | BQ7: =IF(BP7=0,"","X") | BR7: =IFERROR(FIND("Flora",consulta_completa__11[[#This Row],[13 - Ocorrências/Ambientes Atingidos]]),0) -> 0 | BS7: =IF(BR7=0,"","X") | BT7: =IFERROR(FIND("Fauna",consulta_completa__11[[#This Row],[13 - Ocorrências/Ambientes Atingidos]]),0) -> 0 | BU7: =IF(BT7=0,"","X") | BV7: =IFERROR(FIND("UC federal",consulta_completa__11[[#This Row],[13 - Ocorrências/Ambientes Atingidos]]),0) -> 0 | BW7: =IF(BV7=0,"","X") | BX7: =IFERROR(FIND("UC estadual/municipal",consulta_completa__11[[#This Row],[13 - Ocorrências/Ambientes Atingidos]]),0) -> 0 | BY7: =IF(BX7=0,"","X") | BZ7: =IFERROR(FIND("Outro(s)",consulta_completa__11[[#This Row],[13 - Ocorrências/Ambientes Atingidos]]),0) -> 0 | CA7: =IF(BZ7=0,"","X") | CB7: =IFERROR(FIND("Sem dano",consulta_completa__11[[#This Row],[13 - Ocorrências/Ambientes Atingidos]]),0) -> 0 | CC7: =IF(CB7=0,"","X") | CD7: =IF(consulta_completa__11[[#This Row],[13 - Ocorrências/Ambientes Atingidos]]="","X","") | CE7: =IFERROR(FIND("IBAMA",consulta_completa__11[[#This Row],[14 - Inst. Atuando no Local]]),0) -> 0 | CF7: =IF(CE7=0,"","X") | CG7: =IFERROR(FIND("OEMA",consulta_completa__11[[#This Row],[14 - Inst. Atuando no Local]]),0) -> 0 | CH7: =IF(CG7=0,"","X") | CI7: =IFERROR(FIND("DEFESA CIVIL",consulta_completa__11[[#This Row],[14 - Inst. Atuando no Local]]),0) -> 0 | CJ7: =IF(CI7=0,"","X") | CK7: =IFERROR(FIND("CORPO DE BOMBEIROS",consulta_completa__11[[#This Row],[14 - Inst. Atuando no Local]]),0) -> 0 | CL7: =IF(CK7=0,"","X") | CM7: =IFERROR(FIND("POLÍCIA RODOVIÁRIA",consulta_completa__11[[#This Row],[14 - Inst. Atuando no Local]]),0) -> 0 | CN7: =IF(CM7=0,"","X") | CO7: =IFERROR(FIND("POLÍCIA MILITAR",consulta_completa__11[[#This Row],[14 - Inst. Atuando no Local]]),0) -> 0 | CP7: =IF(CO7=0,"","X") | CQ7: =IFERROR(FIND("POLÍCIA CIVIL",consulta_completa__11[[#This Row],[14 - Inst. Atuando no Local]]),0) -> 0 | CR7: =IF(CQ7=0,"","X") | CS7: =IFERROR(FIND("MARINHA DO BRASIL",consulta_completa__11[[#This Row],[14 - Inst. Atuando no Local]]),0) -> 0 | CT7: =IF(CS7=0,"","X") | CU7: =IFERROR(FIND("EMPRESA ESPECIALIZADA EM ATENDIMENTO",consulta_completa__11[[#This Row],[14 - Inst. Atuando no Local]]),0) -> 0 | CV7: =IF(CU7=0,"","X") | CW7: =IFERROR(FIND("IBAMA",consulta_completa__11[[#This Row],[14 - Inst. Atuando no Local]]),0) -> 0 | CX7: =IF(CW7=0,"","X") | CY7: =IF(consulta_completa__11[[#This Row],[14 - Inst. Atuando no Local]]="","X","") | CZ7: =IFERROR(FIND("OUTRA (S)",consulta_completa__11[[#This Row],[14 - Inst. Atuando no Local]]),0) -> 0 | DA7: =IF(CZ7=0,"","X") | DB7: =IF(AH$2="","",IF(AH$2="S","Sim",IF(AH$2="N","Não", IF(AH$2="I","Sem Informação")))) -> Sim | DC7: =IF(AI$2="","",IF(AI$2="S","Sim",IF(AI$2="N","Não", IF(AI$2="I","Sem Informação")))) -> Não | DD7: =IF(AJ$2="","",IF(AJ$2="S","Sim",IF(AJ$2="N","Não", IF(AJ$2="I","Sem Informação")))) -> Sim | DE7: =IF(AD7=1,"Federal",IF(AD7=2,"Estadual",IF(AD7=0,"Sem informação",""))) -> Federal
A8: 20251336027 | B8: 45660 | C8: Praia Grande | D8: SP | E8: Ferrovia | F8: Lançamento de sólidos | J8: Cloreto de Potássio | K8: 10 | L8: T | M8: Solo | N8: Outra(s) | O8: Outra(s) fonte(s) | P8: Sexta | Q8: Matutino | R8: Não | U8: Vandalismo na ferrovia com abertura de bicas em vagão graneleiro carregado fertilizante granular. | V8: Vandalismo com abertura de vagão graneleiro carregado com Fertilizante (Cloreto de Potassio). Lançamento de 10 tonelada de fertilizante granular sobre a linha férrea. | Z8: Ato criminoso caracterizado pela abertura de bicas em vagão graneleiro ferroviário carregado com fertilizante granular. | AA8: Solo dentro dos limites da área de domínio da via férrea. | AB8: Rumo Logistica S. A. | AC8: 02502844000166 | AD8: 1 | AE8: Equipes de atendimento de limpeza, contratadas pela Rumo, atuando no trecho afetado. | AH8: S | AI8: N | AJ8: S | AK8: Equipes de atendimento emergencial de limpeza, contratadas pela rumo, e de segurança patrimonial, atuando no trecho afetado para remoção do material, liberação da via e garantia da segurança dos trabalhadores. | AM8: Eloisa Caxias Coelho | AN8: Rumo Logistica S. A. | AO8: Auditora Ambiental | AP8: 41988207121 | AQ8: eloisa.coelho@rumolog.com | AX8: =IFERROR(FIND("Óbitos/feridos",consulta_completa__11[[#This Row],[13 - Ocorrências/Ambientes Atingidos]]),0) -> 0 | AY8: =IF(AX8=0,"","X") | AZ8: =IFERROR(FIND("População afetada/evacuada",consulta_completa__11[[#This Row],[13 - Ocorrências/Ambientes Atingidos]]),0) -> 0 | BA8: =IF(AZ8=0,"","X") | BB8: =IFERROR(FIND("Suspensão de abastecimento de água",consulta_completa__11[[#This Row],[13 - Ocorrências/Ambientes Atingidos]]),0) -> 0 | BC8: =IF(BB8=0,"","X") | BD8: =IFERROR(FIND("Rio/córrego",consulta_completa__11[[#This Row],[13 - Ocorrências/Ambientes Atingidos]]),0) -> 0 | BE8: =IF(BD8=0,"","X") | BF8: =IFERROR(FIND("Lago",consulta_completa__11[[#This Row],[13 - Ocorrências/Ambientes Atingidos]]),0) -> 0 | BG8: =IF(BF8=0,"","X") | BH8: =IFERROR(FIND("Mar",consulta_completa__11[[#This Row],[13 - Ocorrências/Ambientes Atingidos]]),0) -> 0 | BI8: =IF(BH8=0,"","X") | BJ8: =IFERROR(FIND("Praia",consulta_completa__11[[#This Row],[13 - Ocorrências/Ambientes Atingidos]]),0) -> 0 | BK8: =IF(BJ8=0,"","X") | BL8: =IFERROR(FIND("Solo",consulta_completa__11[[#This Row],[13 - Ocorrências/Ambientes Atingidos]]),0) -> 1 | BM8: =IF(BL8=0,"","X") -> X | BN8: =IFERROR(FIND("Águas subterrâneas",consulta_completa__11[[#This Row],[13 - Ocorrências/Ambientes Atingidos]]),0) -> 0 | BO8: =IF(BN8=0,"","X") | BP8: =IFERROR(FIND("Atmosfera",consulta_completa__11[[#This Row],[13 - Ocorrências/Ambientes Atingidos]]),0) -> 0 | BQ8: =IF(BP8=0,"","X") | BR8: =IFERROR(FIND("Flora",consulta_completa__11[[#This Row],[13 - Ocorrências/Ambientes Atingidos]]),0) -> 0 | BS8: =IF(BR8=0,"","X") | BT8: =IFERROR(FIND("Fauna",consulta_completa__11[[#This Row],[13 - Ocorrências/Ambientes Atingidos]]),0) -> 0 | BU8: =IF(BT8=0,"","X") | BV8: =IFERROR(FIND("UC federal",consulta_completa__11[[#This Row],[13 - Ocorrências/Ambientes Atingidos]]),0) -> 0 | BW8: =IF(BV8=0,"","X") | BX8: =IFERROR(FIND("UC estadual/municipal",consulta_completa__11[[#This Row],[13 - Ocorrências/Ambientes Atingidos]]),0) -> 0 | BY8: =IF(BX8=0,"","X") | BZ8: =IFERROR(FIND("Outro(s)",consulta_completa__11[[#This Row],[13 - Ocorrências/Ambientes Atingidos]]),0) -> 0 | CA8: =IF(BZ8=0,"","X") | CB8: =IFERROR(FIND("Sem dano",consulta_completa__11[[#This Row],[13 - Ocorrências/Ambientes Atingidos]]),0) -> 0 | CC8: =IF(CB8=0,"","X") | CD8: =IF(consulta_completa__11[[#This Row],[13 - Ocorrências/Ambientes Atingidos]]="","X","") | CE8: =IFERROR(FIND("IBAMA",consulta_completa__11[[#This Row],[14 - Inst. Atuando no Local]]),0) -> 0 | CF8: =IF(CE8=0,"","X") | CG8: =IFERROR(FIND("OEMA",consulta_completa__11[[#This Row],[14 - Inst. Atuando no Local]]),0) -> 0 | CH8: =IF(CG8=0,"","X") | CI8: =IFERROR(FIND("DEFESA CIVIL",consulta_completa__11[[#This Row],[14 - Inst. Atuando no Local]]),0) -> 0 | CJ8: =IF(CI8=0,"","X") | CK8: =IFERROR(FIND("CORPO DE BOMBEIROS",consulta_completa__11[[#This Row],[14 - Inst. Atuando no Local]]),0) -> 0 | CL8: =IF(CK8=0,"","X") | CM8: =IFERROR(FIND("POLÍCIA RODOVIÁRIA",consulta_completa__11[[#This Row],[14 - Inst. Atuando no Local]]),0) -> 0 | CN8: =IF(CM8=0,"","X") | CO8: =IFERROR(FIND("POLÍCIA MILITAR",consulta_completa__11[[#This Row],[14 - Inst. Atuando no Local]]),0) -> 0 | CP8: =IF(CO8=0,"","X") | CQ8: =IFERROR(FIND("POLÍCIA CIVIL",consulta_completa__11[[#This Row],[14 - Inst. Atuando no Local]]),0) -> 0 | CR8: =IF(CQ8=0,"","X") | CS8: =IFERROR(FIND("MARINHA DO BRASIL",consulta_completa__11[[#This Row],[14 - Inst. Atuando no Local]]),0) -> 0 | CT8: =IF(CS8=0,"","X") | CU8: =IFERROR(FIND("EMPRESA ESPECIALIZADA EM ATENDIMENTO",consulta_completa__11[[#This Row],[14 - Inst. Atuando no Local]]),0) -> 0 | CV8: =IF(CU8=0,"","X") | CW8: =IFERROR(FIND("IBAMA",consulta_completa__11[[#This Row],[14 - Inst. Atuando no Local]]),0) -> 0 | CX8: =IF(CW8=0,"","X") | CY8: =IF(consulta_completa__11[[#This Row],[14 - Inst. Atuando no Local]]="","X","") | CZ8: =IFERROR(FIND("OUTRA (S)",consulta_completa__11[[#This Row],[14 - Inst. Atuando no Local]]),0) -> 0 | DA8: =IF(CZ8=0,"","X") | DB8: =IF(AH$2="","",IF(AH$2="S","Sim",IF(AH$2="N","Não", IF(AH$2="I","Sem Informação")))) -> Sim | DC8: =IF(AI$2="","",IF(AI$2="S","Sim",IF(AI$2="N","Não", IF(AI$2="I","Sem Informação")))) -> Não | DD8: =IF(AJ$2="","",IF(AJ$2="S","Sim",IF(AJ$2="N","Não", IF(AJ$2="I","Sem Informação")))) -> Sim | DE8: =IF(AD8=1,"Federal",IF(AD8=2,"Estadual",IF(AD8=0,"Sem informação",""))) -> Federal
A9: 20251564830 | B9: 45661 | C9: null | D9: SP | E9: Plataforma | F9: Derramamento de líquidos | J9: Petroleo | K9: 0.034 | L9: M3 | M9: Mar | N9: Outra(s) | O9: Comunicado da empresa/responsável; Outra(s) fonte(s) | P9: Sábado | Q9: Madrugada | R9: Não | S9: Santos | T9: FPSO MARECHAL DUQUE DE CAXIAS (FPSO MDC), Campo de Mero, Bacia de Santos. | U9: Parada emergencial da planta de processo causada pela sensibilização de sensor de gás devido a perda de contenção primária de aproximadamente 0,5 m3 no permutador de placa óleo / óleo no módulo P50. Posteriormente, foi constatada por aeronave de asa fixa, feição oleosa com estimativa de 0,034 m3 conectada à instalação marítima. | V9: Feição oleosa com estimativa de 0,034 m3 conectada à instalação marítima | Z9: Falha no permutador de placas óleo/óleo. Em investigação. | AB9: Petrobras | AC9: 33000167000292 | AD9: 1 | AH9: S | AI9: S | AJ9: S | AK9: Parada imediata da unidade e blowdown da planta de processo. Após término da resposta inicial, foi realizada limpeza do óleo do deck atingidos pelo vazamento. Mobilização de embarcação Oil Recovery que realizou inspeção conforme modelagem e não constatou a feição. | AL9: Situação normalizada. Volume da feição oleosa estimada pela aeronave de asa fixa (Poseidon 2). | AM9: PETRLEO BRASILEIRO S/A - PETROBRAS | AQ9: giselletinoco@petrobras.com.br | AT9: FPSO MARECHAL DUQUE DE CAXIAS | AX9: =IFERROR(FIND("Óbitos/feridos",consulta_completa__11[[#This Row],[13 - Ocorrências/Ambientes Atingidos]]),0) -> 0 | AY9: =IF(AX9=0,"","X") | AZ9: =IFERROR(FIND("População afetada/evacuada",consulta_completa__11[[#This Row],[13 - Ocorrências/Ambientes Atingidos]]),0) -> 0 | BA9: =IF(AZ9=0,"","X") | BB9: =IFERROR(FIND("Suspensão de abastecimento de água",consulta_completa__11[[#This Row],[13 - Ocorrências/Ambientes Atingidos]]),0) -> 0 | BC9: =IF(BB9=0,"","X") | BD9: =IFERROR(FIND("Rio/córrego",consulta_completa__11[[#This Row],[13 - Ocorrências/Ambientes Atingidos]]),0) -> 0 | BE9: =IF(BD9=0,"","X") | BF9: =IFERROR(FIND("Lago",consulta_completa__11[[#This Row],[13 - Ocorrências/Ambientes Atingidos]]),0) -> 0 | BG9: =IF(BF9=0,"","X") | BH9: =IFERROR(FIND("Mar",consulta_completa__11[[#This Row],[13 - Ocorrências/Ambientes Atingidos]]),0) -> 1 | BI9: =IF(BH9=0,"","X") -> X | BJ9: =IFERROR(FIND("Praia",consulta_completa__11[[#This Row],[13 - Ocorrências/Ambientes Atingidos]]),0) -> 0 | BK9: =IF(BJ9=0,"","X") | BL9: =IFERROR(FIND("Solo",consulta_completa__11[[#This Row],[13 - Ocorrências/Ambientes Atingidos]]),0) -> 0 | BM9: =IF(BL9=0,"","X") | BN9: =IFERROR(FIND("Águas subterrâneas",consulta_completa__11[[#This Row],[13 - Ocorrências/Ambientes Atingidos]]),0) -> 0 | BO9: =IF(BN9=0,"","X") | BP9: =IFERROR(FIND("Atmosfera",consulta_completa__11[[#This Row],[13 - Ocorrências/Ambientes Atingidos]]),0) -> 0 | BQ9: =IF(BP9=0,"","X") | BR9: =IFERROR(FIND("Flora",consulta_completa__11[[#This Row],[13 - Ocorrências/Ambientes Atingidos]]),0) -> 0 | BS9: =IF(BR9=0,"","X") | BT9: =IFERROR(FIND("Fauna",consulta_completa__11[[#This Row],[13 - Ocorrências/Ambientes Atingidos]]),0) -> 0 | BU9: =IF(BT9=0,"","X") | BV9: =IFERROR(FIND("UC federal",consulta_completa__11[[#This Row],[13 - Ocorrências/Ambientes Atingidos]]),0) -> 0 | BW9: =IF(BV9=0,"","X") | BX9: =IFERROR(FIND("UC estadual/municipal",consulta_completa__11[[#This Row],[13 - Ocorrências/Ambientes Atingidos]]),0) -> 0 | BY9: =IF(BX9=0,"","X") | BZ9: =IFERROR(FIND("Outro(s)",consulta_completa__11[[#This Row],[13 - Ocorrências/Ambientes Atingidos]]),0) -> 0 | CA9: =IF(BZ9=0,"","X") | CB9: =IFERROR(FIND("Sem dano",consulta_completa__11[[#This Row],[13 - Ocorrências/Ambientes Atingidos]]),0) -> 0 | CC9: =IF(CB9=0,"","X") | CD9: =IF(consulta_completa__11[[#This Row],[13 - Ocorrências/Ambientes Atingidos]]="","X","") | CE9: =IFERROR(FIND("IBAMA",consulta_completa__11[[#This Row],[14 - Inst. Atuando no Local]]),0) -> 0 | CF9: =IF(CE9=0,"","X") | CG9: =IFERROR(FIND("OEMA",consulta_completa__11[[#This Row],[14 - Inst. Atuando no Local]]),0) -> 0 | CH9: =IF(CG9=0,"","X") | CI9: =IFERROR(FIND("DEFESA CIVIL",consulta_completa__11[[#This Row],[14 - Inst. Atuando no Local]]),0) -> 0 | CJ9: =IF(CI9=0,"","X") | CK9: =IFERROR(FIND("CORPO DE BOMBEIROS",consulta_completa__11[[#This Row],[14 - Inst. Atuando no Local]]),0) -> 0 | CL9: =IF(CK9=0,"","X") | CM9: =IFERROR(FIND("POLÍCIA RODOVIÁRIA",consulta_completa__11[[#This Row],[14 - Inst. Atuando no Local]]),0) -> 0 | CN9: =IF(CM9=0,"","X") | CO9: =IFERROR(FIND("POLÍCIA MILITAR",consulta_completa__11[[#This Row],[14 - Inst. Atuando no Local]]),0) -> 0 | CP9: =IF(CO9=0,"","X") | CQ9: =IFERROR(FIND("POLÍCIA CIVIL",consulta_completa__11[[#This Row],[14 - Inst. Atuando no Local]]),0) -> 0 | CR9: =IF(CQ9=0,"","X") | CS9: =IFERROR(FIND("MARINHA DO BRASIL",consulta_completa__11[[#This Row],[14 - Inst. Atuando no Local]]),0) -> 0 | CT9: =IF(CS9=0,"","X") | CU9: =IFERROR(FIND("EMPRESA ESPECIALIZADA EM ATENDIMENTO",consulta_completa__11[[#This Row],[14 - Inst. Atuando no Local]]),0) -> 0 | CV9: =IF(CU9=0,"","X") | CW9: =IFERROR(FIND("IBAMA",consulta_completa__11[[#This Row],[14 - Inst. Atuando no Local]]),0) -> 0 | CX9: =IF(CW9=0,"","X") | CY9: =IF(consulta_completa__11[[#This Row],[14 - Inst. Atuando no Local]]="","X","") | CZ9: =IFERROR(FIND("OUTRA (S)",consulta_completa__11[[#This Row],[14 - Inst. Atuando no Local]]),0) -> 0 | DA9: =IF(CZ9=0,"","X") | DB9: =IF(AH$2="","",IF(AH$2="S","Sim",IF(AH$2="N","Não", IF(AH$2="I","Sem Informação")))) -> Sim | DC9: =IF(AI$2="","",IF(AI$2="S","Sim",IF(AI$2="N","Não", IF(AI$2="I","Sem Informação")))) -> Não | DD9: =IF(AJ$2="","",IF(AJ$2="S","Sim",IF(AJ$2="N","Não", IF(AJ$2="I","Sem Informação")))) -> Sim | DE9: =IF(AD9=1,"Federal",IF(AD9=2,"Estadual",IF(AD9=0,"Sem informação",""))) -> Federal
A10: 20251657612 | B10: 45661 | C10: Macaé | D10: RJ | E10: Plataforma | F10: Derramamento de líquidos | M10: Mar | O10: Comunicado da empresa/responsável | P10: Sábado | Q10: Vespertino | R10: Não | S10: Campos | T10: Polo Pargo - Bacia de Campos | V10: No dia 04 de janeiro de 2025, às 14h30, foi detectada uma feição oleosa na face oeste de PPG1-B, originada de um pequeno vazamento de diesel proveniente de uma linha de 2%u2019%u2019, responsável pela transferência do combustível do tanque para a centrífuga. A maior parte do vazamento, aproximadamente 1 litro, ficou contida na plataforma, mas estima-se que cerca de 200 ml de diesel tenham alcançado o mar. A linha foi imediatamente isolada e reparada por uma empresa especializada, utilizando material compósito. A feição de coloração prateada/iridescente, com dimensões de 5x5m, foi localizada e rapidamente dispersada. | X10: TRUE | Z10: Em investigação | AB10: Perenco Petróleo e Gás do Brasil Ltda. | AC10: 09309027000135 | AD10: 1 | AH10: S | AI10: N | AJ10: S | AK10: A linha de 2%u2019%u2019 foi isolada e o vazamento foi contido. Um reparo com aplicação de compósito foi efetuado. O reparo realizado foi certificado pela empresa especializada que realizou o serviço. | AL10: Um reparo com aplicação de compósito foi efetuado. O reparo realizado foi certificado pela empresa especializada que realizou o serviço. | AM10: PERENCO PETRLEO E GS DO BRASIL LTDA | AN10: PERENCO PETRÓLEO E GÁS DO BRASIL LTDA. | AO10: GERENTE DE QHSE | AP10: 21998863038 | AQ10: mgonin@br.perenco.com | AT10: Pargo-PPG-1B | AU10: Óleo diesel | AV10: 12000000 | AW10: Paralisada | AX10: =IFERROR(FIND("Óbitos/feridos",consulta_completa__11[[#This Row],[13 - Ocorrências/Ambientes Atingidos]]),0) -> 0 | AY10: =IF(AX10=0,"","X") | AZ10: =IFERROR(FIND("População afetada/evacuada",consulta_completa__11[[#This Row],[13 - Ocorrências/Ambientes Atingidos]]),0) -> 0 | BA10: =IF(AZ10=0,"","X") | BB10: =IFERROR(FIND("Suspensão de abastecimento de água",consulta_completa__11[[#This Row],[13 - Ocorrências/Ambientes Atingidos]]),0) -> 0 | BC10: =IF(BB10=0,"","X") | BD10: =IFERROR(FIND("Rio/córrego",consulta_completa__11[[#This Row],[13 - Ocorrências/Ambientes Atingidos]]),0) -> 0 | BE10: =IF(BD10=0,"","X") | BF10: =IFERROR(FIND("Lago",consulta_completa__11[[#This Row],[13 - Ocorrências/Ambientes Atingidos]]),0) -> 0 | BG10: =IF(BF10=0,"","X") | BH10: =IFERROR(FIND("Mar",consulta_completa__11[[#This Row],[13 - Ocorrências/Ambientes Atingidos]]),0) -> 1 | BI10: =IF(BH10=0,"","X") -> X | BJ10: =IFERROR(FIND("Praia",consulta_completa__11[[#This Row],[13 - Ocorrências/Ambientes Atingidos]]),0) -> 0 | BK10: =IF(BJ10=0,"","X") | BL10: =IFERROR(FIND("Solo",consulta_completa__11[[#This Row],[13 - Ocorrências/Ambientes Atingidos]]),0) -> 0 | BM10: =IF(BL10=0,"","X") | BN10: =IFERROR(FIND("Águas subterrâneas",consulta_completa__11[[#This Row],[13 - Ocorrências/Ambientes Atingidos]]),0) -> 0 | BO10: =IF(BN10=0,"","X") | BP10: =IFERROR(FIND("Atmosfera",consulta_completa__11[[#This Row],[13 - Ocorrências/Ambientes Atingidos]]),0) -> 0 | BQ10: =IF(BP10=0,"","X") | BR10: =IFERROR(FIND("Flora",consulta_completa__11[[#This Row],[13 - Ocorrências/Ambientes Atingidos]]),0) -> 0 | BS10: =IF(BR10=0,"","X") | BT10: =IFERROR(FIND("Fauna",consulta_completa__11[[#This Row],[13 - Ocorrências/Ambientes Atingidos]]),0) -> 0 | BU10: =IF(BT10=0,"","X") | BV10: =IFERROR(FIND("UC federal",consulta_completa__11[[#This Row],[13 - Ocorrências/Ambientes Atingidos]]),0) -> 0 | BW10: =IF(BV10=0,"","X") | BX10: =IFERROR(FIND("UC estadual/municipal",consulta_completa__11[[#This Row],[13 - Ocorrências/Ambientes Atingidos]]),0) -> 0 | BY10: =IF(BX10=0,"","X") | BZ10: =IFERROR(FIND("Outro(s)",consulta_completa__11[[#This Row],[13 - Ocorrências/Ambientes Atingidos]]),0) -> 0 | CA10: =IF(BZ10=0,"","X") | CB10: =IFERROR(FIND("Sem dano",consulta_completa__11[[#This Row],[13 - Ocorrências/Ambientes Atingidos]]),0) -> 0 | CC10: =IF(CB10=0,"","X") | CD10: =IF(consulta_completa__11[[#This Row],[13 - Ocorrências/Ambientes Atingidos]]="","X","") | CE10: =IFERROR(FIND("IBAMA",consulta_completa__11[[#This Row],[14 - Inst. Atuando no Local]]),0) -> 0 | CF10: =IF(CE10=0,"","X") | CG10: =IFERROR(FIND("OEMA",consulta_completa__11[[#This Row],[14 - Inst. Atuando no Local]]),0) -> 0 | CH10: =IF(CG10=0,"","X") | CI10: =IFERROR(FIND("DEFESA CIVIL",consulta_completa__11[[#This Row],[14 - Inst. Atuando no Local]]),0) -> 0 | CJ10: =IF(CI10=0,"","X") | CK10: =IFERROR(FIND("CORPO DE BOMBEIROS",consulta_completa__11[[#This Row],[14 - Inst. Atuando no Local]]),0) -> 0 | CL10: =IF(CK10=0,"","X") | CM10: =IFERROR(FIND("POLÍCIA RODOVIÁRIA",consulta_completa__11[[#This Row],[14 - Inst. Atuando no Local]]),0) -> 0 | CN10: =IF(CM10=0,"","X") | CO10: =IFERROR(FIND("POLÍCIA MILITAR",consulta_completa__11[[#This Row],[14 - Inst. Atuando no Local]]),0) -> 0 | CP10: =IF(CO10=0,"","X") | CQ10: =IFERROR(FIND("POLÍCIA CIVIL",consulta_completa__11[[#This Row],[14 - Inst. Atuando no Local]]),0) -> 0 | CR10: =IF(CQ10=0,"","X") | CS10: =IFERROR(FIND("MARINHA DO BRASIL",consulta_completa__11[[#This Row],[14 - Inst. Atuando no Local]]),0) -> 0 | CT10: =IF(CS10=0,"","X") | CU10: =IFERROR(FIND("EMPRESA ESPECIALIZADA EM ATENDIMENTO",consulta_completa__11[[#This Row],[14 - Inst. Atuando no Local]]),0) -> 0 | CV10: =IF(CU10=0,"","X") | CW10: =IFERROR(FIND("IBAMA",consulta_completa__11[[#This Row],[14 - Inst. Atuando no Local]]),0) -> 0 | CX10: =IF(CW10=0,"","X") | CY10: =IF(consulta_completa__11[[#This Row],[14 - Inst. Atuando no Local]]="","X","") -> X | CZ10: =IFERROR(FIND("OUTRA (S)",consulta_completa__11[[#This Row],[14 - Inst. Atuando no Local]]),0) -> 0 | DA10: =IF(CZ10=0,"","X") | DB10: =IF(AH$2="","",IF(AH$2="S","Sim",IF(AH$2="N","Não", IF(AH$2="I","Sem Informação")))) -> Sim | DC10: =IF(AI$2="","",IF(AI$2="S","Sim",IF(AI$2="N","Não", IF(AI$2="I","Sem Informação")))) -> Não | DD10: =IF(AJ$2="","",IF(AJ$2="S","Sim",IF(AJ$2="N","Não", IF(AJ$2="I","Sem Informação")))) -> Sim | DE10: =IF(AD10=1,"Federal",IF(AD10=2,"Estadual",IF(AD10=0,"Sem informação",""))) -> Federal
A11: 202512725255 | B11: 45661 | C11: Alagoinhas | D11: BA | E11: Plataforma | F11: Derramamento de líquidos | J11: Água de injeção | K11: 1 | L11: M3 | M11: Mar | N11: Empresa especializada em atendimento | O11: Comunicado da empresa/responsável | P11: Sábado | Q11: Vespertino | R11: Não | T11: Poço 8-BA-426-BA, Campo de Buracica, Município de Alagoinhas, Bahia | U11: Água de injeção | V11: Vazamento não contido de 1 m³ de água de injeção, através da linha de injeção em uma área de 100m². | Z11: Corrosão | AA11: 1) Características do fluido vazado: TOG- 49mg/l, Salinidade- 39.000; 2) Poço parado, aguardando intervenção da caldeiraria; 3) Vazamento sanado | AB11: PETRÓLEO BRASILEIRO S.A. - PETROBRAS | AC11: 33000167000101 | AD11: 2 | AE11: Petrobras | AH11: I | AI11: N | AJ11: S | AK11: Válvulas bloqueadas e acionamento do carro sugador para atuação no loca | AM11: Gunther Barbosa | AN11: IBAMA | AO11: Analista Ambiental | AQ11: gunther.barbosa@ibama.gov.br | AT11: BURACICA | AW11: Paralisada | AX11: =IFERROR(FIND("Óbitos/feridos",consulta_completa__11[[#This Row],[13 - Ocorrências/Ambientes Atingidos]]),0) -> 0 | AY11: =IF(AX11=0,"","X") | AZ11: =IFERROR(FIND("População afetada/evacuada",consulta_completa__11[[#This Row],[13 - Ocorrências/Ambientes Atingidos]]),0) -> 0 | BA11: =IF(AZ11=0,"","X") | BB11: =IFERROR(FIND("Suspensão de abastecimento de água",consulta_completa__11[[#This Row],[13 - Ocorrências/Ambientes Atingidos]]),0) -> 0 | BC11: =IF(BB11=0,"","X") | BD11: =IFERROR(FIND("Rio/córrego",consulta_completa__11[[#This Row],[13 - Ocorrências/Ambientes Atingidos]]),0) -> 0 | BE11: =IF(BD11=0,"","X") | BF11: =IFERROR(FIND("Lago",consulta_completa__11[[#This Row],[13 - Ocorrências/Ambientes Atingidos]]),0) -> 0 | BG11: =IF(BF11=0,"","X") | BH11: =IFERROR(FIND("Mar",consulta_completa__11[[#This Row],[13 - Ocorrências/Ambientes Atingidos]]),0) -> 1 | BI11: =IF(BH11=0,"","X") -> X | BJ11: =IFERROR(FIND("Praia",consulta_completa__11[[#This Row],[13 - Ocorrências/Ambientes Atingidos]]),0) -> 0 | BK11: =IF(BJ11=0,"","X") | BL11: =IFERROR(FIND("Solo",consulta_completa__11[[#This Row],[13 - Ocorrências/Ambientes Atingidos]]),0) -> 0 | BM11: =IF(BL11=0,"","X") | BN11: =IFERROR(FIND("Águas subterrâneas",consulta_completa__11[[#This Row],[13 - Ocorrências/Ambientes Atingidos]]),0) -> 0 | BO11: =IF(BN11=0,"","X") | BP11: =IFERROR(FIND("Atmosfera",consulta_completa__11[[#This Row],[13 - Ocorrências/Ambientes Atingidos]]),0) -> 0 | BQ11: =IF(BP11=0,"","X") | BR11: =IFERROR(FIND("Flora",consulta_completa__11[[#This Row],[13 - Ocorrências/Ambientes Atingidos]]),0) -> 0 | BS11: =IF(BR11=0,"","X") | BT11: =IFERROR(FIND("Fauna",consulta_completa__11[[#This Row],[13 - Ocorrências/Ambientes Atingidos]]),0) -> 0 | BU11: =IF(BT11=0,"","X") | BV11: =IFERROR(FIND("UC federal",consulta_completa__11[[#This Row],[13 - Ocorrências/Ambientes Atingidos]]),0) -> 0 | BW11: =IF(BV11=0,"","X") | BX11: =IFERROR(FIND("UC estadual/municipal",consulta_completa__11[[#This Row],[13 - Ocorrências/Ambientes Atingidos]]),0) -> 0 | BY11: =IF(BX11=0,"","X") | BZ11: =IFERROR(FIND("Outro(s)",consulta_completa__11[[#This Row],[13 - Ocorrências/Ambientes Atingidos]]),0) -> 0 | CA11: =IF(BZ11=0,"","X") | CB11: =IFERROR(FIND("Sem dano",consulta_completa__11[[#This Row],[13 - Ocorrências/Ambientes Atingidos]]),0) -> 0 | CC11: =IF(CB11=0,"","X") | CD11: =IF(consulta_completa__11[[#This Row],[13 - Ocorrências/Ambientes Atingidos]]="","X","") | CE11: =IFERROR(FIND("IBAMA",consulta_completa__11[[#This Row],[14 - Inst. Atuando no Local]]),0) -> 0 | CF11: =IF(CE11=0,"","X") | CG11: =IFERROR(FIND("OEMA",consulta_completa__11[[#This Row],[14 - Inst. Atuando no Local]]),0) -> 0 | CH11: =IF(CG11=0,"","X") | CI11: =IFERROR(FIND("DEFESA CIVIL",consulta_completa__11[[#This Row],[14 - Inst. Atuando no Local]]),0) -> 0 | CJ11: =IF(CI11=0,"","X") | CK11: =IFERROR(FIND("CORPO DE BOMBEIROS",consulta_completa__11[[#This Row],[14 - Inst. Atuando no Local]]),0) -> 0 | CL11: =IF(CK11=0,"","X") | CM11: =IFERROR(FIND("POLÍCIA RODOVIÁRIA",consulta_completa__11[[#This Row],[14 - Inst. Atuando no Local]]),0) -> 0 | CN11: =IF(CM11=0,"","X") | CO11: =IFERROR(FIND("POLÍCIA MILITAR",consulta_completa__11[[#This Row],[14 - Inst. Atuando no Local]]),0) -> 0 | CP11: =IF(CO11=0,"","X") | CQ11: =IFERROR(FIND("POLÍCIA CIVIL",consulta_completa__11[[#This Row],[14 - Inst. Atuando no Local]]),0) -> 0 | CR11: =IF(CQ11=0,"","X") | CS11: =IFERROR(FIND("MARINHA DO BRASIL",consulta_completa__11[[#This Row],[14 - Inst. Atuando no Local]]),0) -> 0 | CT11: =IF(CS11=0,"","X") | CU11: =IFERROR(FIND("EMPRESA ESPECIALIZADA EM ATENDIMENTO",consulta_completa__11[[#This Row],[14 - Inst. Atuando no Local]]),0) -> 0 | CV11: =IF(CU11=0,"","X") | CW11: =IFERROR(FIND("IBAMA",consulta_completa__11[[#This Row],[14 - Inst. Atuando no Local]]),0) -> 0 | CX11: =IF(CW11=0,"","X") | CY11: =IF(consulta_completa__11[[#This Row],[14 - Inst. Atuando no Local]]="","X","") | CZ11: =IFERROR(FIND("OUTRA (S)",consulta_completa__11[[#This Row],[14 - Inst. Atuando no Local]]),0) -> 0 | DA11: =IF(CZ11=0,"","X") | DB11: =IF(AH$2="","",IF(AH$2="S","Sim",IF(AH$2="N","Não", IF(AH$2="I","Sem Informação")))) -> Sim | DC11: =IF(AI$2="","",IF(AI$2="S","Sim",IF(AI$2="N","Não", IF(AI$2="I","Sem Informação")))) -> Não | DD11: =IF(AJ$2="","",IF(AJ$2="S","Sim",IF(AJ$2="N","Não", IF(AJ$2="I","Sem Informação")))) -> Sim | DE11: =IF(AD11=1,"Federal",IF(AD11=2,"Estadual",IF(AD11=0,"Sem informação",""))) -> Estadual
A12: 20251561230 | B12: 45662 | C12: Minduri | D12: MG | E12: Ferrovia | F12: Lançamento de sólidos | J12: Clinquer | M12: Solo | N12: Outra(s); Empresa especializada em atendimento | O12: Comunicado da empresa/responsável | P12: Domingo | Q12: Vespertino | R12: Não | T12: km 302+00 | U12: Em 05/01/2025 às 14:20 no Corredor Minas Rio da Ferrovia Centro Atlântica, no município de Minduri/MG, a composição C230, Km 302+00 veio a tombar 2 vagões e adernar outros 3 vagões carregados com clínquer. | V12: Em 05/01/2025 às 14:20 no Corredor Minas Rio da Ferrovia Centro Atlântica, no município de Minduri/MG, a composição C230, Km 302+00 veio a tombar 2 vagões e adernar outros 3 vagões carregados com clínquer. | AB12: Ferrovia Centro Atlantica | AC12: 00924429000175 | AD12: 1 | AE12: A equipe de emergência ICS Parakletos e equipe de atendimento da FCA estão se deslocando para o local. | AF12: Diego Faustino | AG12: (31) 98618-6369 | AH12: S | AI12: S | AJ12: N | AL12: O maquinista encontra-se sem bem. O local, conforme mapa em anexo, está em zona rural. | AM12: FERROVIA CENTRO ATLANTICA S/A | AN12: Sâmara Durães de Souza | AO12: Supervisora de Meio Ambiente | AP12: 31982625614 | AQ12: meio.ambiente.vli@vli-logistica.com.br | AX12: =IFERROR(FIND("Óbitos/feridos",consulta_completa__11[[#This Row],[13 - Ocorrências/Ambientes Atingidos]]),0) -> 0 | AY12: =IF(AX12=0,"","X") | AZ12: =IFERROR(FIND("População afetada/evacuada",consulta_completa__11[[#This Row],[13 - Ocorrências/Ambientes Atingidos]]),0) -> 0 | BA12: =IF(AZ12=0,"","X") | BB12: =IFERROR(FIND("Suspensão de abastecimento de água",consulta_completa__11[[#This Row],[13 - Ocorrências/Ambientes Atingidos]]),0) -> 0 | BC12: =IF(BB12=0,"","X") | BD12: =IFERROR(FIND("Rio/córrego",consulta_completa__11[[#This Row],[13 - Ocorrências/Ambientes Atingidos]]),0) -> 0 | BE12: =IF(BD12=0,"","X") | BF12: =IFERROR(FIND("Lago",consulta_completa__11[[#This Row],[13 - Ocorrências/Ambientes Atingidos]]),0) -> 0 | BG12: =IF(BF12=0,"","X") | BH12: =IFERROR(FIND("Mar",consulta_completa__11[[#This Row],[13 - Ocorrências/Ambientes Atingidos]]),0) -> 0 | BI12: =IF(BH12=0,"","X") | BJ12: =IFERROR(FIND("Praia",consulta_completa__11[[#This Row],[13 - Ocorrências/Ambientes Atingidos]]),0) -> 0 | BK12: =IF(BJ12=0,"","X") | BL12: =IFERROR(FIND("Solo",consulta_completa__11[[#This Row],[13 - Ocorrências/Ambientes Atingidos]]),0) -> 1 | BM12: =IF(BL12=0,"","X") -> X | BN12: =IFERROR(FIND("Águas subterrâneas",consulta_completa__11[[#This Row],[13 - Ocorrências/Ambientes Atingidos]]),0) -> 0 | BO12: =IF(BN12=0,"","X") | BP12: =IFERROR(FIND("Atmosfera",consulta_completa__11[[#This Row],[13 - Ocorrências/Ambientes Atingidos]]),0) -> 0 | BQ12: =IF(BP12=0,"","X") | BR12: =IFERROR(FIND("Flora",consulta_completa__11[[#This Row],[13 - Ocorrências/Ambientes Atingidos]]),0) -> 0 | BS12: =IF(BR12=0,"","X") | BT12: =IFERROR(FIND("Fauna",consulta_completa__11[[#This Row],[13 - Ocorrências/Ambientes Atingidos]]),0) -> 0 | BU12: =IF(BT12=0,"","X") | BV12: =IFERROR(FIND("UC federal",consulta_completa__11[[#This Row],[13 - Ocorrências/Ambientes Atingidos]]),0) -> 0 | BW12: =IF(BV12=0,"","X") | BX12: =IFERROR(FIND("UC estadual/municipal",consulta_completa__11[[#This Row],[13 - Ocorrências/Ambientes Atingidos]]),0) -> 0 | BY12: =IF(BX12=0,"","X") | BZ12: =IFERROR(FIND("Outro(s)",consulta_completa__11[[#This Row],[13 - Ocorrências/Ambientes Atingidos]]),0) -> 0 | CA12: =IF(BZ12=0,"","X") | CB12: =IFERROR(FIND("Sem dano",consulta_completa__11[[#This Row],[13 - Ocorrências/Ambientes Atingidos]]),0) -> 0 | CC12: =IF(CB12=0,"","X") | CD12: =IF(consulta_completa__11[[#This Row],[13 - Ocorrências/Ambientes Atingidos]]="","X","") | CE12: =IFERROR(FIND("IBAMA",consulta_completa__11[[#This Row],[14 - Inst. Atuando no Local]]),0) -> 0 | CF12: =IF(CE12=0,"","X") | CG12: =IFERROR(FIND("OEMA",consulta_completa__11[[#This Row],[14 - Inst. Atuando no Local]]),0) -> 0 | CH12: =IF(CG12=0,"","X") | CI12: =IFERROR(FIND("DEFESA CIVIL",consulta_completa__11[[#This Row],[14 - Inst. Atuando no Local]]),0) -> 0 | CJ12: =IF(CI12=0,"","X") | CK12: =IFERROR(FIND("CORPO DE BOMBEIROS",consulta_completa__11[[#This Row],[14 - Inst. Atuando no Local]]),0) -> 0 | CL12: =IF(CK12=0,"","X") | CM12: =IFERROR(FIND("POLÍCIA RODOVIÁRIA",consulta_completa__11[[#This Row],[14 - Inst. Atuando no Local]]),0) -> 0 | CN12: =IF(CM12=0,"","X") | CO12: =IFERROR(FIND("POLÍCIA MILITAR",consulta_completa__11[[#This Row],[14 - Inst. Atuando no Local]]),0) -> 0 | CP12: =IF(CO12=0,"","X") | CQ12: =IFERROR(FIND("POLÍCIA CIVIL",consulta_completa__11[[#This Row],[14 - Inst. Atuando no Local]]),0) -> 0 | CR12: =IF(CQ12=0,"","X") | CS12: =IFERROR(FIND("MARINHA DO BRASIL",consulta_completa__11[[#This Row],[14 - Inst. Atuando no Local]]),0) -> 0 | CT12: =IF(CS12=0,"","X") | CU12: =IFERROR(FIND("EMPRESA ESPECIALIZADA EM ATENDIMENTO",consulta_completa__11[[#This Row],[14 - Inst. Atuando no Local]]),0) -> 0 | CV12: =IF(CU12=0,"","X") | CW12: =IFERROR(FIND("IBAMA",consulta_completa__11[[#This Row],[14 - Inst. Atuando no Local]]),0) -> 0 | CX12: =IF(CW12=0,"","X") | CY12: =IF(consulta_completa__11[[#This Row],[14 - Inst. Atuando no Local]]="","X","") | CZ12: =IFERROR(FIND("OUTRA (S)",consulta_completa__11[[#This Row],[14 - Inst. Atuando no Local]]),0) -> 0 | DA12: =IF(CZ12=0,"","X") | DB12: =IF(AH$2="","",IF(AH$2="S","Sim",IF(AH$2="N","Não", IF(AH$2="I","Sem Informação")))) -> Sim | DC12: =IF(AI$2="","",IF(AI$2="S","Sim",IF(AI$2="N","Não", IF(AI$2="I","Sem Informação")))) -> Não | DD12: =IF(AJ$2="","",IF(AJ$2="S","Sim",IF(AJ$2="N","Não", IF(AJ$2="I","Sem Informação")))) -> Sim | DE12: =IF(AD12=1,"Federal",IF(AD12=2,"Estadual",IF(AD12=0,"Sem informação",""))) -> Federal
A13: 202511414430 | B13: 45662 | C13: São Lourenço | D13: MG | E13: Rodovia | F13: Lançamento de sólidos | G13: ÓXIDO DE CÁLCIO | M13: Solo | N13: Empresa especializada em atendimento | O13: Órgão Estadual ou Municipal de Meio Ambiente | P13: Domingo | Q13: Matutino | R13: Não | T13: RODOVIA MG 460 - TREVO DE ACESSO A SÃO LOURENÇO: | U13: SEGUNDO INFORMADO AO NEA, OCORREU UM TOMBAMENTO DO VEÍCULO COM QUEDA DA CARGA. | V13: Carregamento de cal | Z13: Acidente rodoviário | AB13: TRANSTININHO TRANSPORTES TININHO LTDA | AC13: 01716053000176 | AD13: 2 | AE13: EMPRESA REGULADORA | AH13: I | AI13: N | AJ13: S | AK13: EMPRESA REGULADORA ACIONADA PARA VERIFICAR O LOCAL E CONTRATAR EMPRESA DE ATENDIMENTO ESPECIALIZADA PARA OS TRABALHOS DE LIMPEZA DO LOCAL DO ACIDENTE. TRANSFERÊNCIA DE CARGA DA MINERAÇÃO BELOCAL - UNIDADE DE ARCOS PARA MINERAÇÃO BELOCAL - UNIDADE RIO DE JANEIRO. | AM13: Gunther Barbosa | AN13: IBAMA | AO13: Analista Ambiental | AQ13: gunther.barbosa@ibama.gov.br | AX13: =IFERROR(FIND("Óbitos/feridos",consulta_completa__11[[#This Row],[13 - Ocorrências/Ambientes Atingidos]]),0) -> 0 | AY13: =IF(AX13=0,"","X") | AZ13: =IFERROR(FIND("População afetada/evacuada",consulta_completa__11[[#This Row],[13 - Ocorrências/Ambientes Atingidos]]),0) -> 0 | BA13: =IF(AZ13=0,"","X") | BB13: =IFERROR(FIND("Suspensão de abastecimento de água",consulta_completa__11[[#This Row],[13 - Ocorrências/Ambientes Atingidos]]),0) -> 0 | BC13: =IF(BB13=0,"","X") | BD13: =IFERROR(FIND("Rio/córrego",consulta_completa__11[[#This Row],[13 - Ocorrências/Ambientes Atingidos]]),0) -> 0 | BE13: =IF(BD13=0,"","X") | BF13: =IFERROR(FIND("Lago",consulta_completa__11[[#This Row],[13 - Ocorrências/Ambientes Atingidos]]),0) -> 0 | BG13: =IF(BF13=0,"","X") | BH13: =IFERROR(FIND("Mar",consulta_completa__11[[#This Row],[13 - Ocorrências/Ambientes Atingidos]]),0) -> 0 | BI13: =IF(BH13=0,"","X") | BJ13: =IFERROR(FIND("Praia",consulta_completa__11[[#This Row],[13 - Ocorrências/Ambientes Atingidos]]),0) -> 0 | BK13: =IF(BJ13=0,"","X") | BL13: =IFERROR(FIND("Solo",consulta_completa__11[[#This Row],[13 - Ocorrências/Ambientes Atingidos]]),0) -> 1 | BM13: =IF(BL13=0,"","X") -> X | BN13: =IFERROR(FIND("Águas subterrâneas",consulta_completa__11[[#This Row],[13 - Ocorrências/Ambientes Atingidos]]),0) -> 0 | BO13: =IF(BN13=0,"","X") | BP13: =IFERROR(FIND("Atmosfera",consulta_completa__11[[#This Row],[13 - Ocorrências/Ambientes Atingidos]]),0) -> 0 | BQ13: =IF(BP13=0,"","X") | BR13: =IFERROR(FIND("Flora",consulta_completa__11[[#This Row],[13 - Ocorrências/Ambientes Atingidos]]),0) -> 0 | BS13: =IF(BR13=0,"","X") | BT13: =IFERROR(FIND("Fauna",consulta_completa__11[[#This Row],[13 - Ocorrências/Ambientes Atingidos]]),0) -> 0 | BU13: =IF(BT13=0,"","X") | BV13: =IFERROR(FIND("UC federal",consulta_completa__11[[#This Row],[13 - Ocorrências/Ambientes Atingidos]]),0) -> 0 | BW13: =IF(BV13=0,"","X") | BX13: =IFERROR(FIND("UC estadual/municipal",consulta_completa__11[[#This Row],[13 - Ocorrências/Ambientes Atingidos]]),0) -> 0 | BY13: =IF(BX13=0,"","X") | BZ13: =IFERROR(FIND("Outro(s)",consulta_completa__11[[#This Row],[13 - Ocorrências/Ambientes Atingidos]]),0) -> 0 | CA13: =IF(BZ13=0,"","X") | CB13: =IFERROR(FIND("Sem dano",consulta_completa__11[[#This Row],[13 - Ocorrências/Ambientes Atingidos]]),0) -> 0 | CC13: =IF(CB13=0,"","X") | CD13: =IF(consulta_completa__11[[#This Row],[13 - Ocorrências/Ambientes Atingidos]]="","X","") | CE13: =IFERROR(FIND("IBAMA",consulta_completa__11[[#This Row],[14 - Inst. Atuando no Local]]),0) -> 0 | CF13: =IF(CE13=0,"","X") | CG13: =IFERROR(FIND("OEMA",consulta_completa__11[[#This Row],[14 - Inst. Atuando no Local]]),0) -> 0 | CH13: =IF(CG13=0,"","X") | CI13: =IFERROR(FIND("DEFESA CIVIL",consulta_completa__11[[#This Row],[14 - Inst. Atuando no Local]]),0) -> 0 | CJ13: =IF(CI13=0,"","X") | CK13: =IFERROR(FIND("CORPO DE BOMBEIROS",consulta_completa__11[[#This Row],[14 - Inst. Atuando no Local]]),0) -> 0 | CL13: =IF(CK13=0,"","X") | CM13: =IFERROR(FIND("POLÍCIA RODOVIÁRIA",consulta_completa__11[[#This Row],[14 - Inst. Atuando no Local]]),0) -> 0 | CN13: =IF(CM13=0,"","X") | CO13: =IFERROR(FIND("POLÍCIA MILITAR",consulta_completa__11[[#This Row],[14 - Inst. Atuando no Local]]),0) -> 0 | CP13: =IF(CO13=0,"","X") | CQ13: =IFERROR(FIND("POLÍCIA CIVIL",consulta_completa__11[[#This Row],[14 - Inst. Atuando no Local]]),0) -> 0 | CR13: =IF(CQ13=0,"","X") | CS13: =IFERROR(FIND("MARINHA DO BRASIL",consulta_completa__11[[#This Row],[14 - Inst. Atuando no Local]]),0) -> 0 | CT13: =IF(CS13=0,"","X") | CU13: =IFERROR(FIND("EMPRESA ESPECIALIZADA EM ATENDIMENTO",consulta_completa__11[[#This Row],[14 - Inst. Atuando no Local]]),0) -> 0 | CV13: =IF(CU13=0,"","X") | CW13: =IFERROR(FIND("IBAMA",consulta_completa__11[[#This Row],[14 - Inst. Atuando no Local]]),0) -> 0 | CX13: =IF(CW13=0,"","X") | CY13: =IF(consulta_completa__11[[#This Row],[14 - Inst. Atuando no Local]]="","X","") | CZ13: =IFERROR(FIND("OUTRA (S)",consulta_completa__11[[#This Row],[14 - Inst. Atuando no Local]]),0) -> 0 | DA13: =IF(CZ13=0,"","X") | DB13: =IF(AH$2="","",IF(AH$2="S","Sim",IF(AH$2="N","Não", IF(AH$2="I","Sem Informação")))) -> Sim | DC13: =IF(AI$2="","",IF(AI$2="S","Sim",IF(AI$2="N","Não", IF(AI$2="I","Sem Informação")))) -> Não | DD13: =IF(AJ$2="","",IF(AJ$2="S","Sim",IF(AJ$2="N","Não", IF(AJ$2="I","Sem Informação")))) -> Sim | DE13: =IF(AD13=1,"Federal",IF(AD13=2,"Estadual",IF(AD13=0,"Sem informação",""))) -> Estadual
A14: 20251761252 | B14: 45663 | C14: Piraí | D14: RJ | E14: Rodovia | F14: Derramamento de líquidos | M14: Óbitos/feridos; Solo | N14: Empresa especializada em atendimento ; Polícia Civil; Polícia Rodoviária; Órgão Estadual ou Municipal de Meio Ambiente | O14: Outra(s) fonte(s) | P14: Segunda | Q14: Noturno | R14: Não | T14: Rodovia Presidente Dutra, Km 245+100, Pista Sul | U14: O acidente ocorreu com veículo que trafegava na Rodovia Presidente Dutra, Km 245+100, Pista Sul. Sendo que a primeira observação foi realizada pela Concessionária CCR RioSP, responsável pela administração do trecho sob concessão. | V14: No acidente registrado houve derramamento de líquidos provenientes da carga transportada, composta por tambores e bombonas de óleo lubrificante de motor e graxa. | Z14: De acordo com informações colhidas pela CCR RioSP, o motorista da carreta trafegava na rodovia pela pista sul, quando perdeu o controle do veículo vindo a tombar entre canteiro lateral e ribanceira em local sem acostamento. No tombamento do veículo houve queda de carga composta por tambores e bombonas de óleo lubrificante de motor e graxa. Na nota fiscal consta que o número ONU é 3082 - Substância que apresenta risco para o meio ambiente, líquida, N.E. Porém o veículo não possuia as placas de identificação do número ONU e nem de risco. A queda da carga ocorreu em solo do canteiro lateral e em canaleta de águas pluviais próxima ao local. Para contenção do vazamento foram removidos os tambores e bombonas de óleo do solo. | AA14: Foram atingidos o motorista do veículo que foi removido ao hospital e solo visto que a queda de carga foi no canteiro lateral da rodovia. | AB14: Iconic Lubrificantes S.A. | AC14: 05524572003702 | AD14: 0 | AE14: Foram acionados a PRF - Polícia Rodoviária Federal, que esteve no local acompanhando o destombamento do veículo e liberação do tráfego. O órgão estadual do Rio de Janeiro - INEA foi comunicado por ligação e informou que no dia seguinte se dirigia ao local do acidente. A seguradora da carga realizou o acionamento de empresa especializada em atendimento para avaliação de danos e limpeza do local atingido. | AH14: S | AI14: S | AJ14: N | AL14: O veículo não possuia as placas de identificação de risco e número ONU necessárias ao transporte de produtos perigosos. | AM14: CONCESSIONRIA DO SISTEMA RODOVIRIO RIO - SO PAULO S.A | AQ14: gabriely.hamada@grupoccr.com.br | AX14: =IFERROR(FIND("Óbitos/feridos",consulta_completa__11[[#This Row],[13 - Ocorrências/Ambientes Atingidos]]),0) -> 1 | AY14: =IF(AX14=0,"","X") -> X | AZ14: =IFERROR(FIND("População afetada/evacuada",consulta_completa__11[[#This Row],[13 - Ocorrências/Ambientes Atingidos]]),0) -> 0 | BA14: =IF(AZ14=0,"","X") | BB14: =IFERROR(FIND("Suspensão de abastecimento de água",consulta_completa__11[[#This Row],[13 - Ocorrências/Ambientes Atingidos]]),0) -> 0 | BC14: =IF(BB14=0,"","X") | BD14: =IFERROR(FIND("Rio/córrego",consulta_completa__11[[#This Row],[13 - Ocorrências/Ambientes Atingidos]]),0) -> 0 | BE14: =IF(BD14=0,"","X") | BF14: =IFERROR(FIND("Lago",consulta_completa__11[[#This Row],[13 - Ocorrências/Ambientes Atingidos]]),0) -> 0 | BG14: =IF(BF14=0,"","X") | BH14: =IFERROR(FIND("Mar",consulta_completa__11[[#This Row],[13 - Ocorrências/Ambientes Atingidos]]),0) -> 0 | BI14: =IF(BH14=0,"","X") | BJ14: =IFERROR(FIND("Praia",consulta_completa__11[[#This Row],[13 - Ocorrências/Ambientes Atingidos]]),0) -> 0 | BK14: =IF(BJ14=0,"","X") | BL14: =IFERROR(FIND("Solo",consulta_completa__11[[#This Row],[13 - Ocorrências/Ambientes Atingidos]]),0) -> 17 | BM14: =IF(BL14=0,"","X") -> X | BN14: =IFERROR(FIND("Águas subterrâneas",consulta_completa__11[[#This Row],[13 - Ocorrências/Ambientes Atingidos]]),0) -> 0 | BO14: =IF(BN14=0,"","X") | BP14: =IFERROR(FIND("Atmosfera",consulta_completa__11[[#This Row],[13 - Ocorrências/Ambientes Atingidos]]),0) -> 0 | BQ14: =IF(BP14=0,"","X") | BR14: =IFERROR(FIND("Flora",consulta_completa__11[[#This Row],[13 - Ocorrências/Ambientes Atingidos]]),0) -> 0 | BS14: =IF(BR14=0,"","X") | BT14: =IFERROR(FIND("Fauna",consulta_completa__11[[#This Row],[13 - Ocorrências/Ambientes Atingidos]]),0) -> 0 | BU14: =IF(BT14=0,"","X") | BV14: =IFERROR(FIND("UC federal",consulta_completa__11[[#This Row],[13 - Ocorrências/Ambientes Atingidos]]),0) -> 0 | BW14: =IF(BV14=0,"","X") | BX14: =IFERROR(FIND("UC estadual/municipal",consulta_completa__11[[#This Row],[13 - Ocorrências/Ambientes Atingidos]]),0) -> 0 | BY14: =IF(BX14=0,"","X") | BZ14: =IFERROR(FIND("Outro(s)",consulta_completa__11[[#This Row],[13 - Ocorrências/Ambientes Atingidos]]),0) -> 0 | CA14: =IF(BZ14=0,"","X") | CB14: =IFERROR(FIND("Sem dano",consulta_completa__11[[#This Row],[13 - Ocorrências/Ambientes Atingidos]]),0) -> 0 | CC14: =IF(CB14=0,"","X") | CD14: =IF(consulta_completa__11[[#This Row],[13 - Ocorrências/Ambientes Atingidos]]="","X","") | CE14: =IFERROR(FIND("IBAMA",consulta_completa__11[[#This Row],[14 - Inst. Atuando no Local]]),0) -> 0 | CF14: =IF(CE14=0,"","X") | CG14: =IFERROR(FIND("OEMA",consulta_completa__11[[#This Row],[14 - Inst. Atuando no Local]]),0) -> 0 | CH14: =IF(CG14=0,"","X") | CI14: =IFERROR(FIND("DEFESA CIVIL",consulta_completa__11[[#This Row],[14 - Inst. Atuando no Local]]),0) -> 0 | CJ14: =IF(CI14=0,"","X") | CK14: =IFERROR(FIND("CORPO DE BOMBEIROS",consulta_completa__11[[#This Row],[14 - Inst. Atuando no Local]]),0) -> 0 | CL14: =IF(CK14=0,"","X") | CM14: =IFERROR(FIND("POLÍCIA RODOVIÁRIA",consulta_completa__11[[#This Row],[14 - Inst. Atuando no Local]]),0) -> 0 | CN14: =IF(CM14=0,"","X") | CO14: =IFERROR(FIND("POLÍCIA MILITAR",consulta_completa__11[[#This Row],[14 - Inst. Atuando no Local]]),0) -> 0 | CP14: =IF(CO14=0,"","X") | CQ14: =IFERROR(FIND("POLÍCIA CIVIL",consulta_completa__11[[#This Row],[14 - Inst. Atuando no Local]]),0) -> 0 | CR14: =IF(CQ14=0,"","X") | CS14: =IFERROR(FIND("MARINHA DO BRASIL",consulta_completa__11[[#This Row],[14 - Inst. Atuando no Local]]),0) -> 0 | CT14: =IF(CS14=0,"","X") | CU14: =IFERROR(FIND("EMPRESA ESPECIALIZADA EM ATENDIMENTO",consulta_completa__11[[#This Row],[14 - Inst. Atuando no Local]]),0) -> 0 | CV14: =IF(CU14=0,"","X") | CW14: =IFERROR(FIND("IBAMA",consulta_completa__11[[#This Row],[14 - Inst. Atuando no Local]]),0) -> 0 | CX14: =IF(CW14=0,"","X") | CY14: =IF(consulta_completa__11[[#This Row],[14 - Inst. Atuando no Local]]="","X","") | CZ14: =IFERROR(FIND("OUTRA (S)",consulta_completa__11[[#This Row],[14 - Inst. Atuando no Local]]),0) -> 0 | DA14: =IF(CZ14=0,"","X") | DB14: =IF(AH$2="","",IF(AH$2="S","Sim",IF(AH$2="N","Não", IF(AH$2="I","Sem Informação")))) -> Sim | DC14: =IF(AI$2="","",IF(AI$2="S","Sim",IF(AI$2="N","Não", IF(AI$2="I","Sem Informação")))) -> Não | DD14: =IF(AJ$2="","",IF(AJ$2="S","Sim",IF(AJ$2="N","Não", IF(AJ$2="I","Sem Informação")))) -> Sim | DE14: =IF(AD14=1,"Federal",IF(AD14=2,"Estadual",IF(AD14=0,"Sem informação",""))) -> Sem informação
A15: 20251854018 | B15: 45663 | C15: null | D15: RJ | E15: Plataforma | F15: Derramamento de líquidos | G15: ÓLEO DIESEL | H15: 0.075 | I15: M3 | M15: Mar | N15: Outra(s) | O15: Comunicado da empresa/responsável | P15: Segunda | Q15: Vespertino | R15: Não | S15: Campos | T15: Campo de Marlim, Número IMO 8762874. | V15: Foi identificada a iridescência no mar e imediatamente foi iniciada uma investigação/ronda para localizar a possível origem da fonte na unidade. Foi identificado um fluxo de água oleosa no extravasor das linhas do sistema de drenagem aberta. Após a interrupção do fluxo no extravasor, o volume total da perda de contenção primária foi estimado em 5,575m³. Deste volume, 5,5m³ ficaram contidos na plataforma e foram recuperados. O volume calculado de descarga no mar foi de 0,075 m³. | Z15: Encaminhamento da tubulação de dreno da centrífuga inadequado. | AA15: Mar aberto, além de 12 MN da costa. | AB15: Petrobras | AC15: 33000167100750 | AD15: 1 | AE15: Petrobras | AH15: S | AI15: N | AJ15: S | AK15: Paramos a limpeza da área industrial, efetuamos limpeza nos filtros do TD (Tubo de Despejo) e realizamos coleta para análise de TOG. Por volta das 19:30 foi efetuada a parada dos principais equipamentos consumidores de diesel constatando-se a interrupção do fluxo no extravasor. Após análise da equipe foi confirmado que o fluxo principal era proveniente de um alinhamento inadvertido na descarga da centrífuga de diesel, que foi corrigido imediatamente. | AL15: Situação normalizada. Plataforma em descomissionamento. | AM15: PETROBRAS - PETROLEO BRASILEIRO S.A. | AQ15: crisguerreiro@petrobras.com.br | AT15: PETROBRAS 18 | AW15: Paralisada | AX15: =IFERROR(FIND("Óbitos/feridos",consulta_completa__11[[#This Row],[13 - Ocorrências/Ambientes Atingidos]]),0) -> 0 | AY15: =IF(AX15=0,"","X") | AZ15: =IFERROR(FIND("População afetada/evacuada",consulta_completa__11[[#This Row],[13 - Ocorrências/Ambientes Atingidos]]),0) -> 0 | BA15: =IF(AZ15=0,"","X") | BB15: =IFERROR(FIND("Suspensão de abastecimento de água",consulta_completa__11[[#This Row],[13 - Ocorrências/Ambientes Atingidos]]),0) -> 0 | BC15: =IF(BB15=0,"","X") | BD15: =IFERROR(FIND("Rio/córrego",consulta_completa__11[[#This Row],[13 - Ocorrências/Ambientes Atingidos]]),0) -> 0 | BE15: =IF(BD15=0,"","X") | BF15: =IFERROR(FIND("Lago",consulta_completa__11[[#This Row],[13 - Ocorrências/Ambientes Atingidos]]),0) -> 0 | BG15: =IF(BF15=0,"","X") | BH15: =IFERROR(FIND("Mar",consulta_completa__11[[#This Row],[13 - Ocorrências/Ambientes Atingidos]]),0) -> 1 | BI15: =IF(BH15=0,"","X") -> X | BJ15: =IFERROR(FIND("Praia",consulta_completa__11[[#This Row],[13 - Ocorrências/Ambientes Atingidos]]),0) -> 0 | BK15: =IF(BJ15=0,"","X") | BL15: =IFERROR(FIND("Solo",consulta_completa__11[[#This Row],[13 - Ocorrências/Ambientes Atingidos]]),0) -> 0 | BM15: =IF(BL15=0,"","X") | BN15: =IFERROR(FIND("Águas subterrâneas",consulta_completa__11[[#This Row],[13 - Ocorrências/Ambientes Atingidos]]),0) -> 0 | BO15: =IF(BN15=0,"","X") | BP15: =IFERROR(FIND("Atmosfera",consulta_completa__11[[#This Row],[13 - Ocorrências/Ambientes Atingidos]]),0) -> 0 | BQ15: =IF(BP15=0,"","X") | BR15: =IFERROR(FIND("Flora",consulta_completa__11[[#This Row],[13 - Ocorrências/Ambientes Atingidos]]),0) -> 0 | BS15: =IF(BR15=0,"","X") | BT15: =IFERROR(FIND("Fauna",consulta_completa__11[[#This Row],[13 - Ocorrências/Ambientes Atingidos]]),0) -> 0 | BU15: =IF(BT15=0,"","X") | BV15: =IFERROR(FIND("UC federal",consulta_completa__11[[#This Row],[13 - Ocorrências/Ambientes Atingidos]]),0) -> 0 | BW15: =IF(BV15=0,"","X") | BX15: =IFERROR(FIND("UC estadual/municipal",consulta_completa__11[[#This Row],[13 - Ocorrências/Ambientes Atingidos]]),0) -> 0 | BY15: =IF(BX15=0,"","X") | BZ15: =IFERROR(FIND("Outro(s)",consulta_completa__11[[#This Row],[13 - Ocorrências/Ambientes Atingidos]]),0) -> 0 | CA15: =IF(BZ15=0,"","X") | CB15: =IFERROR(FIND("Sem dano",consulta_completa__11[[#This Row],[13 - Ocorrências/Ambientes Atingidos]]),0) -> 0 | CC15: =IF(CB15=0,"","X") | CD15: =IF(consulta_completa__11[[#This Row],[13 - Ocorrências/Ambientes Atingidos]]="","X","") | CE15: =IFERROR(FIND("IBAMA",consulta_completa__11[[#This Row],[14 - Inst. Atuando no Local]]),0) -> 0 | CF15: =IF(CE15=0,"","X") | CG15: =IFERROR(FIND("OEMA",consulta_completa__11[[#This Row],[14 - Inst. Atuando no Local]]),0) -> 0 | CH15: =IF(CG15=0,"","X") | CI15: =IFERROR(FIND("DEFESA CIVIL",consulta_completa__11[[#This Row],[14 - Inst. Atuando no Local]]),0) -> 0 | CJ15: =IF(CI15=0,"","X") | CK15: =IFERROR(FIND("CORPO DE BOMBEIROS",consulta_completa__11[[#This Row],[14 - Inst. Atuando no Local]]),0) -> 0 | CL15: =IF(CK15=0,"","X") | CM15: =IFERROR(FIND("POLÍCIA RODOVIÁRIA",consulta_completa__11[[#This Row],[14 - Inst. Atuando no Local]]),0) -> 0 | CN15: =IF(CM15=0,"","X") | CO15: =IFERROR(FIND("POLÍCIA MILITAR",consulta_completa__11[[#This Row],[14 - Inst. Atuando no Local]]),0) -> 0 | CP15: =IF(CO15=0,"","X") | CQ15: =IFERROR(FIND("POLÍCIA CIVIL",consulta_completa__11[[#This Row],[14 - Inst. Atuando no Local]]),0) -> 0 | CR15: =IF(CQ15=0,"","X") | CS15: =IFERROR(FIND("MARINHA DO BRASIL",consulta_completa__11[[#This Row],[14 - Inst. Atuando no Local]]),0) -> 0 | CT15: =IF(CS15=0,"","X") | CU15: =IFERROR(FIND("EMPRESA ESPECIALIZADA EM ATENDIMENTO",consulta_completa__11[[#This Row],[14 - Inst. Atuando no Local]]),0) -> 0 | CV15: =IF(CU15=0,"","X") | CW15: =IFERROR(FIND("IBAMA",consulta_completa__11[[#This Row],[14 - Inst. Atuando no Local]]),0) -> 0 | CX15: =IF(CW15=0,"","X") | CY15: =IF(consulta_completa__11[[#This Row],[14 - Inst. Atuando no Local]]="","X","") | CZ15: =IFERROR(FIND("OUTRA (S)",consulta_completa__11[[#This Row],[14 - Inst. Atuando no Local]]),0) -> 0 | DA15: =IF(CZ15=0,"","X") | DB15: =IF(AH$2="","",IF(AH$2="S","Sim",IF(AH$2="N","Não", IF(AH$2="I","Sem Informação")))) -> Sim | DC15: =IF(AI$2="","",IF(AI$2="S","Sim",IF(AI$2="N","Não", IF(AI$2="I","Sem Informação")))) -> Não | DD15: =IF(AJ$2="","",IF(AJ$2="S","Sim",IF(AJ$2="N","Não", IF(AJ$2="I","Sem Informação")))) -> Sim | DE15: =IF(AD15=1,"Federal",IF(AD15=2,"Estadual",IF(AD15=0,"Sem informação",""))) -> Federal
A16: 20251914447 | B16: 45663 | C16: null | D16: null | E16: Terminal/portos/ancoradouros/etc | F16: Derramamento de líquidos | J16: fluido hidralico; água | K16: 0.08; 2.68 | L16: M3; M3 | M16: Mar | N16: Outra(s) | P16: Segunda | Q16: Noturno | R16: Não | S16: Campos | T16: NS-60 (DEEPWATER AQUILA) em operação no poço 1-RJS-761(1-BRSA-1394-RJS) , Norte de Brava. Bacia de Campos. | U16: Durante teste funcional do sistema acústico na instalação do BOP, foi constatado vazamento no sistema de acionamento da gaveta cega-cisalhante inferior do BOP (LBSR). Após uma investigação mais profunda para determinar a origem do vazamento, foi identificado vazamento na função de fechamento da gaveta cega-cisalhante inferior também quando acionada pelo sistema EHBS (Emergency Hydraulic Back Up System). Descarga de fluido estimada em 2,76³ de fluido hidráulico base água. | V16: Descarga de fluido estimada em 2,76³ de fluido hidráulico base água | Z16: Vazamento em uma shuttle valve. | AB16: Petrobras | AC16: 33000167100750 | AD16: 1 | AE16: Petrobras | AH16: S | AI16: N | AJ16: S | AK16: Decidido por interromper as operações em andamento (montagem e descida do BHA de perfuração) para efetuar a retirada do BOP até a superfície para reparo. | AL16: 1) Volume estimado de fluido Stack Magic (97% água industrial + 3% ERIFON) vazado durante os testes: 730 gal = 2,76 m³ (2,68 m³ de água + 0,08 m³ de fluido hidráulico base aquosa); Memória de cálculo: [Volume consumido nos tanques para recarga dos acumuladores] %u2013 [Volume de abertura das gavetas durante os testes]. 2) O Poço está abandonado temporariamente na fase de THD (Top Hole Drilling). 3) Relatório de gestão de mudança com análise do risco não anexado devido retirada de BOP para reparo. 4) Composição química da substância, para substância nociva ou perigosa: Etileno glicol: 24,00 - 36,00% ; Monoetanolamina: 4,00 - 6,00%; Dietanolamina: 3,94 - 5,91% 5) Parte que falhou: Controles do BOP Instalados no Conjunto (Stack); 6) Data do último teste no BOP: 06/01/2025. | AM16: PETROBRAS - PETROLEO BRASILEIRO S.A. | AQ16: crisguerreiro@petrobras.com.br | AX16: =IFERROR(FIND("Óbitos/feridos",consulta_completa__11[[#This Row],[13 - Ocorrências/Ambientes Atingidos]]),0) -> 0 | AY16: =IF(AX16=0,"","X") | AZ16: =IFERROR(FIND("População afetada/evacuada",consulta_completa__11[[#This Row],[13 - Ocorrências/Ambientes Atingidos]]),0) -> 0 | BA16: =IF(AZ16=0,"","X") | BB16: =IFERROR(FIND("Suspensão de abastecimento de água",consulta_completa__11[[#This Row],[13 - Ocorrências/Ambientes Atingidos]]),0) -> 0 | BC16: =IF(BB16=0,"","X") | BD16: =IFERROR(FIND("Rio/córrego",consulta_completa__11[[#This Row],[13 - Ocorrências/Ambientes Atingidos]]),0) -> 0 | BE16: =IF(BD16=0,"","X") | BF16: =IFERROR(FIND("Lago",consulta_completa__11[[#This Row],[13 - Ocorrências/Ambientes Atingidos]]),0) -> 0 | BG16: =IF(BF16=0,"","X") | BH16: =IFERROR(FIND("Mar",consulta_completa__11[[#This Row],[13 - Ocorrências/Ambientes Atingidos]]),0) -> 1 | BI16: =IF(BH16=0,"","X") -> X | BJ16: =IFERROR(FIND("Praia",consulta_completa__11[[#This Row],[13 - Ocorrências/Ambientes Atingidos]]),0) -> 0 | BK16: =IF(BJ16=0,"","X") | BL16: =IFERROR(FIND("Solo",consulta_completa__11[[#This Row],[13 - Ocorrências/Ambientes Atingidos]]),0) -> 0 | BM16: =IF(BL16=0,"","X") | BN16: =IFERROR(FIND("Águas subterrâneas",consulta_completa__11[[#This Row],[13 - Ocorrências/Ambientes Atingidos]]),0) -> 0 | BO16: =IF(BN16=0,"","X") | BP16: =IFERROR(FIND("Atmosfera",consulta_completa__11[[#This Row],[13 - Ocorrências/Ambientes Atingidos]]),0) -> 0 | BQ16: =IF(BP16=0,"","X") | BR16: =IFERROR(FIND("Flora",consulta_completa__11[[#This Row],[13 - Ocorrências/Ambientes Atingidos]]),0) -> 0 | BS16: =IF(BR16=0,"","X") | BT16: =IFERROR(FIND("Fauna",consulta_completa__11[[#This Row],[13 - Ocorrências/Ambientes Atingidos]]),0) -> 0 | BU16: =IF(BT16=0,"","X") | BV16: =IFERROR(FIND("UC federal",consulta_completa__11[[#This Row],[13 - Ocorrências/Ambientes Atingidos]]),0) -> 0 | BW16: =IF(BV16=0,"","X") | BX16: =IFERROR(FIND("UC estadual/municipal",consulta_completa__11[[#This Row],[13 - Ocorrências/Ambientes Atingidos]]),0) -> 0 | BY16: =IF(BX16=0,"","X") | BZ16: =IFERROR(FIND("Outro(s)",consulta_completa__11[[#This Row],[13 - Ocorrências/Ambientes Atingidos]]),0) -> 0 | CA16: =IF(BZ16=0,"","X") | CB16: =IFERROR(FIND("Sem dano",consulta_completa__11[[#This Row],[13 - Ocorrências/Ambientes Atingidos]]),0) -> 0 | CC16: =IF(CB16=0,"","X") | CD16: =IF(consulta_completa__11[[#This Row],[13 - Ocorrências/Ambientes Atingidos]]="","X","") | CE16: =IFERROR(FIND("IBAMA",consulta_completa__11[[#This Row],[14 - Inst. Atuando no Local]]),0) -> 0 | CF16: =IF(CE16=0,"","X") | CG16: =IFERROR(FIND("OEMA",consulta_completa__11[[#This Row],[14 - Inst. Atuando no Local]]),0) -> 0 | CH16: =IF(CG16=0,"","X") | CI16: =IFERROR(FIND("DEFESA CIVIL",consulta_completa__11[[#This Row],[14 - Inst. Atuando no Local]]),0) -> 0 | CJ16: =IF(CI16=0,"","X") | CK16: =IFERROR(FIND("CORPO DE BOMBEIROS",consulta_completa__11[[#This Row],[14 - Inst. Atuando no Local]]),0) -> 0 | CL16: =IF(CK16=0,"","X") | CM16: =IFERROR(FIND("POLÍCIA RODOVIÁRIA",consulta_completa__11[[#This Row],[14 - Inst. Atuando no Local]]),0) -> 0 | CN16: =IF(CM16=0,"","X") | CO16: =IFERROR(FIND("POLÍCIA MILITAR",consulta_completa__11[[#This Row],[14 - Inst. Atuando no Local]]),0) -> 0 | CP16: =IF(CO16=0,"","X") | CQ16: =IFERROR(FIND("POLÍCIA CIVIL",consulta_completa__11[[#This Row],[14 - Inst. Atuando no Local]]),0) -> 0 | CR16: =IF(CQ16=0,"","X") | CS16: =IFERROR(FIND("MARINHA DO BRASIL",consulta_completa__11[[#This Row],[14 - Inst. Atuando no Local]]),0) -> 0 | CT16: =IF(CS16=0,"","X") | CU16: =IFERROR(FIND("EMPRESA ESPECIALIZADA EM ATENDIMENTO",consulta_completa__11[[#This Row],[14 - Inst. Atuando no Local]]),0) -> 0 | CV16: =IF(CU16=0,"","X") | CW16: =IFERROR(FIND("IBAMA",consulta_completa__11[[#This Row],[14 - Inst. Atuando no Local]]),0) -> 0 | CX16: =IF(CW16=0,"","X") | CY16: =IF(consulta_completa__11[[#This Row],[14 - Inst. Atuando no Local]]="","X","") | CZ16: =IFERROR(FIND("OUTRA (S)",consulta_completa__11[[#This Row],[14 - Inst. Atuando no Local]]),0) -> 0 | DA16: =IF(CZ16=0,"","X") | DB16: =IF(AH$2="","",IF(AH$2="S","Sim",IF(AH$2="N","Não", IF(AH$2="I","Sem Informação")))) -> Sim | DC16: =IF(AI$2="","",IF(AI$2="S","Sim",IF(AI$2="N","Não", IF(AI$2="I","Sem Informação")))) -> Não | DD16: =IF(AJ$2="","",IF(AJ$2="S","Sim",IF(AJ$2="N","Não", IF(AJ$2="I","Sem Informação")))) -> Sim | DE16: =IF(AD16=1,"Federal",IF(AD16=2,"Estadual",IF(AD16=0,"Sem informação",""))) -> Federal
A17: 202511621617 | B17: 45663 | C17: Paracatu | D17: MG | E17: Outro(s) | F17: Derramamento de líquidos | J17: Dejeitos de bovinos | M17: Rio/córrego | N17: Polícia Militar | O17: Outra(s) fonte(s) | P17: Segunda | Q17: Madrugada | R17: Não | T17: Fazenda Ambrósio | U17: Zona rural de Paracatu/MG. Processo Sei! 02001.001563/2025-05. | V17: Contaminação de recurso hídrico por efluentes líquidos gerados nas baias de confinamento de bovinos. Segundo informações repassadas ao NEA, na madrugada entre os dias 05 e 06/01/2025, ocorreu transbordamento dos tanques de recebimento do efluente líquido gerado nas baias de confinamento do gado. | Z17: O rompimento das baias pode ter sido causado pelas fortes chuvas que ocorreram na região. | AA17: Córrego do Sabão. | AB17: Fazenda Ambrósio | AD17: 0 | AI17: N | AJ17: N | AL17: Os tanques de dejetos bovinos, em número de 4, foram escavados no solo, sem qualquer tipo de proteção (impermeabilização). | AM17: Mariana Rivetti Ribeiro De Carvalho | AN17: Ibama | AO17: Analista Ambiental | AP17: 31987239130 | AQ17: mariana.carvalho@ibama.gov.br | AX17: =IFERROR(FIND("Óbitos/feridos",consulta_completa__11[[#This Row],[13 - Ocorrências/Ambientes Atingidos]]),0) -> 0 | AY17: =IF(AX17=0,"","X") | AZ17: =IFERROR(FIND("População afetada/evacuada",consulta_completa__11[[#This Row],[13 - Ocorrências/Ambientes Atingidos]]),0) -> 0 | BA17: =IF(AZ17=0,"","X") | BB17: =IFERROR(FIND("Suspensão de abastecimento de água",consulta_completa__11[[#This Row],[13 - Ocorrências/Ambientes Atingidos]]),0) -> 0 | BC17: =IF(BB17=0,"","X") | BD17: =IFERROR(FIND("Rio/córrego",consulta_completa__11[[#This Row],[13 - Ocorrências/Ambientes Atingidos]]),0) -> 1 | BE17: =IF(BD17=0,"","X") -> X | BF17: =IFERROR(FIND("Lago",consulta_completa__11[[#This Row],[13 - Ocorrências/Ambientes Atingidos]]),0) -> 0 | BG17: =IF(BF17=0,"","X") | BH17: =IFERROR(FIND("Mar",consulta_completa__11[[#This Row],[13 - Ocorrências/Ambientes Atingidos]]),0) -> 0 | BI17: =IF(BH17=0,"","X") | BJ17: =IFERROR(FIND("Praia",consulta_completa__11[[#This Row],[13 - Ocorrências/Ambientes Atingidos]]),0) -> 0 | BK17: =IF(BJ17=0,"","X") | BL17: =IFERROR(FIND("Solo",consulta_completa__11[[#This Row],[13 - Ocorrências/Ambientes Atingidos]]),0) -> 0 | BM17: =IF(BL17=0,"","X") | BN17: =IFERROR(FIND("Águas subterrâneas",consulta_completa__11[[#This Row],[13 - Ocorrências/Ambientes Atingidos]]),0) -> 0 | BO17: =IF(BN17=0,"","X") | BP17: =IFERROR(FIND("Atmosfera",consulta_completa__11[[#This Row],[13 - Ocorrências/Ambientes Atingidos]]),0) -> 0 | BQ17: =IF(BP17=0,"","X") | BR17: =IFERROR(FIND("Flora",consulta_completa__11[[#This Row],[13 - Ocorrências/Ambientes Atingidos]]),0) -> 0 | BS17: =IF(BR17=0,"","X") | BT17: =IFERROR(FIND("Fauna",consulta_completa__11[[#This Row],[13 - Ocorrências/Ambientes Atingidos]]),0) -> 0 | BU17: =IF(BT17=0,"","X") | BV17: =IFERROR(FIND("UC federal",consulta_completa__11[[#This Row],[13 - Ocorrências/Ambientes Atingidos]]),0) -> 0 | BW17: =IF(BV17=0,"","X") | BX17: =IFERROR(FIND("UC estadual/municipal",consulta_completa__11[[#This Row],[13 - Ocorrências/Ambientes Atingidos]]),0) -> 0 | BY17: =IF(BX17=0,"","X") | BZ17: =IFERROR(FIND("Outro(s)",consulta_completa__11[[#This Row],[13 - Ocorrências/Ambientes Atingidos]]),0) -> 0 | CA17: =IF(BZ17=0,"","X") | CB17: =IFERROR(FIND("Sem dano",consulta_completa__11[[#This Row],[13 - Ocorrências/Ambientes Atingidos]]),0) -> 0 | CC17: =IF(CB17=0,"","X") | CD17: =IF(consulta_completa__11[[#This Row],[13 - Ocorrências/Ambientes Atingidos]]="","X","") | CE17: =IFERROR(FIND("IBAMA",consulta_completa__11[[#This Row],[14 - Inst. Atuando no Local]]),0) -> 0 | CF17: =IF(CE17=0,"","X") | CG17: =IFERROR(FIND("OEMA",consulta_completa__11[[#This Row],[14 - Inst. Atuando no Local]]),0) -> 0 | CH17: =IF(CG17=0,"","X") | CI17: =IFERROR(FIND("DEFESA CIVIL",consulta_completa__11[[#This Row],[14 - Inst. Atuando no Local]]),0) -> 0 | CJ17: =IF(CI17=0,"","X") | CK17: =IFERROR(FIND("CORPO DE BOMBEIROS",consulta_completa__11[[#This Row],[14 - Inst. Atuando no Local]]),0) -> 0 | CL17: =IF(CK17=0,"","X") | CM17: =IFERROR(FIND("POLÍCIA RODOVIÁRIA",consulta_completa__11[[#This Row],[14 - Inst. Atuando no Local]]),0) -> 0 | CN17: =IF(CM17=0,"","X") | CO17: =IFERROR(FIND("POLÍCIA MILITAR",consulta_completa__11[[#This Row],[14 - Inst. Atuando no Local]]),0) -> 0 | CP17: =IF(CO17=0,"","X") | CQ17: =IFERROR(FIND("POLÍCIA CIVIL",consulta_completa__11[[#This Row],[14 - Inst. Atuando no Local]]),0) -> 0 | CR17: =IF(CQ17=0,"","X") | CS17: =IFERROR(FIND("MARINHA DO BRASIL",consulta_completa__11[[#This Row],[14 - Inst. Atuando no Local]]),0) -> 0 | CT17: =IF(CS17=0,"","X") | CU17: =IFERROR(FIND("EMPRESA ESPECIALIZADA EM ATENDIMENTO",consulta_completa__11[[#This Row],[14 - Inst. Atuando no Local]]),0) -> 0 | CV17: =IF(CU17=0,"","X") | CW17: =IFERROR(FIND("IBAMA",consulta_completa__11[[#This Row],[14 - Inst. Atuando no Local]]),0) -> 0 | CX17: =IF(CW17=0,"","X") | CY17: =IF(consulta_completa__11[[#This Row],[14 - Inst. Atuando no Local]]="","X","") | CZ17: =IFERROR(FIND("OUTRA (S)",consulta_completa__11[[#This Row],[14 - Inst. Atuando no Local]]),0) -> 0 | DA17: =IF(CZ17=0,"","X") | DB17: =IF(AH$2="","",IF(AH$2="S","Sim",IF(AH$2="N","Não", IF(AH$2="I","Sem Informação")))) -> Sim | DC17: =IF(AI$2="","",IF(AI$2="S","Sim",IF(AI$2="N","Não", IF(AI$2="I","Sem Informação")))) -> Não | DD17: =IF(AJ$2="","",IF(AJ$2="S","Sim",IF(AJ$2="N","Não", IF(AJ$2="I","Sem Informação")))) -> Sim | DE17: =IF(AD17=1,"Federal",IF(AD17=2,"Estadual",IF(AD17=0,"Sem informação",""))) -> Sem informação
A18: 202512736016 | B18: 45663 | C18: Triunfo Potiguar | D18: RN | E18: Plataforma | F18: Derramamento de líquidos | J18: Água de injeção | K18: 0.24 | L18: M3 | M18: Solo | O18: Comunicado da empresa/responsável | P18: Segunda | Q18: Matutino | R18: Não | T18: Linha de Injeção 6"x150 da Estação Coletora de Baixa do Algodão no Campo Baixa do Algodão. | U18: Descarga significante de água de injeção Perda de contenção primária significante de água de injeção | V18: Por volta das 10:50h o operador de campo em sua rotina diária detectou um vazamento de água de injeção na linha 6"x150 aço, trecho aéreo. | Z18: Corrosão | AA18: 1)0,24m³. 2)Solo. 3) e 4) N/A. 5)Salinidade: 17.799ppm. Temperatura: 45ºC 7) a 11)N/A. | Volume da perda de contenção: 0,24m³. Metodologia de cálculo = área x lâmina: (12m² x 0,02m) = 0,24m³. | AB18: POTIGUAR E&P S.A | AC18: 30759670000157 | AD18: 2 | AH18: I | AI18: N | AJ18: S | AK18: Realizada as devidas comunicações internas. | AM18: Gunther Barbosa | AN18: IBAMA | AO18: Analista Ambiental | AQ18: gunther.barbosa@ibama.gov.br | AT18: ESTAÇÃO COLETORA DE BAIXA DO ALGODÃO | AW18: Paralisada | AX18: =IFERROR(FIND("Óbitos/feridos",consulta_completa__11[[#This Row],[13 - Ocorrências/Ambientes Atingidos]]),0) -> 0 | AY18: =IF(AX18=0,"","X") | AZ18: =IFERROR(FIND("População afetada/evacuada",consulta_completa__11[[#This Row],[13 - Ocorrências/Ambientes Atingidos]]),0) -> 0 | BA18: =IF(AZ18=0,"","X") | BB18: =IFERROR(FIND("Suspensão de abastecimento de água",consulta_completa__11[[#This Row],[13 - Ocorrências/Ambientes Atingidos]]),0) -> 0 | BC18: =IF(BB18=0,"","X") | BD18: =IFERROR(FIND("Rio/córrego",consulta_completa__11[[#This Row],[13 - Ocorrências/Ambientes Atingidos]]),0) -> 0 | BE18: =IF(BD18=0,"","X") | BF18: =IFERROR(FIND("Lago",consulta_completa__11[[#This Row],[13 - Ocorrências/Ambientes Atingidos]]),0) -> 0 | BG18: =IF(BF18=0,"","X") | BH18: =IFERROR(FIND("Mar",consulta_completa__11[[#This Row],[13 - Ocorrências/Ambientes Atingidos]]),0) -> 0 | BI18: =IF(BH18=0,"","X") | BJ18: =IFERROR(FIND("Praia",consulta_completa__11[[#This Row],[13 - Ocorrências/Ambientes Atingidos]]),0) -> 0 | BK18: =IF(BJ18=0,"","X") | BL18: =IFERROR(FIND("Solo",consulta_completa__11[[#This Row],[13 - Ocorrências/Ambientes Atingidos]]),0) -> 1 | BM18: =IF(BL18=0,"","X") -> X | BN18: =IFERROR(FIND("Águas subterrâneas",consulta_completa__11[[#This Row],[13 - Ocorrências/Ambientes Atingidos]]),0) -> 0 | BO18: =IF(BN18=0,"","X") | BP18: =IFERROR(FIND("Atmosfera",consulta_completa__11[[#This Row],[13 - Ocorrências/Ambientes Atingidos]]),0) -> 0 | BQ18: =IF(BP18=0,"","X") | BR18: =IFERROR(FIND("Flora",consulta_completa__11[[#This Row],[13 - Ocorrências/Ambientes Atingidos]]),0) -> 0 | BS18: =IF(BR18=0,"","X") | BT18: =IFERROR(FIND("Fauna",consulta_completa__11[[#This Row],[13 - Ocorrências/Ambientes Atingidos]]),0) -> 0 | BU18: =IF(BT18=0,"","X") | BV18: =IFERROR(FIND("UC federal",consulta_completa__11[[#This Row],[13 - Ocorrências/Ambientes Atingidos]]),0) -> 0 | BW18: =IF(BV18=0,"","X") | BX18: =IFERROR(FIND("UC estadual/municipal",consulta_completa__11[[#This Row],[13 - Ocorrências/Ambientes Atingidos]]),0) -> 0 | BY18: =IF(BX18=0,"","X") | BZ18: =IFERROR(FIND("Outro(s)",consulta_completa__11[[#This Row],[13 - Ocorrências/Ambientes Atingidos]]),0) -> 0 | CA18: =IF(BZ18=0,"","X") | CB18: =IFERROR(FIND("Sem dano",consulta_completa__11[[#This Row],[13 - Ocorrências/Ambientes Atingidos]]),0) -> 0 | CC18: =IF(CB18=0,"","X") | CD18: =IF(consulta_completa__11[[#This Row],[13 - Ocorrências/Ambientes Atingidos]]="","X","") | CE18: =IFERROR(FIND("IBAMA",consulta_completa__11[[#This Row],[14 - Inst. Atuando no Local]]),0) -> 0 | CF18: =IF(CE18=0,"","X") | CG18: =IFERROR(FIND("OEMA",consulta_completa__11[[#This Row],[14 - Inst. Atuando no Local]]),0) -> 0 | CH18: =IF(CG18=0,"","X") | CI18: =IFERROR(FIND("DEFESA CIVIL",consulta_completa__11[[#This Row],[14 - Inst. Atuando no Local]]),0) -> 0 | CJ18: =IF(CI18=0,"","X") | CK18: =IFERROR(FIND("CORPO DE BOMBEIROS",consulta_completa__11[[#This Row],[14 - Inst. Atuando no Local]]),0) -> 0 | CL18: =IF(CK18=0,"","X") | CM18: =IFERROR(FIND("POLÍCIA RODOVIÁRIA",consulta_completa__11[[#This Row],[14 - Inst. Atuando no Local]]),0) -> 0 | CN18: =IF(CM18=0,"","X") | CO18: =IFERROR(FIND("POLÍCIA MILITAR",consulta_completa__11[[#This Row],[14 - Inst. Atuando no Local]]),0) -> 0 | CP18: =IF(CO18=0,"","X") | CQ18: =IFERROR(FIND("POLÍCIA CIVIL",consulta_completa__11[[#This Row],[14 - Inst. Atuando no Local]]),0) -> 0 | CR18: =IF(CQ18=0,"","X") | CS18: =IFERROR(FIND("MARINHA DO BRASIL",consulta_completa__11[[#This Row],[14 - Inst. Atuando no Local]]),0) -> 0 | CT18: =IF(CS18=0,"","X") | CU18: =IFERROR(FIND("EMPRESA ESPECIALIZADA EM ATENDIMENTO",consulta_completa__11[[#This Row],[14 - Inst. Atuando no Local]]),0) -> 0 | CV18: =IF(CU18=0,"","X") | CW18: =IFERROR(FIND("IBAMA",consulta_completa__11[[#This Row],[14 - Inst. Atuando no Local]]),0) -> 0 | CX18: =IF(CW18=0,"","X") | CY18: =IF(consulta_completa__11[[#This Row],[14 - Inst. Atuando no Local]]="","X","") -> X | CZ18: =IFERROR(FIND("OUTRA (S)",consulta_completa__11[[#This Row],[14 - Inst. Atuando no Local]]),0) -> 0 | DA18: =IF(CZ18=0,"","X") | DB18: =IF(AH$2="","",IF(AH$2="S","Sim",IF(AH$2="N","Não", IF(AH$2="I","Sem Informação")))) -> Sim | DC18: =IF(AI$2="","",IF(AI$2="S","Sim",IF(AI$2="N","Não", IF(AI$2="I","Sem Informação")))) -> Não | DD18: =IF(AJ$2="","",IF(AJ$2="S","Sim",IF(AJ$2="N","Não", IF(AJ$2="I","Sem Informação")))) -> Sim | DE18: =IF(AD18=1,"Federal",IF(AD18=2,"Estadual",IF(AD18=0,"Sem informação",""))) -> Estadual
A19: 20251764838 | B19: 45664 | C19: Votuporanga | D19: SP | E19: Ferrovia | J19: Farelo de soja | M19: Solo | N19: Empresa especializada em atendimento | O19: Comunicado da empresa/responsável | P19: Terça | Q19: Vespertino | R19: Não | T19: Km ferroviário 302+200 | U19: Descarrilamento de vagões graneleiros. | W19: TRUE | AB19: Rumo Malha Paulista | AD19: 1 | AE19: Equipes atuando no local. | AF19: Pedro Afonso | AG19: (16) 99179-7303 | AH19: S | AI19: N | AJ19: N | AM19: Celso Morais | AN19: Rumo Malha Paulista | AO19: Coordenador de Gestão Ambiental | AP19: 11981320058 | AQ19: celso.morais@rumolog.com | AX19: =IFERROR(FIND("Óbitos/feridos",consulta_completa__11[[#This Row],[13 - Ocorrências/Ambientes Atingidos]]),0) -> 0 | AY19: =IF(AX19=0,"","X") | AZ19: =IFERROR(FIND("População afetada/evacuada",consulta_completa__11[[#This Row],[13 - Ocorrências/Ambientes Atingidos]]),0) -> 0 | BA19: =IF(AZ19=0,"","X") | BB19: =IFERROR(FIND("Suspensão de abastecimento de água",consulta_completa__11[[#This Row],[13 - Ocorrências/Ambientes Atingidos]]),0) -> 0 | BC19: =IF(BB19=0,"","X") | BD19: =IFERROR(FIND("Rio/córrego",consulta_completa__11[[#This Row],[13 - Ocorrências/Ambientes Atingidos]]),0) -> 0 | BE19: =IF(BD19=0,"","X") | BF19: =IFERROR(FIND("Lago",consulta_completa__11[[#This Row],[13 - Ocorrências/Ambientes Atingidos]]),0) -> 0 | BG19: =IF(BF19=0,"","X") | BH19: =IFERROR(FIND("Mar",consulta_completa__11[[#This Row],[13 - Ocorrências/Ambientes Atingidos]]),0) -> 0 | BI19: =IF(BH19=0,"","X") | BJ19: =IFERROR(FIND("Praia",consulta_completa__11[[#This Row],[13 - Ocorrências/Ambientes Atingidos]]),0) -> 0 | BK19: =IF(BJ19=0,"","X") | BL19: =IFERROR(FIND("Solo",consulta_completa__11[[#This Row],[13 - Ocorrências/Ambientes Atingidos]]),0) -> 1 | BM19: =IF(BL19=0,"","X") -> X | BN19: =IFERROR(FIND("Águas subterrâneas",consulta_completa__11[[#This Row],[13 - Ocorrências/Ambientes Atingidos]]),0) -> 0 | BO19: =IF(BN19=0,"","X") | BP19: =IFERROR(FIND("Atmosfera",consulta_completa__11[[#This Row],[13 - Ocorrências/Ambientes Atingidos]]),0) -> 0 | BQ19: =IF(BP19=0,"","X") | BR19: =IFERROR(FIND("Flora",consulta_completa__11[[#This Row],[13 - Ocorrências/Ambientes Atingidos]]),0) -> 0 | BS19: =IF(BR19=0,"","X") | BT19: =IFERROR(FIND("Fauna",consulta_completa__11[[#This Row],[13 - Ocorrências/Ambientes Atingidos]]),0) -> 0 | BU19: =IF(BT19=0,"","X") | BV19: =IFERROR(FIND("UC federal",consulta_completa__11[[#This Row],[13 - Ocorrências/Ambientes Atingidos]]),0) -> 0 | BW19: =IF(BV19=0,"","X") | BX19: =IFERROR(FIND("UC estadual/municipal",consulta_completa__11[[#This Row],[13 - Ocorrências/Ambientes Atingidos]]),0) -> 0 | BY19: =IF(BX19=0,"","X") | BZ19: =IFERROR(FIND("Outro(s)",consulta_completa__11[[#This Row],[13 - Ocorrências/Ambientes Atingidos]]),0) -> 0 | CA19: =IF(BZ19=0,"","X") | CB19: =IFERROR(FIND("Sem dano",consulta_completa__11[[#This Row],[13 - Ocorrências/Ambientes Atingidos]]),0) -> 0 | CC19: =IF(CB19=0,"","X") | CD19: =IF(consulta_completa__11[[#This Row],[13 - Ocorrências/Ambientes Atingidos]]="","X","") | CE19: =IFERROR(FIND("IBAMA",consulta_completa__11[[#This Row],[14 - Inst. Atuando no Local]]),0) -> 0 | CF19: =IF(CE19=0,"","X") | CG19: =IFERROR(FIND("OEMA",consulta_completa__11[[#This Row],[14 - Inst. Atuando no Local]]),0) -> 0 | CH19: =IF(CG19=0,"","X") | CI19: =IFERROR(FIND("DEFESA CIVIL",consulta_completa__11[[#This Row],[14 - Inst. Atuando no Local]]),0) -> 0 | CJ19: =IF(CI19=0,"","X") | CK19: =IFERROR(FIND("CORPO DE BOMBEIROS",consulta_completa__11[[#This Row],[14 - Inst. Atuando no Local]]),0) -> 0 | CL19: =IF(CK19=0,"","X") | CM19: =IFERROR(FIND("POLÍCIA RODOVIÁRIA",consulta_completa__11[[#This Row],[14 - Inst. Atuando no Local]]),0) -> 0 | CN19: =IF(CM19=0,"","X") | CO19: =IFERROR(FIND("POLÍCIA MILITAR",consulta_completa__11[[#This Row],[14 - Inst. Atuando no Local]]),0) -> 0 | CP19: =IF(CO19=0,"","X") | CQ19: =IFERROR(FIND("POLÍCIA CIVIL",consulta_completa__11[[#This Row],[14 - Inst. Atuando no Local]]),0) -> 0 | CR19: =IF(CQ19=0,"","X") | CS19: =IFERROR(FIND("MARINHA DO BRASIL",consulta_completa__11[[#This Row],[14 - Inst. Atuando no Local]]),0) -> 0 | CT19: =IF(CS19=0,"","X") | CU19: =IFERROR(FIND("EMPRESA ESPECIALIZADA EM ATENDIMENTO",consulta_completa__11[[#This Row],[14 - Inst. Atuando no Local]]),0) -> 0 | CV19: =IF(CU19=0,"","X") | CW19: =IFERROR(FIND("IBAMA",consulta_completa__11[[#This Row],[14 - Inst. Atuando no Local]]),0) -> 0 | CX19: =IF(CW19=0,"","X") | CY19: =IF(consulta_completa__11[[#This Row],[14 - Inst. Atuando no Local]]="","X","") | CZ19: =IFERROR(FIND("OUTRA (S)",consulta_completa__11[[#This Row],[14 - Inst. Atuando no Local]]),0) -> 0 | DA19: =IF(CZ19=0,"","X") | DB19: =IF(AH$2="","",IF(AH$2="S","Sim",IF(AH$2="N","Não", IF(AH$2="I","Sem Informação")))) -> Sim | DC19: =IF(AI$2="","",IF(AI$2="S","Sim",IF(AI$2="N","Não", IF(AI$2="I","Sem Informação")))) -> Não | DD19: =IF(AJ$2="","",IF(AJ$2="S","Sim",IF(AJ$2="N","Não", IF(AJ$2="I","Sem Informação")))) -> Sim | DE19: =IF(AD19=1,"Federal",IF(AD19=2,"Estadual",IF(AD19=0,"Sem informação",""))) -> Federal
A20: 20251764854 | B20: 45664 | C20: Cubatão | D20: SP | E20: Ferrovia | F20: Lançamento de sólidos | J20: Milho | K20: 110 | L20: T | M20: Solo | N20: Outra(s) | O20: Outra(s) fonte(s) | P20: Terça | Q20: Vespertino | R20: Não | U20: Vandalismo na ferrovia com abertura de bicas em 5 vagões graneleiros carregados com milho. | V20: Vandalismo com abertura de 5 vagões graneleiros carregados com milho. Lançamento de 110 toneladas de milho em grão sobre a linha férrea. | Z20: Ato criminoso caracterizado pela abertura de bicas em 5 vagões graneleiros ferroviário carregados com milho. | AA20: Solo dentro dos limites da área de domínio da linha férrea. | AB20: Rumo Logistica S. A. | AC20: 02502844000166 | AD20: 1 | AE20: Equipes de atendimento de limpeza, contratadas pela rumo, atuando no trecho afetado. | AH20: S | AI20: N | AJ20: S | AK20: Equipes de atendimento de limpeza, contratadas pela rumo, atuando no trecho afetado para remoção do material e liberação da via. | AM20: Eloisa Caxias Coelho | AN20: Rumo Logistica S. A. | AO20: Auditora Ambiental | AP20: 41988207121 | AQ20: eloisa.coelho@rumolog.com | AX20: =IFERROR(FIND("Óbitos/feridos",consulta_completa__11[[#This Row],[13 - Ocorrências/Ambientes Atingidos]]),0) -> 0 | AY20: =IF(AX20=0,"","X") | AZ20: =IFERROR(FIND("População afetada/evacuada",consulta_completa__11[[#This Row],[13 - Ocorrências/Ambientes Atingidos]]),0) -> 0 | BA20: =IF(AZ20=0,"","X") | BB20: =IFERROR(FIND("Suspensão de abastecimento de água",consulta_completa__11[[#This Row],[13 - Ocorrências/Ambientes Atingidos]]),0) -> 0 | BC20: =IF(BB20=0,"","X") | BD20: =IFERROR(FIND("Rio/córrego",consulta_completa__11[[#This Row],[13 - Ocorrências/Ambientes Atingidos]]),0) -> 0 | BE20: =IF(BD20=0,"","X") | BF20: =IFERROR(FIND("Lago",consulta_completa__11[[#This Row],[13 - Ocorrências/Ambientes Atingidos]]),0) -> 0 | BG20: =IF(BF20=0,"","X") | BH20: =IFERROR(FIND("Mar",consulta_completa__11[[#This Row],[13 - Ocorrências/Ambientes Atingidos]]),0) -> 0 | BI20: =IF(BH20=0,"","X") | BJ20: =IFERROR(FIND("Praia",consulta_completa__11[[#This Row],[13 - Ocorrências/Ambientes Atingidos]]),0) -> 0 | BK20: =IF(BJ20=0,"","X") | BL20: =IFERROR(FIND("Solo",consulta_completa__11[[#This Row],[13 - Ocorrências/Ambientes Atingidos]]),0) -> 1 | BM20: =IF(BL20=0,"","X") -> X | BN20: =IFERROR(FIND("Águas subterrâneas",consulta_completa__11[[#This Row],[13 - Ocorrências/Ambientes Atingidos]]),0) -> 0 | BO20: =IF(BN20=0,"","X") | BP20: =IFERROR(FIND("Atmosfera",consulta_completa__11[[#This Row],[13 - Ocorrências/Ambientes Atingidos]]),0) -> 0 | BQ20: =IF(BP20=0,"","X") | BR20: =IFERROR(FIND("Flora",consulta_completa__11[[#This Row],[13 - Ocorrências/Ambientes Atingidos]]),0) -> 0 | BS20: =IF(BR20=0,"","X") | BT20: =IFERROR(FIND("Fauna",consulta_completa__11[[#This Row],[13 - Ocorrências/Ambientes Atingidos]]),0) -> 0 | BU20: =IF(BT20=0,"","X") | BV20: =IFERROR(FIND("UC federal",consulta_completa__11[[#This Row],[13 - Ocorrências/Ambientes Atingidos]]),0) -> 0 | BW20: =IF(BV20=0,"","X") | BX20: =IFERROR(FIND("UC estadual/municipal",consulta_completa__11[[#This Row],[13 - Ocorrências/Ambientes Atingidos]]),0) -> 0 | BY20: =IF(BX20=0,"","X") | BZ20: =IFERROR(FIND("Outro(s)",consulta_completa__11[[#This Row],[13 - Ocorrências/Ambientes Atingidos]]),0) -> 0 | CA20: =IF(BZ20=0,"","X") | CB20: =IFERROR(FIND("Sem dano",consulta_completa__11[[#This Row],[13 - Ocorrências/Ambientes Atingidos]]),0) -> 0 | CC20: =IF(CB20=0,"","X") | CD20: =IF(consulta_completa__11[[#This Row],[13 - Ocorrências/Ambientes Atingidos]]="","X","") | CE20: =IFERROR(FIND("IBAMA",consulta_completa__11[[#This Row],[14 - Inst. Atuando no Local]]),0) -> 0 | CF20: =IF(CE20=0,"","X") | CG20: =IFERROR(FIND("OEMA",consulta_completa__11[[#This Row],[14 - Inst. Atuando no Local]]),0) -> 0 | CH20: =IF(CG20=0,"","X") | CI20: =IFERROR(FIND("DEFESA CIVIL",consulta_completa__11[[#This Row],[14 - Inst. Atuando no Local]]),0) -> 0 | CJ20: =IF(CI20=0,"","X") | CK20: =IFERROR(FIND("CORPO DE BOMBEIROS",consulta_completa__11[[#This Row],[14 - Inst. Atuando no Local]]),0) -> 0 | CL20: =IF(CK20=0,"","X") | CM20: =IFERROR(FIND("POLÍCIA RODOVIÁRIA",consulta_completa__11[[#This Row],[14 - Inst. Atuando no Local]]),0) -> 0 | CN20: =IF(CM20=0,"","X") | CO20: =IFERROR(FIND("POLÍCIA MILITAR",consulta_completa__11[[#This Row],[14 - Inst. Atuando no Local]]),0) -> 0 | CP20: =IF(CO20=0,"","X") | CQ20: =IFERROR(FIND("POLÍCIA CIVIL",consulta_completa__11[[#This Row],[14 - Inst. Atuando no Local]]),0) -> 0 | CR20: =IF(CQ20=0,"","X") | CS20: =IFERROR(FIND("MARINHA DO BRASIL",consulta_completa__11[[#This Row],[14 - Inst. Atuando no Local]]),0) -> 0 | CT20: =IF(CS20=0,"","X") | CU20: =IFERROR(FIND("EMPRESA ESPECIALIZADA EM ATENDIMENTO",consulta_completa__11[[#This Row],[14 - Inst. Atuando no Local]]),0) -> 0 | CV20: =IF(CU20=0,"","X") | CW20: =IFERROR(FIND("IBAMA",consulta_completa__11[[#This Row],[14 - Inst. Atuando no Local]]),0) -> 0 | CX20: =IF(CW20=0,"","X") | CY20: =IF(consulta_completa__11[[#This Row],[14 - Inst. Atuando no Local]]="","X","") | CZ20: =IFERROR(FIND("OUTRA (S)",consulta_completa__11[[#This Row],[14 - Inst. Atuando no Local]]),0) -> 0 | DA20: =IF(CZ20=0,"","X") | DB20: =IF(AH$2="","",IF(AH$2="S","Sim",IF(AH$2="N","Não", IF(AH$2="I","Sem Informação")))) -> Sim | DC20: =IF(AI$2="","",IF(AI$2="S","Sim",IF(AI$2="N","Não", IF(AI$2="I","Sem Informação")))) -> Não | DD20: =IF(AJ$2="","",IF(AJ$2="S","Sim",IF(AJ$2="N","Não", IF(AJ$2="I","Sem Informação")))) -> Sim | DE20: =IF(AD20=1,"Federal",IF(AD20=2,"Estadual",IF(AD20=0,"Sem informação",""))) -> Federal
A21: 20251839658 | B21: 45664 | C21: Pilar | D21: AL | E21: Plataforma | F21: Outro(s) | M21: Solo | N21: Outra(s) | O21: Comunicado da empresa/responsável | P21: Terça | Q21: Vespertino | R21: Não | T21: Fazenda Lamarão, s/n. Zona rural. | U21: Campo Pilar - linha de injeção do poço PIR-166 | V21: Perda de contenção de água de injeção na linha do poço PIR-166 | Z21: Comprometimento da integridade da linha. | AA21: Área de canavial | AB21: ORIGEM ENERGIA ALAGOAS S.A | AC21: 34186669000301 | AD21: 2 | AE21: Recursos próprios | AF21: Selma Fontes de Araújo Andrade | AG21: (82) 98188-8811 | AH21: S | AI21: N | AJ21: S | AK21: Fechamento do poço para sanar o vazamento; Informe do vazamento para a engenharia de plantão; Abertura de nota para corretiva; Contato com superficiário; Acionada equipe de Suporte Operacional para limpeza da área afetada. | AL21: Durante as atividades de monitoramento no supervisório foi identificado um aumento na vazão do ramal de injeção, acompanhado pela redução na pressão de operação do ramal. Imediatamente foi acionada a operação de campo para confirmação de vazamento em algum ramal de injeção . Às 15:46h foi identificado o vazamento de água produzida na linha de injeção do PIR-166, O poço foi imediatamente retirado de operação, com o bloqueio dos pontos a montante e a jusante, interrompendo o vazamento. | AM21: ORIGEM ENERGIA ALAGOAS S.A. | AN21: ORIGEM ENERGIA ALAGOAS S.A | AO21: Assistente de Meio Ambiente | AP21: 82998006713 | AQ21: sms@origemenergia.com | AX21: =IFERROR(FIND("Óbitos/feridos",consulta_completa__11[[#This Row],[13 - Ocorrências/Ambientes Atingidos]]),0) -> 0 | AY21: =IF(AX21=0,"","X") | AZ21: =IFERROR(FIND("População afetada/evacuada",consulta_completa__11[[#This Row],[13 - Ocorrências/Ambientes Atingidos]]),0) -> 0 | BA21: =IF(AZ21=0,"","X") | BB21: =IFERROR(FIND("Suspensão de abastecimento de água",consulta_completa__11[[#This Row],[13 - Ocorrências/Ambientes Atingidos]]),0) -> 0 | BC21: =IF(BB21=0,"","X") | BD21: =IFERROR(FIND("Rio/córrego",consulta_completa__11[[#This Row],[13 - Ocorrências/Ambientes Atingidos]]),0) -> 0 | BE21: =IF(BD21=0,"","X") | BF21: =IFERROR(FIND("Lago",consulta_completa__11[[#This Row],[13 - Ocorrências/Ambientes Atingidos]]),0) -> 0 | BG21: =IF(BF21=0,"","X") | BH21: =IFERROR(FIND("Mar",consulta_completa__11[[#This Row],[13 - Ocorrências/Ambientes Atingidos]]),0) -> 0 | BI21: =IF(BH21=0,"","X") | BJ21: =IFERROR(FIND("Praia",consulta_completa__11[[#This Row],[13 - Ocorrências/Ambientes Atingidos]]),0) -> 0 | BK21: =IF(BJ21=0,"","X") | BL21: =IFERROR(FIND("Solo",consulta_completa__11[[#This Row],[13 - Ocorrências/Ambientes Atingidos]]),0) -> 1 | BM21: =IF(BL21=0,"","X") -> X | BN21: =IFERROR(FIND("Águas subterrâneas",consulta_completa__11[[#This Row],[13 - Ocorrências/Ambientes Atingidos]]),0) -> 0 | BO21: =IF(BN21=0,"","X") | BP21: =IFERROR(FIND("Atmosfera",consulta_completa__11[[#This Row],[13 - Ocorrências/Ambientes Atingidos]]),0) -> 0 | BQ21: =IF(BP21=0,"","X") | BR21: =IFERROR(FIND("Flora",consulta_completa__11[[#This Row],[13 - Ocorrências/Ambientes Atingidos]]),0) -> 0 | BS21: =IF(BR21=0,"","X") | BT21: =IFERROR(FIND("Fauna",consulta_completa__11[[#This Row],[13 - Ocorrências/Ambientes Atingidos]]),0) -> 0 | BU21: =IF(BT21=0,"","X") | BV21: =IFERROR(FIND("UC federal",consulta_completa__11[[#This Row],[13 - Ocorrências/Ambientes Atingidos]]),0) -> 0 | BW21: =IF(BV21=0,"","X") | BX21: =IFERROR(FIND("UC estadual/municipal",consulta_completa__11[[#This Row],[13 - Ocorrências/Ambientes Atingidos]]),0) -> 0 | BY21: =IF(BX21=0,"","X") | BZ21: =IFERROR(FIND("Outro(s)",consulta_completa__11[[#This Row],[13 - Ocorrências/Ambientes Atingidos]]),0) -> 0 | CA21: =IF(BZ21=0,"","X") | CB21: =IFERROR(FIND("Sem dano",consulta_completa__11[[#This Row],[13 - Ocorrências/Ambientes Atingidos]]),0) -> 0 | CC21: =IF(CB21=0,"","X") | CD21: =IF(consulta_completa__11[[#This Row],[13 - Ocorrências/Ambientes Atingidos]]="","X","") | CE21: =IFERROR(FIND("IBAMA",consulta_completa__11[[#This Row],[14 - Inst. Atuando no Local]]),0) -> 0 | CF21: =IF(CE21=0,"","X") | CG21: =IFERROR(FIND("OEMA",consulta_completa__11[[#This Row],[14 - Inst. Atuando no Local]]),0) -> 0 | CH21: =IF(CG21=0,"","X") | CI21: =IFERROR(FIND("DEFESA CIVIL",consulta_completa__11[[#This Row],[14 - Inst. Atuando no Local]]),0) -> 0 | CJ21: =IF(CI21=0,"","X") | CK21: =IFERROR(FIND("CORPO DE BOMBEIROS",consulta_completa__11[[#This Row],[14 - Inst. Atuando no Local]]),0) -> 0 | CL21: =IF(CK21=0,"","X") | CM21: =IFERROR(FIND("POLÍCIA RODOVIÁRIA",consulta_completa__11[[#This Row],[14 - Inst. Atuando no Local]]),0) -> 0 | CN21: =IF(CM21=0,"","X") | CO21: =IFERROR(FIND("POLÍCIA MILITAR",consulta_completa__11[[#This Row],[14 - Inst. Atuando no Local]]),0) -> 0 | CP21: =IF(CO21=0,"","X") | CQ21: =IFERROR(FIND("POLÍCIA CIVIL",consulta_completa__11[[#This Row],[14 - Inst. Atuando no Local]]),0) -> 0 | CR21: =IF(CQ21=0,"","X") | CS21: =IFERROR(FIND("MARINHA DO BRASIL",consulta_completa__11[[#This Row],[14 - Inst. Atuando no Local]]),0) -> 0 | CT21: =IF(CS21=0,"","X") | CU21: =IFERROR(FIND("EMPRESA ESPECIALIZADA EM ATENDIMENTO",consulta_completa__11[[#This Row],[14 - Inst. Atuando no Local]]),0) -> 0 | CV21: =IF(CU21=0,"","X") | CW21: =IFERROR(FIND("IBAMA",consulta_completa__11[[#This Row],[14 - Inst. Atuando no Local]]),0) -> 0 | CX21: =IF(CW21=0,"","X") | CY21: =IF(consulta_completa__11[[#This Row],[14 - Inst. Atuando no Local]]="","X","") | CZ21: =IFERROR(FIND("OUTRA (S)",consulta_completa__11[[#This Row],[14 - Inst. Atuando no Local]]),0) -> 0 | DA21: =IF(CZ21=0,"","X") | DB21: =IF(AH$2="","",IF(AH$2="S","Sim",IF(AH$2="N","Não", IF(AH$2="I","Sem Informação")))) -> Sim | DC21: =IF(AI$2="","",IF(AI$2="S","Sim",IF(AI$2="N","Não", IF(AI$2="I","Sem Informação")))) -> Não | DD21: =IF(AJ$2="","",IF(AJ$2="S","Sim",IF(AJ$2="N","Não", IF(AJ$2="I","Sem Informação")))) -> Sim | DE21: =IF(AD21=1,"Federal",IF(AD21=2,"Estadual",IF(AD21=0,"Sem informação",""))) -> Estadual
A22: 20251864839 | B22: 45664 | C22: null | D22: ES | E22: Outro(s) | F22: Derramamento de líquidos | J22: Fluido Hidráulico | K22: 0.11 | L22: M3 | M22: Mar | N22: Outra(s) | O22: Comunicado da empresa/responsável; Outra(s) fonte(s) | P22: Terça | Q22: Matutino | R22: Não | S22: Espírito-Santo | T22: SS-75 (OCEAN COURAGE), Campo de Jubarte. Número IMO 8768531. | U22: Poço Marítimo 7-BAZ-10DA-ESS | V22: Durante manobra de descida do Flexitubo para corte de VHIF (válvula hidráulica isoladora da formação), foi detectado consumo na função ABRE VG5 da FDR, indicando perda de estanqueidade na função mencionada. Foi descido ROV e observada descarga contínua de fluido hidráulico (Oceanic HW-525 P) pela válvula Dump de Exaustão, para o fundo do mar. Observada queda gradual de pressão da linha da função de abertura da VG5 da FDR na HPU de 2000 psi para 340 psi, vindo a estabilizar. | Z22: Vazamento na válvula Dump de Exaustão da linha de acionamento de abertura da VG5 da FDR. | AA22: Mar aberto, além de 12 MN da costa, em subsuperfície. | AB22: Petrobras | AC22: 33000167000454 | AD22: 1 | AE22: Petrobras | AH22: S | AI22: N | AJ22: S | AK22: Interrompida descida do BHA de corte da VHIF com Flexitubo e retirado até acima da FDR. Preparando solução para manter a válvula aberta sem pressurização. | AL22: A válvula VG5-FDR é de dupla ação e tem uma POCV (check valve que mantém a câmera de abertura pressurizada se o vazamento for antes dela). Foi ciclada a VG5 (BHA acima da FDR) para flush da válvula Dump, na tentativa de obter estanqueidade da linha. Realizados 3 ciclos e o vazamento persistiu, estabilizando somente com 340 psi. Após os ciclos, a linha de acionamento foi bloqueada, às 11:20. Método de cálculo do volume lançado ao mar: redução de volume de HW no sistema da sonda (de 550 l para 440 l = 110 litros). 1) Nome comercial: OCEANIC HW 525 P; 2) Composição química: Etileno glicol (CAS 107-21-1): 20,0000 - 30,0000%; 2-butóxietanol (CAS 111-76-2): 4,0000 - 6,0000%; 3) Descrição da classificação e subclasse ONU ou IMDG: Não classificado como perigoso para o transporte. | AM22: PETROLEO BRASILEIRO SA PETROBRAS - UN-ES | AQ22: crisguerreiro@petrobras.com.br | AX22: =IFERROR(FIND("Óbitos/feridos",consulta_completa__11[[#This Row],[13 - Ocorrências/Ambientes Atingidos]]),0) -> 0 | AY22: =IF(AX22=0,"","X") | AZ22: =IFERROR(FIND("População afetada/evacuada",consulta_completa__11[[#This Row],[13 - Ocorrências/Ambientes Atingidos]]),0) -> 0 | BA22: =IF(AZ22=0,"","X") | BB22: =IFERROR(FIND("Suspensão de abastecimento de água",consulta_completa__11[[#This Row],[13 - Ocorrências/Ambientes Atingidos]]),0) -> 0 | BC22: =IF(BB22=0,"","X") | BD22: =IFERROR(FIND("Rio/córrego",consulta_completa__11[[#This Row],[13 - Ocorrências/Ambientes Atingidos]]),0) -> 0 | BE22: =IF(BD22=0,"","X") | BF22: =IFERROR(FIND("Lago",consulta_completa__11[[#This Row],[13 - Ocorrências/Ambientes Atingidos]]),0) -> 0 | BG22: =IF(BF22=0,"","X") | BH22: =IFERROR(FIND("Mar",consulta_completa__11[[#This Row],[13 - Ocorrências/Ambientes Atingidos]]),0) -> 1 | BI22: =IF(BH22=0,"","X") -> X | BJ22: =IFERROR(FIND("Praia",consulta_completa__11[[#This Row],[13 - Ocorrências/Ambientes Atingidos]]),0) -> 0 | BK22: =IF(BJ22=0,"","X") | BL22: =IFERROR(FIND("Solo",consulta_completa__11[[#This Row],[13 - Ocorrências/Ambientes Atingidos]]),0) -> 0 | BM22: =IF(BL22=0,"","X") | BN22: =IFERROR(FIND("Águas subterrâneas",consulta_completa__11[[#This Row],[13 - Ocorrências/Ambientes Atingidos]]),0) -> 0 | BO22: =IF(BN22=0,"","X") | BP22: =IFERROR(FIND("Atmosfera",consulta_completa__11[[#This Row],[13 - Ocorrências/Ambientes Atingidos]]),0) -> 0 | BQ22: =IF(BP22=0,"","X") | BR22: =IFERROR(FIND("Flora",consulta_completa__11[[#This Row],[13 - Ocorrências/Ambientes Atingidos]]),0) -> 0 | BS22: =IF(BR22=0,"","X") | BT22: =IFERROR(FIND("Fauna",consulta_completa__11[[#This Row],[13 - Ocorrências/Ambientes Atingidos]]),0) -> 0 | BU22: =IF(BT22=0,"","X") | BV22: =IFERROR(FIND("UC federal",consulta_completa__11[[#This Row],[13 - Ocorrências/Ambientes Atingidos]]),0) -> 0 | BW22: =IF(BV22=0,"","X") | BX22: =IFERROR(FIND("UC estadual/municipal",consulta_completa__11[[#This Row],[13 - Ocorrências/Ambientes Atingidos]]),0) -> 0 | BY22: =IF(BX22=0,"","X") | BZ22: =IFERROR(FIND("Outro(s)",consulta_completa__11[[#This Row],[13 - Ocorrências/Ambientes Atingidos]]),0) -> 0 | CA22: =IF(BZ22=0,"","X") | CB22: =IFERROR(FIND("Sem dano",consulta_completa__11[[#This Row],[13 - Ocorrências/Ambientes Atingidos]]),0) -> 0 | CC22: =IF(CB22=0,"","X") | CD22: =IF(consulta_completa__11[[#This Row],[13 - Ocorrências/Ambientes Atingidos]]="","X","") | CE22: =IFERROR(FIND("IBAMA",consulta_completa__11[[#This Row],[14 - Inst. Atuando no Local]]),0) -> 0 | CF22: =IF(CE22=0,"","X") | CG22: =IFERROR(FIND("OEMA",consulta_completa__11[[#This Row],[14 - Inst. Atuando no Local]]),0) -> 0 | CH22: =IF(CG22=0,"","X") | CI22: =IFERROR(FIND("DEFESA CIVIL",consulta_completa__11[[#This Row],[14 - Inst. Atuando no Local]]),0) -> 0 | CJ22: =IF(CI22=0,"","X") | CK22: =IFERROR(FIND("CORPO DE BOMBEIROS",consulta_completa__11[[#This Row],[14 - Inst. Atuando no Local]]),0) -> 0 | CL22: =IF(CK22=0,"","X") | CM22: =IFERROR(FIND("POLÍCIA RODOVIÁRIA",consulta_completa__11[[#This Row],[14 - Inst. Atuando no Local]]),0) -> 0 | CN22: =IF(CM22=0,"","X") | CO22: =IFERROR(FIND("POLÍCIA MILITAR",consulta_completa__11[[#This Row],[14 - Inst. Atuando no Local]]),0) -> 0 | CP22: =IF(CO22=0,"","X") | CQ22: =IFERROR(FIND("POLÍCIA CIVIL",consulta_completa__11[[#This Row],[14 - Inst. Atuando no Local]]),0) -> 0 | CR22: =IF(CQ22=0,"","X") | CS22: =IFERROR(FIND("MARINHA DO BRASIL",consulta_completa__11[[#This Row],[14 - Inst. Atuando no Local]]),0) -> 0 | CT22: =IF(CS22=0,"","X") | CU22: =IFERROR(FIND("EMPRESA ESPECIALIZADA EM ATENDIMENTO",consulta_completa__11[[#This Row],[14 - Inst. Atuando no Local]]),0) -> 0 | CV22: =IF(CU22=0,"","X") | CW22: =IFERROR(FIND("IBAMA",consulta_completa__11[[#This Row],[14 - Inst. Atuando no Local]]),0) -> 0 | CX22: =IF(CW22=0,"","X") | CY22: =IF(consulta_completa__11[[#This Row],[14 - Inst. Atuando no Local]]="","X","") | CZ22: =IFERROR(FIND("OUTRA (S)",consulta_completa__11[[#This Row],[14 - Inst. Atuando no Local]]),0) -> 0 | DA22: =IF(CZ22=0,"","X") | DB22: =IF(AH$2="","",IF(AH$2="S","Sim",IF(AH$2="N","Não", IF(AH$2="I","Sem Informação")))) -> Sim | DC22: =IF(AI$2="","",IF(AI$2="S","Sim",IF(AI$2="N","Não", IF(AI$2="I","Sem Informação")))) -> Não | DD22: =IF(AJ$2="","",IF(AJ$2="S","Sim",IF(AJ$2="N","Não", IF(AJ$2="I","Sem Informação")))) -> Sim | DE22: =IF(AD22=1,"Federal",IF(AD22=2,"Estadual",IF(AD22=0,"Sem informação",""))) -> Federal
A23: 20251950404 | B23: 45664 | C23: null | D23: null | E23: Outro(s); Plataforma | F23: Derramamento de líquidos | J23: água oleosa | K23: 1.6 | L23: M3 | M23: Mar | N23: Outra(s) | O23: Outra(s) fonte(s) | P23: Terça | Q23: Vespertino | R23: Não | S23: Santos | T23: Campo de Mero, Bacia de Santos | U23: Poço 3-BRSA-1343-RJS | V23: Durante inspeção visual no poço, após sua partida, foi identificado escape de emulsão oleosa a partir da estrutura da cabeça do poço, ficando o mesmo contido na estrutura do equipamento submarino (funil down da BAP). Estimado que, aproximadamente 1,6 m³ da emulsão tenha ficado acumulada na estrutura do equipamento submarino e que 0,0003 m³ tenha migrado para o mar. | Z23: Em investigação. | AA23: Mar territorial | AB23: Petrobras | AC23: 33000167000292 | AD23: 1 | AE23: Petrobras | AH23: S | AI23: N | AJ23: S | AK23: 1 - Poço fechado. 2 - Realizada coleta de amostra para análise e caracterização do fluido, de modo a esclarecer a origem do escape. | AL23: Estimado que, aproximadamente 1,6 m³ da emulsão tenha ficado acumulada na estrutura do equipamento submarino e que 0,0003 m³ tenha migrado para o mar. Comunicado através do CAEME UN-MERO-2933. | AM23: PETRLEO BRASILEIRO S/A - PETROBRAS | AQ23: giselletinoco@petrobras.com.br | AX23: =IFERROR(FIND("Óbitos/feridos",consulta_completa__11[[#This Row],[13 - Ocorrências/Ambientes Atingidos]]),0) -> 0 | AY23: =IF(AX23=0,"","X") | AZ23: =IFERROR(FIND("População afetada/evacuada",consulta_completa__11[[#This Row],[13 - Ocorrências/Ambientes Atingidos]]),0) -> 0 | BA23: =IF(AZ23=0,"","X") | BB23: =IFERROR(FIND("Suspensão de abastecimento de água",consulta_completa__11[[#This Row],[13 - Ocorrências/Ambientes Atingidos]]),0) -> 0 | BC23: =IF(BB23=0,"","X") | BD23: =IFERROR(FIND("Rio/córrego",consulta_completa__11[[#This Row],[13 - Ocorrências/Ambientes Atingidos]]),0) -> 0 | BE23: =IF(BD23=0,"","X") | BF23: =IFERROR(FIND("Lago",consulta_completa__11[[#This Row],[13 - Ocorrências/Ambientes Atingidos]]),0) -> 0 | BG23: =IF(BF23=0,"","X") | BH23: =IFERROR(FIND("Mar",consulta_completa__11[[#This Row],[13 - Ocorrências/Ambientes Atingidos]]),0) -> 1 | BI23: =IF(BH23=0,"","X") -> X | BJ23: =IFERROR(FIND("Praia",consulta_completa__11[[#This Row],[13 - Ocorrências/Ambientes Atingidos]]),0) -> 0 | BK23: =IF(BJ23=0,"","X") | BL23: =IFERROR(FIND("Solo",consulta_completa__11[[#This Row],[13 - Ocorrências/Ambientes Atingidos]]),0) -> 0 | BM23: =IF(BL23=0,"","X") | BN23: =IFERROR(FIND("Águas subterrâneas",consulta_completa__11[[#This Row],[13 - Ocorrências/Ambientes Atingidos]]),0) -> 0 | BO23: =IF(BN23=0,"","X") | BP23: =IFERROR(FIND("Atmosfera",consulta_completa__11[[#This Row],[13 - Ocorrências/Ambientes Atingidos]]),0) -> 0 | BQ23: =IF(BP23=0,"","X") | BR23: =IFERROR(FIND("Flora",consulta_completa__11[[#This Row],[13 - Ocorrências/Ambientes Atingidos]]),0) -> 0 | BS23: =IF(BR23=0,"","X") | BT23: =IFERROR(FIND("Fauna",consulta_completa__11[[#This Row],[13 - Ocorrências/Ambientes Atingidos]]),0) -> 0 | BU23: =IF(BT23=0,"","X") | BV23: =IFERROR(FIND("UC federal",consulta_completa__11[[#This Row],[13 - Ocorrências/Ambientes Atingidos]]),0) -> 0 | BW23: =IF(BV23=0,"","X") | BX23: =IFERROR(FIND("UC estadual/municipal",consulta_completa__11[[#This Row],[13 - Ocorrências/Ambientes Atingidos]]),0) -> 0 | BY23: =IF(BX23=0,"","X") | BZ23: =IFERROR(FIND("Outro(s)",consulta_completa__11[[#This Row],[13 - Ocorrências/Ambientes Atingidos]]),0) -> 0 | CA23: =IF(BZ23=0,"","X") | CB23: =IFERROR(FIND("Sem dano",consulta_completa__11[[#This Row],[13 - Ocorrências/Ambientes Atingidos]]),0) -> 0 | CC23: =IF(CB23=0,"","X") | CD23: =IF(consulta_completa__11[[#This Row],[13 - Ocorrências/Ambientes Atingidos]]="","X","") | CE23: =IFERROR(FIND("IBAMA",consulta_completa__11[[#This Row],[14 - Inst. Atuando no Local]]),0) -> 0 | CF23: =IF(CE23=0,"","X") | CG23: =IFERROR(FIND("OEMA",consulta_completa__11[[#This Row],[14 - Inst. Atuando no Local]]),0) -> 0 | CH23: =IF(CG23=0,"","X") | CI23: =IFERROR(FIND("DEFESA CIVIL",consulta_completa__11[[#This Row],[14 - Inst. Atuando no Local]]),0) -> 0 | CJ23: =IF(CI23=0,"","X") | CK23: =IFERROR(FIND("CORPO DE BOMBEIROS",consulta_completa__11[[#This Row],[14 - Inst. Atuando no Local]]),0) -> 0 | CL23: =IF(CK23=0,"","X") | CM23: =IFERROR(FIND("POLÍCIA RODOVIÁRIA",consulta_completa__11[[#This Row],[14 - Inst. Atuando no Local]]),0) -> 0 | CN23: =IF(CM23=0,"","X") | CO23: =IFERROR(FIND("POLÍCIA MILITAR",consulta_completa__11[[#This Row],[14 - Inst. Atuando no Local]]),0) -> 0 | CP23: =IF(CO23=0,"","X") | CQ23: =IFERROR(FIND("POLÍCIA CIVIL",consulta_completa__11[[#This Row],[14 - Inst. Atuando no Local]]),0) -> 0 | CR23: =IF(CQ23=0,"","X") | CS23: =IFERROR(FIND("MARINHA DO BRASIL",consulta_completa__11[[#This Row],[14 - Inst. Atuando no Local]]),0) -> 0 | CT23: =IF(CS23=0,"","X") | CU23: =IFERROR(FIND("EMPRESA ESPECIALIZADA EM ATENDIMENTO",consulta_completa__11[[#This Row],[14 - Inst. Atuando no Local]]),0) -> 0 | CV23: =IF(CU23=0,"","X") | CW23: =IFERROR(FIND("IBAMA",consulta_completa__11[[#This Row],[14 - Inst. Atuando no Local]]),0) -> 0 | CX23: =IF(CW23=0,"","X") | CY23: =IF(consulta_completa__11[[#This Row],[14 - Inst. Atuando no Local]]="","X","") | CZ23: =IFERROR(FIND("OUTRA (S)",consulta_completa__11[[#This Row],[14 - Inst. Atuando no Local]]),0) -> 0 | DA23: =IF(CZ23=0,"","X") | DB23: =IF(AH$2="","",IF(AH$2="S","Sim",IF(AH$2="N","Não", IF(AH$2="I","Sem Informação")))) -> Sim | DC23: =IF(AI$2="","",IF(AI$2="S","Sim",IF(AI$2="N","Não", IF(AI$2="I","Sem Informação")))) -> Não | DD23: =IF(AJ$2="","",IF(AJ$2="S","Sim",IF(AJ$2="N","Não", IF(AJ$2="I","Sem Informação")))) -> Sim | DE23: =IF(AD23=1,"Federal",IF(AD23=2,"Estadual",IF(AD23=0,"Sem informação",""))) -> Federal
A24: 202512232441 | B24: 45665 | C24: Caldas | D24: MG | E24: Outro(s) | F24: Outro(s) | J24: Resíduos de ETE | K24: 10 | L24: M3 | M24: Solo | O24: Comunicado da empresa/responsável | P24: Quarta | Q24: Matutino | R24: Não | T24: Rodovia Poços Andradas, km 20,6 Campo do Cercado | U24: Sistema de bombeamento de lodo da estação de tratamento de efluente (ETE1) | V24: Vazamento de lodo do tratamento de drenagem ácida de mina (Diuranato de Cálcio - DUCA) | Z24: Rompimento de tubulação de transporte de DUCA da ETE1 para a Cava da Mina, ocasionado pelas prováveis causas: - Degradação natural da tubulação por tempo de uso; - Dilatação térmica causada por grande variação de temperatura. | AB24: Indústrias Nucleares do Brasil SA | AC24: 00322818003650 | AD24: 1 | AH24: N | AI24: N | AJ24: S | AK24: Em 08/01/2025: - Desligamento imediato do sistema de bombeamento para cessar o vazamento; - Conserto imediato da tubulação; - Retirada do material para sua deposição na Cava da Mina, no local onde é depositado comumente através de tubulação. Em 10/01/2025: - Coleta de amostras de solo para análise química e radiológica. | AL24: Processo sei nº #{23740890|02001.002389/2025-18} (Emergência Ambiental: Acidente Ambiental)# A ocorrência foi comunicada à CNEN através de Formulário de Informe de Evento (n° 01/2025). | AM24: INDSTRIAS NUCLEARES DO BRASIL S/A | AN24: Indústrias Nucleares do Brasil - INB | AO24: Gerente de Descomissionamento | AP24: 3521073120 | AQ24: gefis@inb.gov.br | AX24: =IFERROR(FIND("Óbitos/feridos",consulta_completa__11[[#This Row],[13 - Ocorrências/Ambientes Atingidos]]),0) -> 0 | AY24: =IF(AX24=0,"","X") | AZ24: =IFERROR(FIND("População afetada/evacuada",consulta_completa__11[[#This Row],[13 - Ocorrências/Ambientes Atingidos]]),0) -> 0 | BA24: =IF(AZ24=0,"","X") | BB24: =IFERROR(FIND("Suspensão de abastecimento de água",consulta_completa__11[[#This Row],[13 - Ocorrências/Ambientes Atingidos]]),0) -> 0 | BC24: =IF(BB24=0,"","X") | BD24: =IFERROR(FIND("Rio/córrego",consulta_completa__11[[#This Row],[13 - Ocorrências/Ambientes Atingidos]]),0) -> 0 | BE24: =IF(BD24=0,"","X") | BF24: =IFERROR(FIND("Lago",consulta_completa__11[[#This Row],[13 - Ocorrências/Ambientes Atingidos]]),0) -> 0 | BG24: =IF(BF24=0,"","X") | BH24: =IFERROR(FIND("Mar",consulta_completa__11[[#This Row],[13 - Ocorrências/Ambientes Atingidos]]),0) -> 0 | BI24: =IF(BH24=0,"","X") | BJ24: =IFERROR(FIND("Praia",consulta_completa__11[[#This Row],[13 - Ocorrências/Ambientes Atingidos]]),0) -> 0 | BK24: =IF(BJ24=0,"","X") | BL24: =IFERROR(FIND("Solo",consulta_completa__11[[#This Row],[13 - Ocorrências/Ambientes Atingidos]]),0) -> 1 | BM24: =IF(BL24=0,"","X") -> X | BN24: =IFERROR(FIND("Águas subterrâneas",consulta_completa__11[[#This Row],[13 - Ocorrências/Ambientes Atingidos]]),0) -> 0 | BO24: =IF(BN24=0,"","X") | BP24: =IFERROR(FIND("Atmosfera",consulta_completa__11[[#This Row],[13 - Ocorrências/Ambientes Atingidos]]),0) -> 0 | BQ24: =IF(BP24=0,"","X") | BR24: =IFERROR(FIND("Flora",consulta_completa__11[[#This Row],[13 - Ocorrências/Ambientes Atingidos]]),0) -> 0 | BS24: =IF(BR24=0,"","X") | BT24: =IFERROR(FIND("Fauna",consulta_completa__11[[#This Row],[13 - Ocorrências/Ambientes Atingidos]]),0) -> 0 | BU24: =IF(BT24=0,"","X") | BV24: =IFERROR(FIND("UC federal",consulta_completa__11[[#This Row],[13 - Ocorrências/Ambientes Atingidos]]),0) -> 0 | BW24: =IF(BV24=0,"","X") | BX24: =IFERROR(FIND("UC estadual/municipal",consulta_completa__11[[#This Row],[13 - Ocorrências/Ambientes Atingidos]]),0) -> 0 | BY24: =IF(BX24=0,"","X") | BZ24: =IFERROR(FIND("Outro(s)",consulta_completa__11[[#This Row],[13 - Ocorrências/Ambientes Atingidos]]),0) -> 0 | CA24: =IF(BZ24=0,"","X") | CB24: =IFERROR(FIND("Sem dano",consulta_completa__11[[#This Row],[13 - Ocorrências/Ambientes Atingidos]]),0) -> 0 | CC24: =IF(CB24=0,"","X") | CD24: =IF(consulta_completa__11[[#This Row],[13 - Ocorrências/Ambientes Atingidos]]="","X","") | CE24: =IFERROR(FIND("IBAMA",consulta_completa__11[[#This Row],[14 - Inst. Atuando no Local]]),0) -> 0 | CF24: =IF(CE24=0,"","X") | CG24: =IFERROR(FIND("OEMA",consulta_completa__11[[#This Row],[14 - Inst. Atuando no Local]]),0) -> 0 | CH24: =IF(CG24=0,"","X") | CI24: =IFERROR(FIND("DEFESA CIVIL",consulta_completa__11[[#This Row],[14 - Inst. Atuando no Local]]),0) -> 0 | CJ24: =IF(CI24=0,"","X") | CK24: =IFERROR(FIND("CORPO DE BOMBEIROS",consulta_completa__11[[#This Row],[14 - Inst. Atuando no Local]]),0) -> 0 | CL24: =IF(CK24=0,"","X") | CM24: =IFERROR(FIND("POLÍCIA RODOVIÁRIA",consulta_completa__11[[#This Row],[14 - Inst. Atuando no Local]]),0) -> 0 | CN24: =IF(CM24=0,"","X") | CO24: =IFERROR(FIND("POLÍCIA MILITAR",consulta_completa__11[[#This Row],[14 - Inst. Atuando no Local]]),0) -> 0 | CP24: =IF(CO24=0,"","X") | CQ24: =IFERROR(FIND("POLÍCIA CIVIL",consulta_completa__11[[#This Row],[14 - Inst. Atuando no Local]]),0) -> 0 | CR24: =IF(CQ24=0,"","X") | CS24: =IFERROR(FIND("MARINHA DO BRASIL",consulta_completa__11[[#This Row],[14 - Inst. Atuando no Local]]),0) -> 0 | CT24: =IF(CS24=0,"","X") | CU24: =IFERROR(FIND("EMPRESA ESPECIALIZADA EM ATENDIMENTO",consulta_completa__11[[#This Row],[14 - Inst. Atuando no Local]]),0) -> 0 | CV24: =IF(CU24=0,"","X") | CW24: =IFERROR(FIND("IBAMA",consulta_completa__11[[#This Row],[14 - Inst. Atuando no Local]]),0) -> 0 | CX24: =IF(CW24=0,"","X") | CY24: =IF(consulta_completa__11[[#This Row],[14 - Inst. Atuando no Local]]="","X","") -> X | CZ24: =IFERROR(FIND("OUTRA (S)",consulta_completa__11[[#This Row],[14 - Inst. Atuando no Local]]),0) -> 0 | DA24: =IF(CZ24=0,"","X") | DB24: =IF(AH$2="","",IF(AH$2="S","Sim",IF(AH$2="N","Não", IF(AH$2="I","Sem Informação")))) -> Sim | DC24: =IF(AI$2="","",IF(AI$2="S","Sim",IF(AI$2="N","Não", IF(AI$2="I","Sem Informação")))) -> Não | DD24: =IF(AJ$2="","",IF(AJ$2="S","Sim",IF(AJ$2="N","Não", IF(AJ$2="I","Sem Informação")))) -> Sim | DE24: =IF(AD24=1,"Federal",IF(AD24=2,"Estadual",IF(AD24=0,"Sem informação",""))) -> Federal
A25: 202512721604 | B25: 45665 | C25: Santo Estêvão | D25: BA | E25: Plataforma | F25: Derramamento de líquidos | J25: Água de injeção | K25: 3.7 | L25: M3 | M25: Solo | N25: Empresa especializada em atendimento | O25: Comunicado da empresa/responsável | P25: Quarta | Q25: Noturno | R25: Não | T25: Linha de injeção, Campo de Cassarongongo, Ativo Bahia. | U25: No dia 08/01/2025, por volta das 18:30h o operador de campo, verificou um vazamento onde foi detectado um rompimento na linha de injeção de 4" de fibra. | V25: Descarga significante de água de injeção Perda de contenção primária significante de água de injeção | Z25: Corrosão. | AA25: 1)3,70m³; 2)Solo; 3) e 4) N/A; 5) Será retificado; 7) a 11)N/A; Volume da perda de contenção: 3,70m³; Metodologia de cálculo = área x lâmina: (185m² x 0,02m) = 3,70m³. | AB25: PETRORECÔNCAVO S.A. | AC25: 03342704000130 | AD25: 2 | AE25: Própria Empresa | AH25: I | AI25: N | AJ25: S | AK25: Realizada devidas comunicações internas. | AM25: Gunther Barbosa | AN25: IBAMA | AO25: Analista Ambiental | AQ25: gunther.barbosa@ibama.gov.br | AT25: CASSARONGONGO | AW25: Paralisada | AX25: =IFERROR(FIND("Óbitos/feridos",consulta_completa__11[[#This Row],[13 - Ocorrências/Ambientes Atingidos]]),0) -> 0 | AY25: =IF(AX25=0,"","X") | AZ25: =IFERROR(FIND("População afetada/evacuada",consulta_completa__11[[#This Row],[13 - Ocorrências/Ambientes Atingidos]]),0) -> 0 | BA25: =IF(AZ25=0,"","X") | BB25: =IFERROR(FIND("Suspensão de abastecimento de água",consulta_completa__11[[#This Row],[13 - Ocorrências/Ambientes Atingidos]]),0) -> 0 | BC25: =IF(BB25=0,"","X") | BD25: =IFERROR(FIND("Rio/córrego",consulta_completa__11[[#This Row],[13 - Ocorrências/Ambientes Atingidos]]),0) -> 0 | BE25: =IF(BD25=0,"","X") | BF25: =IFERROR(FIND("Lago",consulta_completa__11[[#This Row],[13 - Ocorrências/Ambientes Atingidos]]),0) -> 0 | BG25: =IF(BF25=0,"","X") | BH25: =IFERROR(FIND("Mar",consulta_completa__11[[#This Row],[13 - Ocorrências/Ambientes Atingidos]]),0) -> 0 | BI25: =IF(BH25=0,"","X") | BJ25: =IFERROR(FIND("Praia",consulta_completa__11[[#This Row],[13 - Ocorrências/Ambientes Atingidos]]),0) -> 0 | BK25: =IF(BJ25=0,"","X") | BL25: =IFERROR(FIND("Solo",consulta_completa__11[[#This Row],[13 - Ocorrências/Ambientes Atingidos]]),0) -> 1 | BM25: =IF(BL25=0,"","X") -> X | BN25: =IFERROR(FIND("Águas subterrâneas",consulta_completa__11[[#This Row],[13 - Ocorrências/Ambientes Atingidos]]),0) -> 0 | BO25: =IF(BN25=0,"","X") | BP25: =IFERROR(FIND("Atmosfera",consulta_completa__11[[#This Row],[13 - Ocorrências/Ambientes Atingidos]]),0) -> 0 | BQ25: =IF(BP25=0,"","X") | BR25: =IFERROR(FIND("Flora",consulta_completa__11[[#This Row],[13 - Ocorrências/Ambientes Atingidos]]),0) -> 0 | BS25: =IF(BR25=0,"","X") | BT25: =IFERROR(FIND("Fauna",consulta_completa__11[[#This Row],[13 - Ocorrências/Ambientes Atingidos]]),0) -> 0 | BU25: =IF(BT25=0,"","X") | BV25: =IFERROR(FIND("UC federal",consulta_completa__11[[#This Row],[13 - Ocorrências/Ambientes Atingidos]]),0) -> 0 | BW25: =IF(BV25=0,"","X") | BX25: =IFERROR(FIND("UC estadual/municipal",consulta_completa__11[[#This Row],[13 - Ocorrências/Ambientes Atingidos]]),0) -> 0 | BY25: =IF(BX25=0,"","X") | BZ25: =IFERROR(FIND("Outro(s)",consulta_completa__11[[#This Row],[13 - Ocorrências/Ambientes Atingidos]]),0) -> 0 | CA25: =IF(BZ25=0,"","X") | CB25: =IFERROR(FIND("Sem dano",consulta_completa__11[[#This Row],[13 - Ocorrências/Ambientes Atingidos]]),0) -> 0 | CC25: =IF(CB25=0,"","X") | CD25: =IF(consulta_completa__11[[#This Row],[13 - Ocorrências/Ambientes Atingidos]]="","X","") | CE25: =IFERROR(FIND("IBAMA",consulta_completa__11[[#This Row],[14 - Inst. Atuando no Local]]),0) -> 0 | CF25: =IF(CE25=0,"","X") | CG25: =IFERROR(FIND("OEMA",consulta_completa__11[[#This Row],[14 - Inst. Atuando no Local]]),0) -> 0 | CH25: =IF(CG25=0,"","X") | CI25: =IFERROR(FIND("DEFESA CIVIL",consulta_completa__11[[#This Row],[14 - Inst. Atuando no Local]]),0) -> 0 | CJ25: =IF(CI25=0,"","X") | CK25: =IFERROR(FIND("CORPO DE BOMBEIROS",consulta_completa__11[[#This Row],[14 - Inst. Atuando no Local]]),0) -> 0 | CL25: =IF(CK25=0,"","X") | CM25: =IFERROR(FIND("POLÍCIA RODOVIÁRIA",consulta_completa__11[[#This Row],[14 - Inst. Atuando no Local]]),0) -> 0 | CN25: =IF(CM25=0,"","X") | CO25: =IFERROR(FIND("POLÍCIA MILITAR",consulta_completa__11[[#This Row],[14 - Inst. Atuando no Local]]),0) -> 0 | CP25: =IF(CO25=0,"","X") | CQ25: =IFERROR(FIND("POLÍCIA CIVIL",consulta_completa__11[[#This Row],[14 - Inst. Atuando no Local]]),0) -> 0 | CR25: =IF(CQ25=0,"","X") | CS25: =IFERROR(FIND("MARINHA DO BRASIL",consulta_completa__11[[#This Row],[14 - Inst. Atuando no Local]]),0) -> 0 | CT25: =IF(CS25=0,"","X") | CU25: =IFERROR(FIND("EMPRESA ESPECIALIZADA EM ATENDIMENTO",consulta_completa__11[[#This Row],[14 - Inst. Atuando no Local]]),0) -> 0 | CV25: =IF(CU25=0,"","X") | CW25: =IFERROR(FIND("IBAMA",consulta_completa__11[[#This Row],[14 - Inst. Atuando no Local]]),0) -> 0 | CX25: =IF(CW25=0,"","X") | CY25: =IF(consulta_completa__11[[#This Row],[14 - Inst. Atuando no Local]]="","X","") | CZ25: =IFERROR(FIND("OUTRA (S)",consulta_completa__11[[#This Row],[14 - Inst. Atuando no Local]]),0) -> 0 | DA25: =IF(CZ25=0,"","X") | DB25: =IF(AH$2="","",IF(AH$2="S","Sim",IF(AH$2="N","Não", IF(AH$2="I","Sem Informação")))) -> Sim | DC25: =IF(AI$2="","",IF(AI$2="S","Sim",IF(AI$2="N","Não", IF(AI$2="I","Sem Informação")))) -> Não | DD25: =IF(AJ$2="","",IF(AJ$2="S","Sim",IF(AJ$2="N","Não", IF(AJ$2="I","Sem Informação")))) -> Sim | DE25: =IF(AD25=1,"Federal",IF(AD25=2,"Estadual",IF(AD25=0,"Sem informação",""))) -> Estadual
A26: 202512728809 | B26: 45665 | C26: Jucurutu | D26: RN | E26: Plataforma | F26: Derramamento de líquidos | G26: PETRÓLEO, CRU | H26: 0.067 | I26: M3 | J26: Água Produzida fora de especificação | K26: 0.213 | L26: M3 | M26: Solo | O26: Comunicado da empresa/responsável | P26: Quarta | Q26: Vespertino | R26: Não | T26: Linha de produção do poço 7-SBO-34-RN, Campo Sabiá Bico-de-Osso, Bacia Potiguar | U26: Descarga significante de óleo Perda de contenção primária significante de óleo | V26: No dia 08/01/2025, por volta das 16:53 o supervisor de produção em visita ao poço SBO0034, detectou um vazamento na linha de produção do poço em um trecho aterrado. | Z26: Corrosão. | AA26: 1) 0,28m³; 2) Solo; 3) BSW 76%;4) a 11)N/A; Volume da perda de contenção: 0,28m³; Metodologia de cálculo = área x lâmina: (14m² x 0,02m) = 0,28m³. | AB26: POTIGUAR E&P S.A. | AC26: 30759670000157 | AD26: 2 | AH26: I | AI26: N | AJ26: S | AK26: Realizada as devidas comunicações internas | AM26: Gunther Barbosa | AN26: IBAMA | AQ26: gunther.barbosa@ibama.gov.br | AT26: 7-SBO-34-RN | AW26: Paralisada | AX26: =IFERROR(FIND("Óbitos/feridos",consulta_completa__11[[#This Row],[13 - Ocorrências/Ambientes Atingidos]]),0) -> 0 | AY26: =IF(AX26=0,"","X") | AZ26: =IFERROR(FIND("População afetada/evacuada",consulta_completa__11[[#This Row],[13 - Ocorrências/Ambientes Atingidos]]),0) -> 0 | BA26: =IF(AZ26=0,"","X") | BB26: =IFERROR(FIND("Suspensão de abastecimento de água",consulta_completa__11[[#This Row],[13 - Ocorrências/Ambientes Atingidos]]),0) -> 0 | BC26: =IF(BB26=0,"","X") | BD26: =IFERROR(FIND("Rio/córrego",consulta_completa__11[[#This Row],[13 - Ocorrências/Ambientes Atingidos]]),0) -> 0 | BE26: =IF(BD26=0,"","X") | BF26: =IFERROR(FIND("Lago",consulta_completa__11[[#This Row],[13 - Ocorrências/Ambientes Atingidos]]),0) -> 0 | BG26: =IF(BF26=0,"","X") | BH26: =IFERROR(FIND("Mar",consulta_completa__11[[#This Row],[13 - Ocorrências/Ambientes Atingidos]]),0) -> 0 | BI26: =IF(BH26=0,"","X") | BJ26: =IFERROR(FIND("Praia",consulta_completa__11[[#This Row],[13 - Ocorrências/Ambientes Atingidos]]),0) -> 0 | BK26: =IF(BJ26=0,"","X") | BL26: =IFERROR(FIND("Solo",consulta_completa__11[[#This Row],[13 - Ocorrências/Ambientes Atingidos]]),0) -> 1 | BM26: =IF(BL26=0,"","X") -> X | BN26: =IFERROR(FIND("Águas subterrâneas",consulta_completa__11[[#This Row],[13 - Ocorrências/Ambientes Atingidos]]),0) -> 0 | BO26: =IF(BN26=0,"","X") | BP26: =IFERROR(FIND("Atmosfera",consulta_completa__11[[#This Row],[13 - Ocorrências/Ambientes Atingidos]]),0) -> 0 | BQ26: =IF(BP26=0,"","X") | BR26: =IFERROR(FIND("Flora",consulta_completa__11[[#This Row],[13 - Ocorrências/Ambientes Atingidos]]),0) -> 0 | BS26: =IF(BR26=0,"","X") | BT26: =IFERROR(FIND("Fauna",consulta_completa__11[[#This Row],[13 - Ocorrências/Ambientes Atingidos]]),0) -> 0 | BU26: =IF(BT26=0,"","X") | BV26: =IFERROR(FIND("UC federal",consulta_completa__11[[#This Row],[13 - Ocorrências/Ambientes Atingidos]]),0) -> 0 | BW26: =IF(BV26=0,"","X") | BX26: =IFERROR(FIND("UC estadual/municipal",consulta_completa__11[[#This Row],[13 - Ocorrências/Ambientes Atingidos]]),0) -> 0 | BY26: =IF(BX26=0,"","X") | BZ26: =IFERROR(FIND("Outro(s)",consulta_completa__11[[#This Row],[13 - Ocorrências/Ambientes Atingidos]]),0) -> 0 | CA26: =IF(BZ26=0,"","X") | CB26: =IFERROR(FIND("Sem dano",consulta_completa__11[[#This Row],[13 - Ocorrências/Ambientes Atingidos]]),0) -> 0 | CC26: =IF(CB26=0,"","X") | CD26: =IF(consulta_completa__11[[#This Row],[13 - Ocorrências/Ambientes Atingidos]]="","X","") | CE26: =IFERROR(FIND("IBAMA",consulta_completa__11[[#This Row],[14 - Inst. Atuando no Local]]),0) -> 0 | CF26: =IF(CE26=0,"","X") | CG26: =IFERROR(FIND("OEMA",consulta_completa__11[[#This Row],[14 - Inst. Atuando no Local]]),0) -> 0 | CH26: =IF(CG26=0,"","X") | CI26: =IFERROR(FIND("DEFESA CIVIL",consulta_completa__11[[#This Row],[14 - Inst. Atuando no Local]]),0) -> 0 | CJ26: =IF(CI26=0,"","X") | CK26: =IFERROR(FIND("CORPO DE BOMBEIROS",consulta_completa__11[[#This Row],[14 - Inst. Atuando no Local]]),0) -> 0 | CL26: =IF(CK26=0,"","X") | CM26: =IFERROR(FIND("POLÍCIA RODOVIÁRIA",consulta_completa__11[[#This Row],[14 - Inst. Atuando no Local]]),0) -> 0 | CN26: =IF(CM26=0,"","X") | CO26: =IFERROR(FIND("POLÍCIA MILITAR",consulta_completa__11[[#This Row],[14 - Inst. Atuando no Local]]),0) -> 0 | CP26: =IF(CO26=0,"","X") | CQ26: =IFERROR(FIND("POLÍCIA CIVIL",consulta_completa__11[[#This Row],[14 - Inst. Atuando no Local]]),0) -> 0 | CR26: =IF(CQ26=0,"","X") | CS26: =IFERROR(FIND("MARINHA DO BRASIL",consulta_completa__11[[#This Row],[14 - Inst. Atuando no Local]]),0) -> 0 | CT26: =IF(CS26=0,"","X") | CU26: =IFERROR(FIND("EMPRESA ESPECIALIZADA EM ATENDIMENTO",consulta_completa__11[[#This Row],[14 - Inst. Atuando no Local]]),0) -> 0 | CV26: =IF(CU26=0,"","X") | CW26: =IFERROR(FIND("IBAMA",consulta_completa__11[[#This Row],[14 - Inst. Atuando no Local]]),0) -> 0 | CX26: =IF(CW26=0,"","X") | CY26: =IF(consulta_completa__11[[#This Row],[14 - Inst. Atuando no Local]]="","X","") -> X | CZ26: =IFERROR(FIND("OUTRA (S)",consulta_completa__11[[#This Row],[14 - Inst. Atuando no Local]]),0) -> 0 | DA26: =IF(CZ26=0,"","X") | DB26: =IF(AH$2="","",IF(AH$2="S","Sim",IF(AH$2="N","Não", IF(AH$2="I","Sem Informação")))) -> Sim | DC26: =IF(AI$2="","",IF(AI$2="S","Sim",IF(AI$2="N","Não", IF(AI$2="I","Sem Informação")))) -> Não | DD26: =IF(AJ$2="","",IF(AJ$2="S","Sim",IF(AJ$2="N","Não", IF(AJ$2="I","Sem Informação")))) -> Sim | DE26: =IF(AD26=1,"Federal",IF(AD26=2,"Estadual",IF(AD26=0,"Sem informação",""))) -> Estadual
A27: 202511421625 | B27: 45667 | C27: Olinda | D27: PE | E27: Embarcação | F27: Lançamento de sólidos; Derramamento de líquidos | G27: ALCATRÕES LÍQUIDOS, INCLUSIVE ASFALTO, ÓLEOS, BETUMES E CUT BACKS RODOVIÁRIOS | J27: produtos alimentícios | M27: Praia | N27: Marinha do Brasil | O27: Mídia | P27: Sexta | Q27: Noturno | R27: Não | T27: Praia de Casa Caiada. | U27: Processo Sei! 02001.001248/2025-70. De acordo com a Marinha, a embarcação afundou a cerca de três milhas náuticas (aproximadamente cinco quilômetros) da Praia de Casa Caiada, em Olinda, restando cerca de 40 minutos de percurso até o Porto do Recife. | V27: A embarcação estava carregada com alimentos, bebidas e materiais de construção, ainda, foram observadas manchas de óleo diesel nos arredores do acidente. | Z27: A Marinha do Brasil abriu um inquérito para apurar as circunstâncias do acidente e determinar as causas. | AA27: Houve dispersão da carga e de óleo diesel. | AB27: Além Mar Transportes e Navegação Ltda | AC27: 07995104000122 | AD27: 0 | AH27: I | AI27: N | AJ27: S | AK27: Salvamento dos tripulantes. | AL27: A carga foi parcialmente saqueada. | AM27: Mariana Rivetti Ribeiro De Carvalho | AN27: Ibama | AO27: Analista Ambiental | AP27: 31987239130 | AQ27: mariana.carvalho@ibama.gov.br | AS27: Topa Tudo Noronha | AW27: Sem condições de informar | AX27: =IFERROR(FIND("Óbitos/feridos",consulta_completa__11[[#This Row],[13 - Ocorrências/Ambientes Atingidos]]),0) -> 0 | AY27: =IF(AX27=0,"","X") | AZ27: =IFERROR(FIND("População afetada/evacuada",consulta_completa__11[[#This Row],[13 - Ocorrências/Ambientes Atingidos]]),0) -> 0 | BA27: =IF(AZ27=0,"","X") | BB27: =IFERROR(FIND("Suspensão de abastecimento de água",consulta_completa__11[[#This Row],[13 - Ocorrências/Ambientes Atingidos]]),0) -> 0 | BC27: =IF(BB27=0,"","X") | BD27: =IFERROR(FIND("Rio/córrego",consulta_completa__11[[#This Row],[13 - Ocorrências/Ambientes Atingidos]]),0) -> 0 | BE27: =IF(BD27=0,"","X") | BF27: =IFERROR(FIND("Lago",consulta_completa__11[[#This Row],[13 - Ocorrências/Ambientes Atingidos]]),0) -> 0 | BG27: =IF(BF27=0,"","X") | BH27: =IFERROR(FIND("Mar",consulta_completa__11[[#This Row],[13 - Ocorrências/Ambientes Atingidos]]),0) -> 0 | BI27: =IF(BH27=0,"","X") | BJ27: =IFERROR(FIND("Praia",consulta_completa__11[[#This Row],[13 - Ocorrências/Ambientes Atingidos]]),0) -> 1 | BK27: =IF(BJ27=0,"","X") -> X | BL27: =IFERROR(FIND("Solo",consulta_completa__11[[#This Row],[13 - Ocorrências/Ambientes Atingidos]]),0) -> 0 | BM27: =IF(BL27=0,"","X") | BN27: =IFERROR(FIND("Águas subterrâneas",consulta_completa__11[[#This Row],[13 - Ocorrências/Ambientes Atingidos]]),0) -> 0 | BO27: =IF(BN27=0,"","X") | BP27: =IFERROR(FIND("Atmosfera",consulta_completa__11[[#This Row],[13 - Ocorrências/Ambientes Atingidos]]),0) -> 0 | BQ27: =IF(BP27=0,"","X") | BR27: =IFERROR(FIND("Flora",consulta_completa__11[[#This Row],[13 - Ocorrências/Ambientes Atingidos]]),0) -> 0 | BS27: =IF(BR27=0,"","X") | BT27: =IFERROR(FIND("Fauna",consulta_completa__11[[#This Row],[13 - Ocorrências/Ambientes Atingidos]]),0) -> 0 | BU27: =IF(BT27=0,"","X") | BV27: =IFERROR(FIND("UC federal",consulta_completa__11[[#This Row],[13 - Ocorrências/Ambientes Atingidos]]),0) -> 0 | BW27: =IF(BV27=0,"","X") | BX27: =IFERROR(FIND("UC estadual/municipal",consulta_completa__11[[#This Row],[13 - Ocorrências/Ambientes Atingidos]]),0) -> 0 | BY27: =IF(BX27=0,"","X") | BZ27: =IFERROR(FIND("Outro(s)",consulta_completa__11[[#This Row],[13 - Ocorrências/Ambientes Atingidos]]),0) -> 0 | CA27: =IF(BZ27=0,"","X") | CB27: =IFERROR(FIND("Sem dano",consulta_completa__11[[#This Row],[13 - Ocorrências/Ambientes Atingidos]]),0) -> 0 | CC27: =IF(CB27=0,"","X") | CD27: =IF(consulta_completa__11[[#This Row],[13 - Ocorrências/Ambientes Atingidos]]="","X","") | CE27: =IFERROR(FIND("IBAMA",consulta_completa__11[[#This Row],[14 - Inst. Atuando no Local]]),0) -> 0 | CF27: =IF(CE27=0,"","X") | CG27: =IFERROR(FIND("OEMA",consulta_completa__11[[#This Row],[14 - Inst. Atuando no Local]]),0) -> 0 | CH27: =IF(CG27=0,"","X") | CI27: =IFERROR(FIND("DEFESA CIVIL",consulta_completa__11[[#This Row],[14 - Inst. Atuando no Local]]),0) -> 0 | CJ27: =IF(CI27=0,"","X") | CK27: =IFERROR(FIND("CORPO DE BOMBEIROS",consulta_completa__11[[#This Row],[14 - Inst. Atuando no Local]]),0) -> 0 | CL27: =IF(CK27=0,"","X") | CM27: =IFERROR(FIND("POLÍCIA RODOVIÁRIA",consulta_completa__11[[#This Row],[14 - Inst. Atuando no Local]]),0) -> 0 | CN27: =IF(CM27=0,"","X") | CO27: =IFERROR(FIND("POLÍCIA MILITAR",consulta_completa__11[[#This Row],[14 - Inst. Atuando no Local]]),0) -> 0 | CP27: =IF(CO27=0,"","X") | CQ27: =IFERROR(FIND("POLÍCIA CIVIL",consulta_completa__11[[#This Row],[14 - Inst. Atuando no Local]]),0) -> 0 | CR27: =IF(CQ27=0,"","X") | CS27: =IFERROR(FIND("MARINHA DO BRASIL",consulta_completa__11[[#This Row],[14 - Inst. Atuando no Local]]),0) -> 0 | CT27: =IF(CS27=0,"","X") | CU27: =IFERROR(FIND("EMPRESA ESPECIALIZADA EM ATENDIMENTO",consulta_completa__11[[#This Row],[14 - Inst. Atuando no Local]]),0) -> 0 | CV27: =IF(CU27=0,"","X") | CW27: =IFERROR(FIND("IBAMA",consulta_completa__11[[#This Row],[14 - Inst. Atuando no Local]]),0) -> 0 | CX27: =IF(CW27=0,"","X") | CY27: =IF(consulta_completa__11[[#This Row],[14 - Inst. Atuando no Local]]="","X","") | CZ27: =IFERROR(FIND("OUTRA (S)",consulta_completa__11[[#This Row],[14 - Inst. Atuando no Local]]),0) -> 0 | DA27: =IF(CZ27=0,"","X") | DB27: =IF(AH$2="","",IF(AH$2="S","Sim",IF(AH$2="N","Não", IF(AH$2="I","Sem Informação")))) -> Sim | DC27: =IF(AI$2="","",IF(AI$2="S","Sim",IF(AI$2="N","Não", IF(AI$2="I","Sem Informação")))) -> Não | DD27: =IF(AJ$2="","",IF(AJ$2="S","Sim",IF(AJ$2="N","Não", IF(AJ$2="I","Sem Informação")))) -> Sim | DE27: =IF(AD27=1,"Federal",IF(AD27=2,"Estadual",IF(AD27=0,"Sem informação",""))) -> Sem informação
A28: 20251133624 | B28: 45668 | C28: null | D28: null | E28: Outro(s) | F28: Outro(s) | M28: Mar | N28: Outra(s) | O28: Outra(s) fonte(s) | P28: Sábado | Q28: Vespertino | R28: Não | S28: Santos | T28: Mancha de origem indeterminada na Bacia de Santos | U28: Mancha de origem indeterminada na Bacia de Santos. Processo: 02001.001117/2025-92. | V28: Detecção de feição de origem indeterminada durante sobrevoo de monitoramento ambiental (asa fixa) realizado no dia 11/01/2025. Mobilizada embarcação oil recovery para o local e programado sobrevoo de inspeção (asa móvel). A embarcação, ao chegar no local, constatou se tratar de uma feição oleosa, sendo coletada uma amostra para identificação do tipo de óleo e iniciada as ações de combate a feição oleosa por dispersão mecânica. | Z28: O resultado preliminar da análise da amostra coletada indica se tratar de óleo diesel e não foi identificado a origem. | AB28: Petrobras | AC28: 33000167000292 | AD28: 1 | AE28: Petrobras | AH28: S | AI28: N | AJ28: S | AK28: Mobilização de sobrevoo de inspeção e embarcação oil recovery para confirmação, coleta de amostra e combate a mancha. Realizada a dispersão mecânica da mancha e encaminhada a amostra coletada para análise no CENPES. As unidades Petrobras próximas a mancha após serem consultadas, não reportaram anormalidades em seus processos produtivos. | AL28: Estimativa preliminar de volume: 91,0 l / 0,091 m3 Sentido da deriva aparente: 280 graus Dimensões dos fragmentos da feição oleosa ( 3 fragmentos): 0,98 MN x 0,22 MN, 0,19 MN X 0,16 MN, 0,17 MN X 0,10 MN Coloração do óleo: brilho prateado, arco-íris e metálico. Sobre voo no dia 11/01/2025 às 16:30 e no sobre voo do dia 12/01/2025 não foram identificados mais traços do óleo na região. Comunicado pelo CAEME LOEP/LOFF-2955 | AM28: PETRLEO BRASILEIRO S/A - PETROBRAS | AQ28: giselletinoco@petrobras.com.br | AX28: =IFERROR(FIND("Óbitos/feridos",consulta_completa__11[[#This Row],[13 - Ocorrências/Ambientes Atingidos]]),0) -> 0 | AY28: =IF(AX28=0,"","X") | AZ28: =IFERROR(FIND("População afetada/evacuada",consulta_completa__11[[#This Row],[13 - Ocorrências/Ambientes Atingidos]]),0) -> 0 | BA28: =IF(AZ28=0,"","X") | BB28: =IFERROR(FIND("Suspensão de abastecimento de água",consulta_completa__11[[#This Row],[13 - Ocorrências/Ambientes Atingidos]]),0) -> 0 | BC28: =IF(BB28=0,"","X") | BD28: =IFERROR(FIND("Rio/córrego",consulta_completa__11[[#This Row],[13 - Ocorrências/Ambientes Atingidos]]),0) -> 0 | BE28: =IF(BD28=0,"","X") | BF28: =IFERROR(FIND("Lago",consulta_completa__11[[#This Row],[13 - Ocorrências/Ambientes Atingidos]]),0) -> 0 | BG28: =IF(BF28=0,"","X") | BH28: =IFERROR(FIND("Mar",consulta_completa__11[[#This Row],[13 - Ocorrências/Ambientes Atingidos]]),0) -> 1 | BI28: =IF(BH28=0,"","X") -> X | BJ28: =IFERROR(FIND("Praia",consulta_completa__11[[#This Row],[13 - Ocorrências/Ambientes Atingidos]]),0) -> 0 | BK28: =IF(BJ28=0,"","X") | BL28: =IFERROR(FIND("Solo",consulta_completa__11[[#This Row],[13 - Ocorrências/Ambientes Atingidos]]),0) -> 0 | BM28: =IF(BL28=0,"","X") | BN28: =IFERROR(FIND("Águas subterrâneas",consulta_completa__11[[#This Row],[13 - Ocorrências/Ambientes Atingidos]]),0) -> 0 | BO28: =IF(BN28=0,"","X") | BP28: =IFERROR(FIND("Atmosfera",consulta_completa__11[[#This Row],[13 - Ocorrências/Ambientes Atingidos]]),0) -> 0 | BQ28: =IF(BP28=0,"","X") | BR28: =IFERROR(FIND("Flora",consulta_completa__11[[#This Row],[13 - Ocorrências/Ambientes Atingidos]]),0) -> 0 | BS28: =IF(BR28=0,"","X") | BT28: =IFERROR(FIND("Fauna",consulta_completa__11[[#This Row],[13 - Ocorrências/Ambientes Atingidos]]),0) -> 0 | BU28: =IF(BT28=0,"","X") | BV28: =IFERROR(FIND("UC federal",consulta_completa__11[[#This Row],[13 - Ocorrências/Ambientes Atingidos]]),0) -> 0 | BW28: =IF(BV28=0,"","X") | BX28: =IFERROR(FIND("UC estadual/municipal",consulta_completa__11[[#This Row],[13 - Ocorrências/Ambientes Atingidos]]),0) -> 0 | BY28: =IF(BX28=0,"","X") | BZ28: =IFERROR(FIND("Outro(s)",consulta_completa__11[[#This Row],[13 - Ocorrências/Ambientes Atingidos]]),0) -> 0 | CA28: =IF(BZ28=0,"","X") | CB28: =IFERROR(FIND("Sem dano",consulta_completa__11[[#This Row],[13 - Ocorrências/Ambientes Atingidos]]),0) -> 0 | CC28: =IF(CB28=0,"","X") | CD28: =IF(consulta_completa__11[[#This Row],[13 - Ocorrências/Ambientes Atingidos]]="","X","") | CE28: =IFERROR(FIND("IBAMA",consulta_completa__11[[#This Row],[14 - Inst. Atuando no Local]]),0) -> 0 | CF28: =IF(CE28=0,"","X") | CG28: =IFERROR(FIND("OEMA",consulta_completa__11[[#This Row],[14 - Inst. Atuando no Local]]),0) -> 0 | CH28: =IF(CG28=0,"","X") | CI28: =IFERROR(FIND("DEFESA CIVIL",consulta_completa__11[[#This Row],[14 - Inst. Atuando no Local]]),0) -> 0 | CJ28: =IF(CI28=0,"","X") | CK28: =IFERROR(FIND("CORPO DE BOMBEIROS",consulta_completa__11[[#This Row],[14 - Inst. Atuando no Local]]),0) -> 0 | CL28: =IF(CK28=0,"","X") | CM28: =IFERROR(FIND("POLÍCIA RODOVIÁRIA",consulta_completa__11[[#This Row],[14 - Inst. Atuando no Local]]),0) -> 0 | CN28: =IF(CM28=0,"","X") | CO28: =IFERROR(FIND("POLÍCIA MILITAR",consulta_completa__11[[#This Row],[14 - Inst. Atuando no Local]]),0) -> 0 | CP28: =IF(CO28=0,"","X") | CQ28: =IFERROR(FIND("POLÍCIA CIVIL",consulta_completa__11[[#This Row],[14 - Inst. Atuando no Local]]),0) -> 0 | CR28: =IF(CQ28=0,"","X") | CS28: =IFERROR(FIND("MARINHA DO BRASIL",consulta_completa__11[[#This Row],[14 - Inst. Atuando no Local]]),0) -> 0 | CT28: =IF(CS28=0,"","X") | CU28: =IFERROR(FIND("EMPRESA ESPECIALIZADA EM ATENDIMENTO",consulta_completa__11[[#This Row],[14 - Inst. Atuando no Local]]),0) -> 0 | CV28: =IF(CU28=0,"","X") | CW28: =IFERROR(FIND("IBAMA",consulta_completa__11[[#This Row],[14 - Inst. Atuando no Local]]),0) -> 0 | CX28: =IF(CW28=0,"","X") | CY28: =IF(consulta_completa__11[[#This Row],[14 - Inst. Atuando no Local]]="","X","") | CZ28: =IFERROR(FIND("OUTRA (S)",consulta_completa__11[[#This Row],[14 - Inst. Atuando no Local]]),0) -> 0 | DA28: =IF(CZ28=0,"","X") | DB28: =IF(AH$2="","",IF(AH$2="S","Sim",IF(AH$2="N","Não", IF(AH$2="I","Sem Informação")))) -> Sim | DC28: =IF(AI$2="","",IF(AI$2="S","Sim",IF(AI$2="N","Não", IF(AI$2="I","Sem Informação")))) -> Não | DD28: =IF(AJ$2="","",IF(AJ$2="S","Sim",IF(AJ$2="N","Não", IF(AJ$2="I","Sem Informação")))) -> Sim | DE28: =IF(AD28=1,"Federal",IF(AD28=2,"Estadual",IF(AD28=0,"Sem informação",""))) -> Federal
A29: 20251143636 | B29: 45669 | C29: null | D29: null | E29: Outro(s) | F29: Derramamento de líquidos | J29: fluido hidráulico; água | K29: 0.007; 0.22 | L29: M3; M3 | M29: Mar | N29: Outra(s) | O29: Outra(s) fonte(s) | P29: Domingo | Q29: Matutino | R29: Não | S29: Santos | T29: Campo de Aram, Bacia de Santos | U29: Poço 4-BRSA-1395-SPS. Processo Sei!: 02001.001255/2025-71. | V29: Durante início da perfuração da fase 16%u201D, foi observado pelo ROV um pequeno vazamento na linha de vent da reguladora de 5K-3K do Supply do POD Amarelo. Nesta condição, com o POD amarelo selecionado como POD ativo, o acionamento de bombas da HPU do BOP ocorre em aproximadamente 1h 30 min. Ambos os PODs permanecem operacionais. Descarga para o mar de 0,227 m3 de fluido hidráulico base água - mistura de 97% de água potável (0,220 m3) e 3% de fluido hidráulico para BOP ERIFON HD 603 HP (0,007 m3). | Z29: Falha de estanqueidade na linha de dreno (vent line) da reguladora de pressão (5000 psi para 3000 psi) do POD amarelo. | AB29: Petrobras | AC29: 33000167089501 | AD29: 1 | AE29: Petrobras | AH29: S | AI29: N | AJ29: S | AK29: Elaborada gestão de mudança na qual o risco foi considerado tolerável para prosseguir com operações do poço, alterando os comandos do BOP para o POD azul. | AL29: Memória de cálculo para estimativa de volume de fluido hidráulico (97% água potável + 3% Erifon): volume total contabilizado pelo flowmeter desde o início da entrada de bombas até a alteração para o POD azul (60 US gal = 0,227 m3 de fluido descarregado = 0,220 m3 de água potável + 0,007 m3 de Erifon). Relatório de gestão de mudança com análise do risco: Em anexo. Data do último teste no BOP: 2025-01-10 Definir a(s) parte(s) do sistema BOP onde ocorreu a falha: Pods de Controle do BOP Nome comercial: ERIFON HD 603 HP Composição química: Etileno glicol: 24-36% / Monoetanolamina: 4 - 6% / Dietanolamina: 3,94 - 5,91% Área atingida: Mar Territorial Descrição da classificação e subclasse ONU ou IMDG: Não classificado como perigoso, comunicado pelo CAEME POCOS/SM-2961 | AM29: PETRLEO BRASILEIRO S.A. | AQ29: siema.bs@petrobras.com.br | AX29: =IFERROR(FIND("Óbitos/feridos",consulta_completa__11[[#This Row],[13 - Ocorrências/Ambientes Atingidos]]),0) -> 0 | AY29: =IF(AX29=0,"","X") | AZ29: =IFERROR(FIND("População afetada/evacuada",consulta_completa__11[[#This Row],[13 - Ocorrências/Ambientes Atingidos]]),0) -> 0 | BA29: =IF(AZ29=0,"","X") | BB29: =IFERROR(FIND("Suspensão de abastecimento de água",consulta_completa__11[[#This Row],[13 - Ocorrências/Ambientes Atingidos]]),0) -> 0 | BC29: =IF(BB29=0,"","X") | BD29: =IFERROR(FIND("Rio/córrego",consulta_completa__11[[#This Row],[13 - Ocorrências/Ambientes Atingidos]]),0) -> 0 | BE29: =IF(BD29=0,"","X") | BF29: =IFERROR(FIND("Lago",consulta_completa__11[[#This Row],[13 - Ocorrências/Ambientes Atingidos]]),0) -> 0 | BG29: =IF(BF29=0,"","X") | BH29: =IFERROR(FIND("Mar",consulta_completa__11[[#This Row],[13 - Ocorrências/Ambientes Atingidos]]),0) -> 1 | BI29: =IF(BH29=0,"","X") -> X | BJ29: =IFERROR(FIND("Praia",consulta_completa__11[[#This Row],[13 - Ocorrências/Ambientes Atingidos]]),0) -> 0 | BK29: =IF(BJ29=0,"","X") | BL29: =IFERROR(FIND("Solo",consulta_completa__11[[#This Row],[13 - Ocorrências/Ambientes Atingidos]]),0) -> 0 | BM29: =IF(BL29=0,"","X") | BN29: =IFERROR(FIND("Águas subterrâneas",consulta_completa__11[[#This Row],[13 - Ocorrências/Ambientes Atingidos]]),0) -> 0 | BO29: =IF(BN29=0,"","X") | BP29: =IFERROR(FIND("Atmosfera",consulta_completa__11[[#This Row],[13 - Ocorrências/Ambientes Atingidos]]),0) -> 0 | BQ29: =IF(BP29=0,"","X") | BR29: =IFERROR(FIND("Flora",consulta_completa__11[[#This Row],[13 - Ocorrências/Ambientes Atingidos]]),0) -> 0 | BS29: =IF(BR29=0,"","X") | BT29: =IFERROR(FIND("Fauna",consulta_completa__11[[#This Row],[13 - Ocorrências/Ambientes Atingidos]]),0) -> 0 | BU29: =IF(BT29=0,"","X") | BV29: =IFERROR(FIND("UC federal",consulta_completa__11[[#This Row],[13 - Ocorrências/Ambientes Atingidos]]),0) -> 0 | BW29: =IF(BV29=0,"","X") | BX29: =IFERROR(FIND("UC estadual/municipal",consulta_completa__11[[#This Row],[13 - Ocorrências/Ambientes Atingidos]]),0) -> 0 | BY29: =IF(BX29=0,"","X") | BZ29: =IFERROR(FIND("Outro(s)",consulta_completa__11[[#This Row],[13 - Ocorrências/Ambientes Atingidos]]),0) -> 0 | CA29: =IF(BZ29=0,"","X") | CB29: =IFERROR(FIND("Sem dano",consulta_completa__11[[#This Row],[13 - Ocorrências/Ambientes Atingidos]]),0) -> 0 | CC29: =IF(CB29=0,"","X") | CD29: =IF(consulta_completa__11[[#This Row],[13 - Ocorrências/Ambientes Atingidos]]="","X","") | CE29: =IFERROR(FIND("IBAMA",consulta_completa__11[[#This Row],[14 - Inst. Atuando no Local]]),0) -> 0 | CF29: =IF(CE29=0,"","X") | CG29: =IFERROR(FIND("OEMA",consulta_completa__11[[#This Row],[14 - Inst. Atuando no Local]]),0) -> 0 | CH29: =IF(CG29=0,"","X") | CI29: =IFERROR(FIND("DEFESA CIVIL",consulta_completa__11[[#This Row],[14 - Inst. Atuando no Local]]),0) -> 0 | CJ29: =IF(CI29=0,"","X") | CK29: =IFERROR(FIND("CORPO DE BOMBEIROS",consulta_completa__11[[#This Row],[14 - Inst. Atuando no Local]]),0) -> 0 | CL29: =IF(CK29=0,"","X") | CM29: =IFERROR(FIND("POLÍCIA RODOVIÁRIA",consulta_completa__11[[#This Row],[14 - Inst. Atuando no Local]]),0) -> 0 | CN29: =IF(CM29=0,"","X") | CO29: =IFERROR(FIND("POLÍCIA MILITAR",consulta_completa__11[[#This Row],[14 - Inst. Atuando no Local]]),0) -> 0 | CP29: =IF(CO29=0,"","X") | CQ29: =IFERROR(FIND("POLÍCIA CIVIL",consulta_completa__11[[#This Row],[14 - Inst. Atuando no Local]]),0) -> 0 | CR29: =IF(CQ29=0,"","X") | CS29: =IFERROR(FIND("MARINHA DO BRASIL",consulta_completa__11[[#This Row],[14 - Inst. Atuando no Local]]),0) -> 0 | CT29: =IF(CS29=0,"","X") | CU29: =IFERROR(FIND("EMPRESA ESPECIALIZADA EM ATENDIMENTO",consulta_completa__11[[#This Row],[14 - Inst. Atuando no Local]]),0) -> 0 | CV29: =IF(CU29=0,"","X") | CW29: =IFERROR(FIND("IBAMA",consulta_completa__11[[#This Row],[14 - Inst. Atuando no Local]]),0) -> 0 | CX29: =IF(CW29=0,"","X") | CY29: =IF(consulta_completa__11[[#This Row],[14 - Inst. Atuando no Local]]="","X","") | CZ29: =IFERROR(FIND("OUTRA (S)",consulta_completa__11[[#This Row],[14 - Inst. Atuando no Local]]),0) -> 0 | DA29: =IF(CZ29=0,"","X") | DB29: =IF(AH$2="","",IF(AH$2="S","Sim",IF(AH$2="N","Não", IF(AH$2="I","Sem Informação")))) -> Sim | DC29: =IF(AI$2="","",IF(AI$2="S","Sim",IF(AI$2="N","Não", IF(AI$2="I","Sem Informação")))) -> Não | DD29: =IF(AJ$2="","",IF(AJ$2="S","Sim",IF(AJ$2="N","Não", IF(AJ$2="I","Sem Informação")))) -> Sim | DE29: =IF(AD29=1,"Federal",IF(AD29=2,"Estadual",IF(AD29=0,"Sem informação",""))) -> Federal
A30: 202511632424 | B30: 45669 | C30: Araxá | D30: MG | E30: Barragem | F30: Derramamento de líquidos | G30: ÁCIDO CLORÍDRICO | H30: 27 | I30: T | M30: Solo | N30: Outra(s) | O30: Órgão Estadual ou Municipal de Meio Ambiente | P30: Domingo | Q30: Vespertino | R30: Não | T30: R. Córrego da Mata, s/n, Araxá - MG, 38183-903 | U30: Conforme informado ao NEA, ocorreu retorno de produto no registro de adição de água no sistema, permitindo o vazamento de aproximadamente 27,0 ton de produto, o qual, em sua maior parte, ficou retido nas estruturas de contenção da empresa e foi encaminhado para as barragens de rejeito da empresa. Processo Sei1 02001.001573/2025-32 | V30: Acidente em unidade industrial envolvendo derramamento de produto químico. | AA30: A emprersa informou maior parte do produto ficou retido nas estruturas de contenção da empresa. | AB30: Cia Brasileira de Metalurgia e Mineração CBMM | AC30: 33131541000108 | AD30: 2 | AE30: A empresa afirma que estão sendo adotadas as medidas de limpeza e manutenção dos sistemas. (34) -3000 | AF30: Luis Sayão | AG30: 3436693000 | AH30: I | AI30: N | AJ30: S | AK30: Limpeza pela própia empresa. | AL30: PRODUTO: Ácido clorídrico | NÚMERO ONU: 1789| CLASSE DE RISCO: 8. | AM30: Mariana Rivetti Ribeiro De Carvalho | AN30: Ibama | AO30: Analista Ambiental | AP30: 31987239130 | AQ30: mariana.carvalho@ibama.gov.br | AX30: =IFERROR(FIND("Óbitos/feridos",consulta_completa__11[[#This Row],[13 - Ocorrências/Ambientes Atingidos]]),0) -> 0 | AY30: =IF(AX30=0,"","X") | AZ30: =IFERROR(FIND("População afetada/evacuada",consulta_completa__11[[#This Row],[13 - Ocorrências/Ambientes Atingidos]]),0) -> 0 | BA30: =IF(AZ30=0,"","X") | BB30: =IFERROR(FIND("Suspensão de abastecimento de água",consulta_completa__11[[#This Row],[13 - Ocorrências/Ambientes Atingidos]]),0) -> 0 | BC30: =IF(BB30=0,"","X") | BD30: =IFERROR(FIND("Rio/córrego",consulta_completa__11[[#This Row],[13 - Ocorrências/Ambientes Atingidos]]),0) -> 0 | BE30: =IF(BD30=0,"","X") | BF30: =IFERROR(FIND("Lago",consulta_completa__11[[#This Row],[13 - Ocorrências/Ambientes Atingidos]]),0) -> 0 | BG30: =IF(BF30=0,"","X") | BH30: =IFERROR(FIND("Mar",consulta_completa__11[[#This Row],[13 - Ocorrências/Ambientes Atingidos]]),0) -> 0 | BI30: =IF(BH30=0,"","X") | BJ30: =IFERROR(FIND("Praia",consulta_completa__11[[#This Row],[13 - Ocorrências/Ambientes Atingidos]]),0) -> 0 | BK30: =IF(BJ30=0,"","X") | BL30: =IFERROR(FIND("Solo",consulta_completa__11[[#This Row],[13 - Ocorrências/Ambientes Atingidos]]),0) -> 1 | BM30: =IF(BL30=0,"","X") -> X | BN30: =IFERROR(FIND("Águas subterrâneas",consulta_completa__11[[#This Row],[13 - Ocorrências/Ambientes Atingidos]]),0) -> 0 | BO30: =IF(BN30=0,"","X") | BP30: =IFERROR(FIND("Atmosfera",consulta_completa__11[[#This Row],[13 - Ocorrências/Ambientes Atingidos]]),0) -> 0 | BQ30: =IF(BP30=0,"","X") | BR30: =IFERROR(FIND("Flora",consulta_completa__11[[#This Row],[13 - Ocorrências/Ambientes Atingidos]]),0) -> 0 | BS30: =IF(BR30=0,"","X") | BT30: =IFERROR(FIND("Fauna",consulta_completa__11[[#This Row],[13 - Ocorrências/Ambientes Atingidos]]),0) -> 0 | BU30: =IF(BT30=0,"","X") | BV30: =IFERROR(FIND("UC federal",consulta_completa__11[[#This Row],[13 - Ocorrências/Ambientes Atingidos]]),0) -> 0 | BW30: =IF(BV30=0,"","X") | BX30: =IFERROR(FIND("UC estadual/municipal",consulta_completa__11[[#This Row],[13 - Ocorrências/Ambientes Atingidos]]),0) -> 0 | BY30: =IF(BX30=0,"","X") | BZ30: =IFERROR(FIND("Outro(s)",consulta_completa__11[[#This Row],[13 - Ocorrências/Ambientes Atingidos]]),0) -> 0 | CA30: =IF(BZ30=0,"","X") | CB30: =IFERROR(FIND("Sem dano",consulta_completa__11[[#This Row],[13 - Ocorrências/Ambientes Atingidos]]),0) -> 0 | CC30: =IF(CB30=0,"","X") | CD30: =IF(consulta_completa__11[[#This Row],[13 - Ocorrências/Ambientes Atingidos]]="","X","") | CE30: =IFERROR(FIND("IBAMA",consulta_completa__11[[#This Row],[14 - Inst. Atuando no Local]]),0) -> 0 | CF30: =IF(CE30=0,"","X") | CG30: =IFERROR(FIND("OEMA",consulta_completa__11[[#This Row],[14 - Inst. Atuando no Local]]),0) -> 0 | CH30: =IF(CG30=0,"","X") | CI30: =IFERROR(FIND("DEFESA CIVIL",consulta_completa__11[[#This Row],[14 - Inst. Atuando no Local]]),0) -> 0 | CJ30: =IF(CI30=0,"","X") | CK30: =IFERROR(FIND("CORPO DE BOMBEIROS",consulta_completa__11[[#This Row],[14 - Inst. Atuando no Local]]),0) -> 0 | CL30: =IF(CK30=0,"","X") | CM30: =IFERROR(FIND("POLÍCIA RODOVIÁRIA",consulta_completa__11[[#This Row],[14 - Inst. Atuando no Local]]),0) -> 0 | CN30: =IF(CM30=0,"","X") | CO30: =IFERROR(FIND("POLÍCIA MILITAR",consulta_completa__11[[#This Row],[14 - Inst. Atuando no Local]]),0) -> 0 | CP30: =IF(CO30=0,"","X") | CQ30: =IFERROR(FIND("POLÍCIA CIVIL",consulta_completa__11[[#This Row],[14 - Inst. Atuando no Local]]),0) -> 0 | CR30: =IF(CQ30=0,"","X") | CS30: =IFERROR(FIND("MARINHA DO BRASIL",consulta_completa__11[[#This Row],[14 - Inst. Atuando no Local]]),0) -> 0 | CT30: =IF(CS30=0,"","X") | CU30: =IFERROR(FIND("EMPRESA ESPECIALIZADA EM ATENDIMENTO",consulta_completa__11[[#This Row],[14 - Inst. Atuando no Local]]),0) -> 0 | CV30: =IF(CU30=0,"","X") | CW30: =IFERROR(FIND("IBAMA",consulta_completa__11[[#This Row],[14 - Inst. Atuando no Local]]),0) -> 0 | CX30: =IF(CW30=0,"","X") | CY30: =IF(consulta_completa__11[[#This Row],[14 - Inst. Atuando no Local]]="","X","") | CZ30: =IFERROR(FIND("OUTRA (S)",consulta_completa__11[[#This Row],[14 - Inst. Atuando no Local]]),0) -> 0 | DA30: =IF(CZ30=0,"","X") | DB30: =IF(AH$2="","",IF(AH$2="S","Sim",IF(AH$2="N","Não", IF(AH$2="I","Sem Informação")))) -> Sim | DC30: =IF(AI$2="","",IF(AI$2="S","Sim",IF(AI$2="N","Não", IF(AI$2="I","Sem Informação")))) -> Não | DD30: =IF(AJ$2="","",IF(AJ$2="S","Sim",IF(AJ$2="N","Não", IF(AJ$2="I","Sem Informação")))) -> Sim | DE30: =IF(AD30=1,"Federal",IF(AD30=2,"Estadual",IF(AD30=0,"Sem informação",""))) -> Estadual
A31: 202512721613 | B31: 45669 | C31: Esplanada | D31: BA | E31: Plataforma | F31: Derramamento de líquidos | G31: PETRÓLEO, CRU | H31: 0.0371 | I31: M3 | J31: água produzida | K31: 0.9629 | L31: M3 | M31: Solo | N31: Empresa especializada em atendimento | O31: Comunicado da empresa/responsável | P31: Domingo | Q31: Matutino | R31: Não | T31: Linha tronco do satélite FBM-B, Campo de Fazenda Bálsamo, Bacia do Recôncav | U31: Descarga significante de óleo Perda de contenção primária significante de óleo | V31: Descarga de 1m³ de emulsão oleosa (0,9629m³ água produzida e 0,0371m³ de óleo) por furo na linha tronco de produção do satélite em campo terrestre. O fluido vazado atingiu terreno natural no entorno da instalação. | Z31: Em investigação. | AA31: terreno natural no entorno da instalação | AB31: : PETRÓLEO BRASILEIRO S.A. - PETROBRAS | AC31: 33000167000101 | AD31: 2 | AE31: Equipes de limpeza e de manutenção | AH31: I | AI31: N | AJ31: S | AK31: Isolado e despressurizado o trecho. Acionadas equipes de limpeza e de manutenção. | AL31: BSW da emulsão oleosa: 96,29%. Este evento foi comunicado ao órgão ambiental estadual (INEMA) dentro do prazo de até 2h, por meio do Disque Meio Ambiente (telefone 71 0800 071 1400), sob o protocolo de nº 47773 às 09h56. | AM31: Gunther Barbosa | AN31: IBAMA | AO31: Analista Ambiental | AQ31: gunther.barbosa@ibama.gov.br | AT31: FAZENDA BÁLSAMO | AW31: Paralisada | AX31: =IFERROR(FIND("Óbitos/feridos",consulta_completa__11[[#This Row],[13 - Ocorrências/Ambientes Atingidos]]),0) -> 0 | AY31: =IF(AX31=0,"","X") | AZ31: =IFERROR(FIND("População afetada/evacuada",consulta_completa__11[[#This Row],[13 - Ocorrências/Ambientes Atingidos]]),0) -> 0 | BA31: =IF(AZ31=0,"","X") | BB31: =IFERROR(FIND("Suspensão de abastecimento de água",consulta_completa__11[[#This Row],[13 - Ocorrências/Ambientes Atingidos]]),0) -> 0 | BC31: =IF(BB31=0,"","X") | BD31: =IFERROR(FIND("Rio/córrego",consulta_completa__11[[#This Row],[13 - Ocorrências/Ambientes Atingidos]]),0) -> 0 | BE31: =IF(BD31=0,"","X") | BF31: =IFERROR(FIND("Lago",consulta_completa__11[[#This Row],[13 - Ocorrências/Ambientes Atingidos]]),0) -> 0 | BG31: =IF(BF31=0,"","X") | BH31: =IFERROR(FIND("Mar",consulta_completa__11[[#This Row],[13 - Ocorrências/Ambientes Atingidos]]),0) -> 0 | BI31: =IF(BH31=0,"","X") | BJ31: =IFERROR(FIND("Praia",consulta_completa__11[[#This Row],[13 - Ocorrências/Ambientes Atingidos]]),0) -> 0 | BK31: =IF(BJ31=0,"","X") | BL31: =IFERROR(FIND("Solo",consulta_completa__11[[#This Row],[13 - Ocorrências/Ambientes Atingidos]]),0) -> 1 | BM31: =IF(BL31=0,"","X") -> X | BN31: =IFERROR(FIND("Águas subterrâneas",consulta_completa__11[[#This Row],[13 - Ocorrências/Ambientes Atingidos]]),0) -> 0 | BO31: =IF(BN31=0,"","X") | BP31: =IFERROR(FIND("Atmosfera",consulta_completa__11[[#This Row],[13 - Ocorrências/Ambientes Atingidos]]),0) -> 0 | BQ31: =IF(BP31=0,"","X") | BR31: =IFERROR(FIND("Flora",consulta_completa__11[[#This Row],[13 - Ocorrências/Ambientes Atingidos]]),0) -> 0 | BS31: =IF(BR31=0,"","X") | BT31: =IFERROR(FIND("Fauna",consulta_completa__11[[#This Row],[13 - Ocorrências/Ambientes Atingidos]]),0) -> 0 | BU31: =IF(BT31=0,"","X") | BV31: =IFERROR(FIND("UC federal",consulta_completa__11[[#This Row],[13 - Ocorrências/Ambientes Atingidos]]),0) -> 0 | BW31: =IF(BV31=0,"","X") | BX31: =IFERROR(FIND("UC estadual/municipal",consulta_completa__11[[#This Row],[13 - Ocorrências/Ambientes Atingidos]]),0) -> 0 | BY31: =IF(BX31=0,"","X") | BZ31: =IFERROR(FIND("Outro(s)",consulta_completa__11[[#This Row],[13 - Ocorrências/Ambientes Atingidos]]),0) -> 0 | CA31: =IF(BZ31=0,"","X") | CB31: =IFERROR(FIND("Sem dano",consulta_completa__11[[#This Row],[13 - Ocorrências/Ambientes Atingidos]]),0) -> 0 | CC31: =IF(CB31=0,"","X") | CD31: =IF(consulta_completa__11[[#This Row],[13 - Ocorrências/Ambientes Atingidos]]="","X","") | CE31: =IFERROR(FIND("IBAMA",consulta_completa__11[[#This Row],[14 - Inst. Atuando no Local]]),0) -> 0 | CF31: =IF(CE31=0,"","X") | CG31: =IFERROR(FIND("OEMA",consulta_completa__11[[#This Row],[14 - Inst. Atuando no Local]]),0) -> 0 | CH31: =IF(CG31=0,"","X") | CI31: =IFERROR(FIND("DEFESA CIVIL",consulta_completa__11[[#This Row],[14 - Inst. Atuando no Local]]),0) -> 0 | CJ31: =IF(CI31=0,"","X") | CK31: =IFERROR(FIND("CORPO DE BOMBEIROS",consulta_completa__11[[#This Row],[14 - Inst. Atuando no Local]]),0) -> 0 | CL31: =IF(CK31=0,"","X") | CM31: =IFERROR(FIND("POLÍCIA RODOVIÁRIA",consulta_completa__11[[#This Row],[14 - Inst. Atuando no Local]]),0) -> 0 | CN31: =IF(CM31=0,"","X") | CO31: =IFERROR(FIND("POLÍCIA MILITAR",consulta_completa__11[[#This Row],[14 - Inst. Atuando no Local]]),0) -> 0 | CP31: =IF(CO31=0,"","X") | CQ31: =IFERROR(FIND("POLÍCIA CIVIL",consulta_completa__11[[#This Row],[14 - Inst. Atuando no Local]]),0) -> 0 | CR31: =IF(CQ31=0,"","X") | CS31: =IFERROR(FIND("MARINHA DO BRASIL",consulta_completa__11[[#This Row],[14 - Inst. Atuando no Local]]),0) -> 0 | CT31: =IF(CS31=0,"","X") | CU31: =IFERROR(FIND("EMPRESA ESPECIALIZADA EM ATENDIMENTO",consulta_completa__11[[#This Row],[14 - Inst. Atuando no Local]]),0) -> 0 | CV31: =IF(CU31=0,"","X") | CW31: =IFERROR(FIND("IBAMA",consulta_completa__11[[#This Row],[14 - Inst. Atuando no Local]]),0) -> 0 | CX31: =IF(CW31=0,"","X") | CY31: =IF(consulta_completa__11[[#This Row],[14 - Inst. Atuando no Local]]="","X","") | CZ31: =IFERROR(FIND("OUTRA (S)",consulta_completa__11[[#This Row],[14 - Inst. Atuando no Local]]),0) -> 0 | DA31: =IF(CZ31=0,"","X") | DB31: =IF(AH$2="","",IF(AH$2="S","Sim",IF(AH$2="N","Não", IF(AH$2="I","Sem Informação")))) -> Sim | DC31: =IF(AI$2="","",IF(AI$2="S","Sim",IF(AI$2="N","Não", IF(AI$2="I","Sem Informação")))) -> Não | DD31: =IF(AJ$2="","",IF(AJ$2="S","Sim",IF(AJ$2="N","Não", IF(AJ$2="I","Sem Informação")))) -> Sim | DE31: =IF(AD31=1,"Federal",IF(AD31=2,"Estadual",IF(AD31=0,"Sem informação",""))) -> Estadual
A32: 202511514406 | B32: 45670 | C32: null | D32: null | E32: Outro(s) | F32: Derramamento de líquidos | J32: fluido hidráulico | K32: 0.08 | L32: M3 | M32: Mar | N32: Outra(s) | P32: Segunda | Q32: Noturno | R32: Não | S32: Santos | T32: Campo de Búzios, Bacia de Santos | U32: Poço 8-BUZ-16-RJS. Processo Sei! 02001.001414/2025-38 | V32: Observado expurgo de fluido translucido da válvula de alívio da linha de retorno do Módulo de Controle Submarino do poço. | Z32: Em investigação | AB32: Petrobras | AC32: 33000167000292 | AD32: 1 | AE32: Petrobras | AH32: S | AI32: N | AJ32: S | AK32: %u2022 Mantida a Injeção paralisada no poço BUZ 16 %u2022 Envio de barco para Monitoramento e Inspeção do Poço, com alternância de atuadores buscando a origem do vazamento. | AL32: Não estávamos com leitura no flowmeter de LP, portanto o volume vazado estava abaixo da mínima vazão de leitura do flowmeter, que no modelo da Aker é de 20L/h. O escape era bem pequeno, contudo para efeito de cálculo, pode-se considerar o a vazão de 20L/h, sendo muito criterioso, visto que a vazão observada era bem pequena. A operação durou cerca de 4 horas, sendo então considerado um volume de 80L durante a operação. O vazamento não cessou pelo retorno ao final da operação. Volume: 0,08 m3 Área atingida: Mar territorial Nome comercial: TRANSAQUA DW; Composição química: Etileno Glicol e aditivos em solução aquosa; Classificação ONU/IMDG: Este produto não é classificado como perigoso para transporte. Comunicado pelo CAEME UN-BUZ 2970. | AM32: PETRLEO BRASILEIRO S/A - PETROBRAS | AQ32: giselletinoco@petrobras.com.br | AX32: =IFERROR(FIND("Óbitos/feridos",consulta_completa__11[[#This Row],[13 - Ocorrências/Ambientes Atingidos]]),0) -> 0 | AY32: =IF(AX32=0,"","X") | AZ32: =IFERROR(FIND("População afetada/evacuada",consulta_completa__11[[#This Row],[13 - Ocorrências/Ambientes Atingidos]]),0) -> 0 | BA32: =IF(AZ32=0,"","X") | BB32: =IFERROR(FIND("Suspensão de abastecimento de água",consulta_completa__11[[#This Row],[13 - Ocorrências/Ambientes Atingidos]]),0) -> 0 | BC32: =IF(BB32=0,"","X") | BD32: =IFERROR(FIND("Rio/córrego",consulta_completa__11[[#This Row],[13 - Ocorrências/Ambientes Atingidos]]),0) -> 0 | BE32: =IF(BD32=0,"","X") | BF32: =IFERROR(FIND("Lago",consulta_completa__11[[#This Row],[13 - Ocorrências/Ambientes Atingidos]]),0) -> 0 | BG32: =IF(BF32=0,"","X") | BH32: =IFERROR(FIND("Mar",consulta_completa__11[[#This Row],[13 - Ocorrências/Ambientes Atingidos]]),0) -> 1 | BI32: =IF(BH32=0,"","X") -> X | BJ32: =IFERROR(FIND("Praia",consulta_completa__11[[#This Row],[13 - Ocorrências/Ambientes Atingidos]]),0) -> 0 | BK32: =IF(BJ32=0,"","X") | BL32: =IFERROR(FIND("Solo",consulta_completa__11[[#This Row],[13 - Ocorrências/Ambientes Atingidos]]),0) -> 0 | BM32: =IF(BL32=0,"","X") | BN32: =IFERROR(FIND("Águas subterrâneas",consulta_completa__11[[#This Row],[13 - Ocorrências/Ambientes Atingidos]]),0) -> 0 | BO32: =IF(BN32=0,"","X") | BP32: =IFERROR(FIND("Atmosfera",consulta_completa__11[[#This Row],[13 - Ocorrências/Ambientes Atingidos]]),0) -> 0 | BQ32: =IF(BP32=0,"","X") | BR32: =IFERROR(FIND("Flora",consulta_completa__11[[#This Row],[13 - Ocorrências/Ambientes Atingidos]]),0) -> 0 | BS32: =IF(BR32=0,"","X") | BT32: =IFERROR(FIND("Fauna",consulta_completa__11[[#This Row],[13 - Ocorrências/Ambientes Atingidos]]),0) -> 0 | BU32: =IF(BT32=0,"","X") | BV32: =IFERROR(FIND("UC federal",consulta_completa__11[[#This Row],[13 - Ocorrências/Ambientes Atingidos]]),0) -> 0 | BW32: =IF(BV32=0,"","X") | BX32: =IFERROR(FIND("UC estadual/municipal",consulta_completa__11[[#This Row],[13 - Ocorrências/Ambientes Atingidos]]),0) -> 0 | BY32: =IF(BX32=0,"","X") | BZ32: =IFERROR(FIND("Outro(s)",consulta_completa__11[[#This Row],[13 - Ocorrências/Ambientes Atingidos]]),0) -> 0 | CA32: =IF(BZ32=0,"","X") | CB32: =IFERROR(FIND("Sem dano",consulta_completa__11[[#This Row],[13 - Ocorrências/Ambientes Atingidos]]),0) -> 0 | CC32: =IF(CB32=0,"","X") | CD32: =IF(consulta_completa__11[[#This Row],[13 - Ocorrências/Ambientes Atingidos]]="","X","") | CE32: =IFERROR(FIND("IBAMA",consulta_completa__11[[#This Row],[14 - Inst. Atuando no Local]]),0) -> 0 | CF32: =IF(CE32=0,"","X") | CG32: =IFERROR(FIND("OEMA",consulta_completa__11[[#This Row],[14 - Inst. Atuando no Local]]),0) -> 0 | CH32: =IF(CG32=0,"","X") | CI32: =IFERROR(FIND("DEFESA CIVIL",consulta_completa__11[[#This Row],[14 - Inst. Atuando no Local]]),0) -> 0 | CJ32: =IF(CI32=0,"","X") | CK32: =IFERROR(FIND("CORPO DE BOMBEIROS",consulta_completa__11[[#This Row],[14 - Inst. Atuando no Local]]),0) -> 0 | CL32: =IF(CK32=0,"","X") | CM32: =IFERROR(FIND("POLÍCIA RODOVIÁRIA",consulta_completa__11[[#This Row],[14 - Inst. Atuando no Local]]),0) -> 0 | CN32: =IF(CM32=0,"","X") | CO32: =IFERROR(FIND("POLÍCIA MILITAR",consulta_completa__11[[#This Row],[14 - Inst. Atuando no Local]]),0) -> 0 | CP32: =IF(CO32=0,"","X") | CQ32: =IFERROR(FIND("POLÍCIA CIVIL",consulta_completa__11[[#This Row],[14 - Inst. Atuando no Local]]),0) -> 0 | CR32: =IF(CQ32=0,"","X") | CS32: =IFERROR(FIND("MARINHA DO BRASIL",consulta_completa__11[[#This Row],[14 - Inst. Atuando no Local]]),0) -> 0 | CT32: =IF(CS32=0,"","X") | CU32: =IFERROR(FIND("EMPRESA ESPECIALIZADA EM ATENDIMENTO",consulta_completa__11[[#This Row],[14 - Inst. Atuando no Local]]),0) -> 0 | CV32: =IF(CU32=0,"","X") | CW32: =IFERROR(FIND("IBAMA",consulta_completa__11[[#This Row],[14 - Inst. Atuando no Local]]),0) -> 0 | CX32: =IF(CW32=0,"","X") | CY32: =IF(consulta_completa__11[[#This Row],[14 - Inst. Atuando no Local]]="","X","") | CZ32: =IFERROR(FIND("OUTRA (S)",consulta_completa__11[[#This Row],[14 - Inst. Atuando no Local]]),0) -> 0 | DA32: =IF(CZ32=0,"","X") | DB32: =IF(AH$2="","",IF(AH$2="S","Sim",IF(AH$2="N","Não", IF(AH$2="I","Sem Informação")))) -> Sim | DC32: =IF(AI$2="","",IF(AI$2="S","Sim",IF(AI$2="N","Não", IF(AI$2="I","Sem Informação")))) -> Não | DD32: =IF(AJ$2="","",IF(AJ$2="S","Sim",IF(AJ$2="N","Não", IF(AJ$2="I","Sem Informação")))) -> Sim | DE32: =IF(AD32=1,"Federal",IF(AD32=2,"Estadual",IF(AD32=0,"Sem informação",""))) -> Federal
A33: 202511539610 | B33: 45670 | C33: null | D33: null | E33: Plataforma | F33: Derramamento de líquidos | J33: Água; Petroleo | K33: 0.9; 0.1 | L33: M3; M3 | M33: Mar | N33: Outra(s) | O33: Outra(s) fonte(s) | P33: Segunda | Q33: Matutino | R33: Não | S33: Campos | T33: Campo de Marlim leste - Bacia de Campos. | U33: [PETROBRAS 53]: Durante sobrevoo de monitoramento ambiental, foi detectada uma feição conectada a plataforma (sentido de proa da unidade). No momento do avistamento o descarte de água produzida encontrava-se fechada (fechada às 13/01/2025 7h27). Causa provável: Falha no LIT-5336014A (Controle de nível) do TQ-533603-A (tanque de drenagem aberta de hidrocarbonetos) com transbordamento do tanque de costado. Em investigação. Processo Sei! 02001.001473/2025-14. | V33: Volume de descarga estimada de 1,0 m3 de água oleosa, sendo 0,1 m3 de óleo e 0,9 m3 de água. | Z33: Falha no LIT-5336014A (Controle de nível) do TQ-533603-A (tanque de drenagem aberta de hidrocarbonetos) com transbordamento do tanque de costado. Em investigação. | AB33: PETROBRAS | AC33: 33000167100750 | AD33: 1 | AE33: PETROBRAS | AH33: S | AI33: S | AJ33: S | AK33: Acionado o PEVO através da CAE - Central de Atendimento a Emergência; Mobilizado as embarcações oil recovery Mar Limpo IV e Jim O Brien; e realizado sobrevoo para monitoramento ambiental. | AL33: - Volume de descarga estimada de 1,0 m3 de água oleosa, sendo 0,1 m3 de óleo e 0,9 m3 de água. - Área atingida: Mar. - O tanque TQ-533601A recebe tomadas de coleta de amostras de forma rotineira e não contínua, além de bacia de contenção de equipamentos. - O TQ-533601-A não recebe descarte de água produzida. - Não ocorreu chuva nem acionamento de ADV na região drenada. - O término do incidente corresponde ao término das ações de resposta (em andamento). O controle da fonte ocorreu no momento da primeira observação. - Situação normalizada. O LIT-5336014A foi manutenido. | AM33: PETROBRAS - PETROLEO BRASILEIRO S.A. | AQ33: crisguerreiro@petrobras.com.br | AT33: P-53 | AU33: ÁGUA OLEOSA | AV33: 10000000000 | AW33: Paralisada | AX33: =IFERROR(FIND("Óbitos/feridos",consulta_completa__11[[#This Row],[13 - Ocorrências/Ambientes Atingidos]]),0) -> 0 | AY33: =IF(AX33=0,"","X") | AZ33: =IFERROR(FIND("População afetada/evacuada",consulta_completa__11[[#This Row],[13 - Ocorrências/Ambientes Atingidos]]),0) -> 0 | BA33: =IF(AZ33=0,"","X") | BB33: =IFERROR(FIND("Suspensão de abastecimento de água",consulta_completa__11[[#This Row],[13 - Ocorrências/Ambientes Atingidos]]),0) -> 0 | BC33: =IF(BB33=0,"","X") | BD33: =IFERROR(FIND("Rio/córrego",consulta_completa__11[[#This Row],[13 - Ocorrências/Ambientes Atingidos]]),0) -> 0 | BE33: =IF(BD33=0,"","X") | BF33: =IFERROR(FIND("Lago",consulta_completa__11[[#This Row],[13 - Ocorrências/Ambientes Atingidos]]),0) -> 0 | BG33: =IF(BF33=0,"","X") | BH33: =IFERROR(FIND("Mar",consulta_completa__11[[#This Row],[13 - Ocorrências/Ambientes Atingidos]]),0) -> 1 | BI33: =IF(BH33=0,"","X") -> X | BJ33: =IFERROR(FIND("Praia",consulta_completa__11[[#This Row],[13 - Ocorrências/Ambientes Atingidos]]),0) -> 0 | BK33: =IF(BJ33=0,"","X") | BL33: =IFERROR(FIND("Solo",consulta_completa__11[[#This Row],[13 - Ocorrências/Ambientes Atingidos]]),0) -> 0 | BM33: =IF(BL33=0,"","X") | BN33: =IFERROR(FIND("Águas subterrâneas",consulta_completa__11[[#This Row],[13 - Ocorrências/Ambientes Atingidos]]),0) -> 0 | BO33: =IF(BN33=0,"","X") | BP33: =IFERROR(FIND("Atmosfera",consulta_completa__11[[#This Row],[13 - Ocorrências/Ambientes Atingidos]]),0) -> 0 | BQ33: =IF(BP33=0,"","X") | BR33: =IFERROR(FIND("Flora",consulta_completa__11[[#This Row],[13 - Ocorrências/Ambientes Atingidos]]),0) -> 0 | BS33: =IF(BR33=0,"","X") | BT33: =IFERROR(FIND("Fauna",consulta_completa__11[[#This Row],[13 - Ocorrências/Ambientes Atingidos]]),0) -> 0 | BU33: =IF(BT33=0,"","X") | BV33: =IFERROR(FIND("UC federal",consulta_completa__11[[#This Row],[13 - Ocorrências/Ambientes Atingidos]]),0) -> 0 | BW33: =IF(BV33=0,"","X") | BX33: =IFERROR(FIND("UC estadual/municipal",consulta_completa__11[[#This Row],[13 - Ocorrências/Ambientes Atingidos]]),0) -> 0 | BY33: =IF(BX33=0,"","X") | BZ33: =IFERROR(FIND("Outro(s)",consulta_completa__11[[#This Row],[13 - Ocorrências/Ambientes Atingidos]]),0) -> 0 | CA33: =IF(BZ33=0,"","X") | CB33: =IFERROR(FIND("Sem dano",consulta_completa__11[[#This Row],[13 - Ocorrências/Ambientes Atingidos]]),0) -> 0 | CC33: =IF(CB33=0,"","X") | CD33: =IF(consulta_completa__11[[#This Row],[13 - Ocorrências/Ambientes Atingidos]]="","X","") | CE33: =IFERROR(FIND("IBAMA",consulta_completa__11[[#This Row],[14 - Inst. Atuando no Local]]),0) -> 0 | CF33: =IF(CE33=0,"","X") | CG33: =IFERROR(FIND("OEMA",consulta_completa__11[[#This Row],[14 - Inst. Atuando no Local]]),0) -> 0 | CH33: =IF(CG33=0,"","X") | CI33: =IFERROR(FIND("DEFESA CIVIL",consulta_completa__11[[#This Row],[14 - Inst. Atuando no Local]]),0) -> 0 | CJ33: =IF(CI33=0,"","X") | CK33: =IFERROR(FIND("CORPO DE BOMBEIROS",consulta_completa__11[[#This Row],[14 - Inst. Atuando no Local]]),0) -> 0 | CL33: =IF(CK33=0,"","X") | CM33: =IFERROR(FIND("POLÍCIA RODOVIÁRIA",consulta_completa__11[[#This Row],[14 - Inst. Atuando no Local]]),0) -> 0 | CN33: =IF(CM33=0,"","X") | CO33: =IFERROR(FIND("POLÍCIA MILITAR",consulta_completa__11[[#This Row],[14 - Inst. Atuando no Local]]),0) -> 0 | CP33: =IF(CO33=0,"","X") | CQ33: =IFERROR(FIND("POLÍCIA CIVIL",consulta_completa__11[[#This Row],[14 - Inst. Atuando no Local]]),0) -> 0 | CR33: =IF(CQ33=0,"","X") | CS33: =IFERROR(FIND("MARINHA DO BRASIL",consulta_completa__11[[#This Row],[14 - Inst. Atuando no Local]]),0) -> 0 | CT33: =IF(CS33=0,"","X") | CU33: =IFERROR(FIND("EMPRESA ESPECIALIZADA EM ATENDIMENTO",consulta_completa__11[[#This Row],[14 - Inst. Atuando no Local]]),0) -> 0 | CV33: =IF(CU33=0,"","X") | CW33: =IFERROR(FIND("IBAMA",consulta_completa__11[[#This Row],[14 - Inst. Atuando no Local]]),0) -> 0 | CX33: =IF(CW33=0,"","X") | CY33: =IF(consulta_completa__11[[#This Row],[14 - Inst. Atuando no Local]]="","X","") | CZ33: =IFERROR(FIND("OUTRA (S)",consulta_completa__11[[#This Row],[14 - Inst. Atuando no Local]]),0) -> 0 | DA33: =IF(CZ33=0,"","X") | DB33: =IF(AH$2="","",IF(AH$2="S","Sim",IF(AH$2="N","Não", IF(AH$2="I","Sem Informação")))) -> Sim | DC33: =IF(AI$2="","",IF(AI$2="S","Sim",IF(AI$2="N","Não", IF(AI$2="I","Sem Informação")))) -> Não | DD33: =IF(AJ$2="","",IF(AJ$2="S","Sim",IF(AJ$2="N","Não", IF(AJ$2="I","Sem Informação")))) -> Sim | DE33: =IF(AD33=1,"Federal",IF(AD33=2,"Estadual",IF(AD33=0,"Sem informação",""))) -> Federal
A34: 202511550405 | B34: 45670 | C34: null | D34: null | E34: Outro(s) | F34: Derramamento de líquidos | J34: Petroleo | K34: 0.0005 | L34: M3 | M34: Mar | N34: Outra(s) | O34: Outra(s) fonte(s) | P34: Segunda | Q34: Vespertino | R34: Não | S34: Santos | T34: Campo de Búzios - Bacia de Santos. | U34: [NS-55 (WEST JUPITER) em operação no poço 7-BUZ-81D-RJS]: Durante a retirada do conjunto de workover ao chegar à superfície foi constatada uma mancha escura no moon pool, de dimensões equivalentes estimadas em área de 2,2 m x 4,6 m e espessura de 50 micrometros (Protocolo de Bonn: cores escuras descontínuas). Processo Sei! 02001.001505/2025-73. | V34: Óleo - 0,0005 m3. | Z34: Limpeza insuficiente do HCR (High Collapse Resistance) antes da desconexão do conjunto de workover da ANM (árvore de natal molhada). | AB34: PETROBRAS | AC34: 33000167000292 | AD34: 1 | AE34: PETROBRAS | AH34: S | AI34: N | AJ34: S | AK34: Efetuada tentativa de coletar amostra, através de balde e corda, sem sucesso. Efetuada limpeza da área do moon pool com kit SOPEP, não sendo possível extrair amostra para análise. Circulado 18,5 bbl de água do mar no sentido da coluna de DPR (Drill Pipe Riser) para HCR (High Collapse Resistance) para limpeza adicional do sistema. Coletado fluido do retorno para análise e constatado tratar-se de mistura de água com resíduo oleoso. | AL34: [1] Volume descarregado: 0,0005 m3 de óleo, estimado baseado na avaliação visual da área da mancha (2,2 m x 4,6 m) e espessura baseada no Protocolo de Bonn (0,5 micrometros) com coloração escura descontínua (50.000-200.000 Litros/Km2); [2] Área atingida: mar. | AM34: PETRLEO BRASILEIRO S/A - PETROBRAS | AQ34: giselletinoco@petrobras.com.br | AS34: NS-55 (WEST JUPITER) | AU34: petróleo | AV34: 5000000 | AW34: Paralisada | AX34: =IFERROR(FIND("Óbitos/feridos",consulta_completa__11[[#This Row],[13 - Ocorrências/Ambientes Atingidos]]),0) -> 0 | AY34: =IF(AX34=0,"","X") | AZ34: =IFERROR(FIND("População afetada/evacuada",consulta_completa__11[[#This Row],[13 - Ocorrências/Ambientes Atingidos]]),0) -> 0 | BA34: =IF(AZ34=0,"","X") | BB34: =IFERROR(FIND("Suspensão de abastecimento de água",consulta_completa__11[[#This Row],[13 - Ocorrências/Ambientes Atingidos]]),0) -> 0 | BC34: =IF(BB34=0,"","X") | BD34: =IFERROR(FIND("Rio/córrego",consulta_completa__11[[#This Row],[13 - Ocorrências/Ambientes Atingidos]]),0) -> 0 | BE34: =IF(BD34=0,"","X") | BF34: =IFERROR(FIND("Lago",consulta_completa__11[[#This Row],[13 - Ocorrências/Ambientes Atingidos]]),0) -> 0 | BG34: =IF(BF34=0,"","X") | BH34: =IFERROR(FIND("Mar",consulta_completa__11[[#This Row],[13 - Ocorrências/Ambientes Atingidos]]),0) -> 1 | BI34: =IF(BH34=0,"","X") -> X | BJ34: =IFERROR(FIND("Praia",consulta_completa__11[[#This Row],[13 - Ocorrências/Ambientes Atingidos]]),0) -> 0 | BK34: =IF(BJ34=0,"","X") | BL34: =IFERROR(FIND("Solo",consulta_completa__11[[#This Row],[13 - Ocorrências/Ambientes Atingidos]]),0) -> 0 | BM34: =IF(BL34=0,"","X") | BN34: =IFERROR(FIND("Águas subterrâneas",consulta_completa__11[[#This Row],[13 - Ocorrências/Ambientes Atingidos]]),0) -> 0 | BO34: =IF(BN34=0,"","X") | BP34: =IFERROR(FIND("Atmosfera",consulta_completa__11[[#This Row],[13 - Ocorrências/Ambientes Atingidos]]),0) -> 0 | BQ34: =IF(BP34=0,"","X") | BR34: =IFERROR(FIND("Flora",consulta_completa__11[[#This Row],[13 - Ocorrências/Ambientes Atingidos]]),0) -> 0 | BS34: =IF(BR34=0,"","X") | BT34: =IFERROR(FIND("Fauna",consulta_completa__11[[#This Row],[13 - Ocorrências/Ambientes Atingidos]]),0) -> 0 | BU34: =IF(BT34=0,"","X") | BV34: =IFERROR(FIND("UC federal",consulta_completa__11[[#This Row],[13 - Ocorrências/Ambientes Atingidos]]),0) -> 0 | BW34: =IF(BV34=0,"","X") | BX34: =IFERROR(FIND("UC estadual/municipal",consulta_completa__11[[#This Row],[13 - Ocorrências/Ambientes Atingidos]]),0) -> 0 | BY34: =IF(BX34=0,"","X") | BZ34: =IFERROR(FIND("Outro(s)",consulta_completa__11[[#This Row],[13 - Ocorrências/Ambientes Atingidos]]),0) -> 0 | CA34: =IF(BZ34=0,"","X") | CB34: =IFERROR(FIND("Sem dano",consulta_completa__11[[#This Row],[13 - Ocorrências/Ambientes Atingidos]]),0) -> 0 | CC34: =IF(CB34=0,"","X") | CD34: =IF(consulta_completa__11[[#This Row],[13 - Ocorrências/Ambientes Atingidos]]="","X","") | CE34: =IFERROR(FIND("IBAMA",consulta_completa__11[[#This Row],[14 - Inst. Atuando no Local]]),0) -> 0 | CF34: =IF(CE34=0,"","X") | CG34: =IFERROR(FIND("OEMA",consulta_completa__11[[#This Row],[14 - Inst. Atuando no Local]]),0) -> 0 | CH34: =IF(CG34=0,"","X") | CI34: =IFERROR(FIND("DEFESA CIVIL",consulta_completa__11[[#This Row],[14 - Inst. Atuando no Local]]),0) -> 0 | CJ34: =IF(CI34=0,"","X") | CK34: =IFERROR(FIND("CORPO DE BOMBEIROS",consulta_completa__11[[#This Row],[14 - Inst. Atuando no Local]]),0) -> 0 | CL34: =IF(CK34=0,"","X") | CM34: =IFERROR(FIND("POLÍCIA RODOVIÁRIA",consulta_completa__11[[#This Row],[14 - Inst. Atuando no Local]]),0) -> 0 | CN34: =IF(CM34=0,"","X") | CO34: =IFERROR(FIND("POLÍCIA MILITAR",consulta_completa__11[[#This Row],[14 - Inst. Atuando no Local]]),0) -> 0 | CP34: =IF(CO34=0,"","X") | CQ34: =IFERROR(FIND("POLÍCIA CIVIL",consulta_completa__11[[#This Row],[14 - Inst. Atuando no Local]]),0) -> 0 | CR34: =IF(CQ34=0,"","X") | CS34: =IFERROR(FIND("MARINHA DO BRASIL",consulta_completa__11[[#This Row],[14 - Inst. Atuando no Local]]),0) -> 0 | CT34: =IF(CS34=0,"","X") | CU34: =IFERROR(FIND("EMPRESA ESPECIALIZADA EM ATENDIMENTO",consulta_completa__11[[#This Row],[14 - Inst. Atuando no Local]]),0) -> 0 | CV34: =IF(CU34=0,"","X") | CW34: =IFERROR(FIND("IBAMA",consulta_completa__11[[#This Row],[14 - Inst. Atuando no Local]]),0) -> 0 | CX34: =IF(CW34=0,"","X") | CY34: =IF(consulta_completa__11[[#This Row],[14 - Inst. Atuando no Local]]="","X","") | CZ34: =IFERROR(FIND("OUTRA (S)",consulta_completa__11[[#This Row],[14 - Inst. Atuando no Local]]),0) -> 0 | DA34: =IF(CZ34=0,"","X") | DB34: =IF(AH$2="","",IF(AH$2="S","Sim",IF(AH$2="N","Não", IF(AH$2="I","Sem Informação")))) -> Sim | DC34: =IF(AI$2="","",IF(AI$2="S","Sim",IF(AI$2="N","Não", IF(AI$2="I","Sem Informação")))) -> Não | DD34: =IF(AJ$2="","",IF(AJ$2="S","Sim",IF(AJ$2="N","Não", IF(AJ$2="I","Sem Informação")))) -> Sim | DE34: =IF(AD34=1,"Federal",IF(AD34=2,"Estadual",IF(AD34=0,"Sem informação",""))) -> Federal
